Workbook
Name ABC: #REF!
Name scn_A_cogs_up: Scenario_Analysis!$Y$2
Name scn_B_returns_up: Scenario_Analysis!$Y$3
Name scn_C_price_down: Scenario_Analysis!$Y$4

Sheet Raw_Data
A2: sku_rank | B2: product_id | C2: category | D2: units_sold | E2: order_count | F2: gross_revenue | G2: cogs | H2: storage_cost | I2: fulfillment_cost | J2: freight_cost | K2: return_loss | L2: total_cost_sql_check | M2: net_profit_sql_check | N2: net_margin_pct_sql_check | O2: avg_review_score | P2: decision
A3: 1 | B3: bb50f2e236e5eea0100680137654686c | C3: health_beauty | D3: 195 | E3: 187 | F3: 63885 | G3: 26831.7 | H3: 195 | I3: 748 | J3: 3721.1 | K3: 70.2 | L3: 31566 | M3: 32319 | N3: 0.5059 | O3: 4.22 | P3: SCALE
A4: 2 | B4: 6cdd53843498f92890544667809f1595 | C4: health_beauty | D4: 156 | E4: 151 | F4: 54730.2 | G4: 22986.68 | H4: 156 | I4: 604 | J4: 4363.79 | K4: 56.16 | L4: 28166.63 | M4: 26563.57 | N4: 0.4854 | O4: 4.32 | P4: SCALE
A5: 3 | B5: d6160fb7873f184099d9bc95e30376af | C5: computers | D5: 35 | E5: 35 | F5: 48899.34 | G5: 27872.62 | H5: 78.75 | I5: 350 | J5: 1426.84 | K5: 31.5 | L5: 29759.71 | M5: 19139.63 | N5: 0.3914 | O5: 4.57 | P5: SCALE
A6: 4 | B6: d1c427060a0f73f6b889a5c7c61f2ac4 | C6: computers_accessories | D6: 341 | E6: 321 | F6: 46916.51 | G6: 26742.41 | H6: 767.25 | I6: 3210 | J6: 13680.78 | K6: 306.9 | L6: 44707.34 | M6: 2209.17 | N6: 0.0471 | O6: 4.2 | P6: EXIT
A7: 5 | B7: 99a4788cb24856965c36a24e339b6058 | C7: bed_bath_table | D7: 487 | E7: 466 | F7: 42938.66 | G7: 19322.4 | H7: 1095.75 | I7: 3029 | J7: 8024.94 | K7: 175.32 | L7: 31647.41 | M7: 11291.25 | N7: 0.263 | O7: 3.9 | P7: OPTIMIZE
A8: 6 | B8: 3dd2a17168ec895c781a9191c1e95ad7 | C8: computers_accessories | D8: 274 | E8: 255 | F8: 41082.6 | G8: 23417.08 | H8: 616.5 | I8: 2550 | J8: 7129.62 | K8: 246.6 | L8: 33959.8 | M8: 7122.8 | N8: 0.1734 | O8: 4.21 | P8: OPTIMIZE
A9: 7 | B9: 25c38557cf793876c5abdd5931f922db | C9: baby | D9: 38 | E9: 38 | F9: 38907.32 | G9: 16341.07 | H9: 38 | I9: 152 | J9: 1404.63 | K9: 13.68 | L9: 17949.38 | M9: 20957.94 | N9: 0.5387 | O9: 2.68 | P9: EXIT
A10: 8 | B10: 5f504b3a1c75b73d6151be81eb05bdc9 | C10: cool_stuff | D10: 63 | E10: 63 | F10: 37733.9 | G10: 16980.26 | H10: 63 | I10: 252 | J10: 3991.91 | K10: 22.68 | L10: 21309.85 | M10: 16424.05 | N10: 0.4353 | O10: 4.56 | P10: SCALE
A11: 9 | B11: 53b36df67ebb7c41585e8d54d6772e08 | C11: watches_gifts | D11: 323 | E11: 306 | F11: 37683.42 | G11: 15827.04 | H11: 323 | I11: 1224 | J11: 2274.51 | K11: 116.28 | L11: 19764.83 | M11: 17918.59 | N11: 0.4755 | O11: 4.19 | P11: SCALE
A12: 10 | B12: aca2eb7d00ea1a7b8ebd4e68314663af | C12: furniture_decor | D12: 527 | E12: 431 | F12: 37608.9 | G12: 16924.01 | H12: 2635 | I12: 4310 | J12: 7211.86 | K12: 189.72 | L12: 31270.59 | M12: 6338.31 | N12: 0.1685 | O12: 4.02 | P12: OPTIMIZE
A13: 11 | B13: e0d64dcfaa3b6db5c54ca298ae101d05 | C13: watches_gifts | D13: 194 | E13: 194 | F13: 31786.82 | G13: 13350.46 | H13: 194 | I13: 776 | J13: 3557.27 | K13: 69.84 | L13: 17947.57 | M13: 13839.25 | N13: 0.4354 | O13: 3.78 | P13: OPTIMIZE
A14: 12 | B14: d285360f29ac7fd97640bf0baef03de0 | C14: watches_gifts | D14: 123 | E14: 122 | F14: 31623.81 | G14: 13282 | H14: 123 | I14: 488 | J14: 1983.76 | K14: 44.28 | L14: 15921.04 | M14: 15702.77 | N14: 0.4965 | O14: 3.72 | P14: OPTIMIZE
... A402: 400 | B402: 6902c1962dd19d540807d0ab8fade5c6 | C402: watches_gifts | D402: 1 | E402: 1 | F402: 3999.9 | G402: 1679.96 | H402: 1 | I402: 4 | J402: 17.01 | K402: 0.36 | L402: 1702.33 | M402: 2297.57 | N402: 0.5744 | O402: 5 | P402: SCALE

Sheet Profitability_Model
A2: product_id | B2: category | C2: gross_revenue | D2: return_loss | E2: net_revenue_after_returns | F2: cogs | G2: operating_costs | H2: net_profit | I2: gross_margin_pct | J2: net_margin_pct | K2: break_even_price | L2: decision
A3: =tbl_raw[[#This Row],[product_id]] -> bb50f2e236e5eea0100680137654686c | B3: =tbl_raw[[#This Row],[category]] -> health_beauty | C3: =tbl_raw[[#This Row],[gross_revenue]] -> 63885 | D3: =tbl_raw[[#This Row],[return_loss]] -> 70.2 | E3: =C3-D3 -> 63814.8 | F3: =tbl_raw[[#This Row],[cogs]] -> 26831.7 | G3: =SUM(tbl_raw[[#This Row],[storage_cost]:[freight_cost]]) -> 4664.1 | H3: =tbl_profitability[[#This Row],[net_revenue_after_returns]]-tbl_profitability[[#This Row],[cogs]]-tbl_profitability[[#This Row],[operating_costs]] -> 32319 | I3: =(tbl_profitability[[#This Row],[gross_revenue]]-tbl_profitability[[#This Row],[cogs]])/tbl_profitability[[#This Row],[gross_revenue]] -> 0.58 | J3: =tbl_profitability[[#This Row],[net_profit]]/tbl_profitability[[#This Row],[gross_revenue]] -> 0.5058934 | K3: =(tbl_profitability[[#This Row],[cogs]]+tbl_profitability[[#This Row],[return_loss]]+tbl_profitability[[#This Row],[operating_costs]])/tbl_raw[[#This Row],[units_sold]] -> 161.87692 | L3: =tbl_raw[[#This Row],[decision]] -> SCALE
A4: =tbl_raw[[#This Row],[product_id]] -> 6cdd53843498f92890544667809f1595 | B4: =tbl_raw[[#This Row],[category]] -> health_beauty | C4: =tbl_raw[[#This Row],[gross_revenue]] -> 54730.2 | D4: =tbl_raw[[#This Row],[return_loss]] -> 56.16 | E4: =C4-D4 -> 54674.04 | F4: =tbl_raw[[#This Row],[cogs]] -> 22986.68 | G4: =SUM(tbl_raw[[#This Row],[storage_cost]:[freight_cost]]) -> 5123.79 | H4: =tbl_profitability[[#This Row],[net_revenue_after_returns]]-tbl_profitability[[#This Row],[cogs]]-tbl_profitability[[#This Row],[operating_costs]] -> 26563.57 | I4: =(tbl_profitability[[#This Row],[gross_revenue]]-tbl_profitability[[#This Row],[cogs]])/tbl_profitability[[#This Row],[gross_revenue]] -> 0.58000007 | J4: =tbl_profitability[[#This Row],[net_profit]]/tbl_profitability[[#This Row],[gross_revenue]] -> 0.48535489 | K4: =(tbl_profitability[[#This Row],[cogs]]+tbl_profitability[[#This Row],[return_loss]]+tbl_profitability[[#This Row],[operating_costs]])/tbl_raw[[#This Row],[units_sold]] -> 180.55532 | L4: =tbl_raw[[#This Row],[decision]] -> SCALE
A5: =tbl_raw[[#This Row],[product_id]] -> d6160fb7873f184099d9bc95e30376af | B5: =tbl_raw[[#This Row],[category]] -> computers | C5: =tbl_raw[[#This Row],[gross_revenue]] -> 48899.34 | D5: =tbl_raw[[#This Row],[return_loss]] -> 31.5 | E5: =C5-D5 -> 48867.84 | F5: =tbl_raw[[#This Row],[cogs]] -> 27872.62 | G5: =SUM(tbl_raw[[#This Row],[storage_cost]:[freight_cost]]) -> 1855.59 | H5: =tbl_profitability[[#This Row],[net_revenue_after_returns]]-tbl_profitability[[#This Row],[cogs]]-tbl_profitability[[#This Row],[operating_costs]] -> 19139.63 | I5: =(tbl_profitability[[#This Row],[gross_revenue]]-tbl_profitability[[#This Row],[cogs]])/tbl_profitability[[#This Row],[gross_revenue]] -> 0.43000008 | J5: =tbl_profitability[[#This Row],[net_profit]]/tbl_profitability[[#This Row],[gross_revenue]] -> 0.39140876 | K5: =(tbl_profitability[[#This Row],[cogs]]+tbl_profitability[[#This Row],[return_loss]]+tbl_profitability[[#This Row],[operating_costs]])/tbl_raw[[#This Row],[units_sold]] -> 850.27743 | L5: =tbl_raw[[#This Row],[decision]] -> SCALE
A6: =tbl_raw[[#This Row],[product_id]] -> d1c427060a0f73f6b889a5c7c61f2ac4 | B6: =tbl_raw[[#This Row],[category]] -> computers_accessories | C6: =tbl_raw[[#This Row],[gross_revenue]] -> 46916.51 | D6: =tbl_raw[[#This Row],[return_loss]] -> 306.9 | E6: =C6-D6 -> 46609.61 | F6: =tbl_raw[[#This Row],[cogs]] -> 26742.41 | G6: =SUM(tbl_raw[[#This Row],[storage_cost]:[freight_cost]]) -> 17658.03 | H6: =tbl_profitability[[#This Row],[net_revenue_after_returns]]-tbl_profitability[[#This Row],[cogs]]-tbl_profitability[[#This Row],[operating_costs]] -> 2209.17 | I6: =(tbl_profitability[[#This Row],[gross_revenue]]-tbl_profitability[[#This Row],[cogs]])/tbl_profitability[[#This Row],[gross_revenue]] -> 0.43000001 | J6: =tbl_profitability[[#This Row],[net_profit]]/tbl_profitability[[#This Row],[gross_revenue]] -> 0.047087262 | K6: =(tbl_profitability[[#This Row],[cogs]]+tbl_profitability[[#This Row],[return_loss]]+tbl_profitability[[#This Row],[operating_costs]])/tbl_raw[[#This Row],[units_sold]] -> 131.10657 | L6: =tbl_raw[[#This Row],[decision]] -> EXIT
A7: =tbl_raw[[#This Row],[product_id]] -> 99a4788cb24856965c36a24e339b6058 | B7: =tbl_raw[[#This Row],[category]] -> bed_bath_table | C7: =tbl_raw[[#This Row],[gross_revenue]] -> 42938.66 | D7: =tbl_raw[[#This Row],[return_loss]] -> 175.32 | E7: =C7-D7 -> 42763.34 | F7: =tbl_raw[[#This Row],[cogs]] -> 19322.4 | G7: =SUM(tbl_raw[[#This Row],[storage_cost]:[freight_cost]]) -> 12149.69 | H7: =tbl_profitability[[#This Row],[net_revenue_after_returns]]-tbl_profitability[[#This Row],[cogs]]-tbl_profitability[[#This Row],[operating_costs]] -> 11291.25 | I7: =(tbl_profitability[[#This Row],[gross_revenue]]-tbl_profitability[[#This Row],[cogs]])/tbl_profitability[[#This Row],[gross_revenue]] -> 0.54999993 | J7: =tbl_profitability[[#This Row],[net_profit]]/tbl_profitability[[#This Row],[gross_revenue]] -> 0.26296233 | K7: =(tbl_profitability[[#This Row],[cogs]]+tbl_profitability[[#This Row],[return_loss]]+tbl_profitability[[#This Row],[operating_costs]])/tbl_raw[[#This Row],[units_sold]] -> 64.984415 | L7: =tbl_raw[[#This Row],[decision]] -> OPTIMIZE
A8: =tbl_raw[[#This Row],[product_id]] -> 3dd2a17168ec895c781a9191c1e95ad7 | B8: =tbl_raw[[#This Row],[category]] -> computers_accessories | C8: =tbl_raw[[#This Row],[gross_revenue]] -> 41082.6 | D8: =tbl_raw[[#This Row],[return_loss]] -> 246.6 | E8: =C8-D8 -> 40836 | F8: =tbl_raw[[#This Row],[cogs]] -> 23417.08 | G8: =SUM(tbl_raw[[#This Row],[storage_cost]:[freight_cost]]) -> 10296.12 | H8: =tbl_profitability[[#This Row],[net_revenue_after_returns]]-tbl_profitability[[#This Row],[cogs]]-tbl_profitability[[#This Row],[operating_costs]] -> 7122.8 | I8: =(tbl_profitability[[#This Row],[gross_revenue]]-tbl_profitability[[#This Row],[cogs]])/tbl_profitability[[#This Row],[gross_revenue]] -> 0.43000005 | J8: =tbl_profitability[[#This Row],[net_profit]]/tbl_profitability[[#This Row],[gross_revenue]] -> 0.17337754 | K8: =(tbl_profitability[[#This Row],[cogs]]+tbl_profitability[[#This Row],[return_loss]]+tbl_profitability[[#This Row],[operating_costs]])/tbl_raw[[#This Row],[units_sold]] -> 123.94088 | L8: =tbl_raw[[#This Row],[decision]] -> OPTIMIZE
A9: =tbl_raw[[#This Row],[product_id]] -> 25c38557cf793876c5abdd5931f922db | B9: =tbl_raw[[#This Row],[category]] -> baby | C9: =tbl_raw[[#This Row],[gross_revenue]] -> 38907.32 | D9: =tbl_raw[[#This Row],[return_loss]] -> 13.68 | E9: =C9-D9 -> 38893.64 | F9: =tbl_raw[[#This Row],[cogs]] -> 16341.07 | G9: =SUM(tbl_raw[[#This Row],[storage_cost]:[freight_cost]]) -> 1594.63 | H9: =tbl_profitability[[#This Row],[net_revenue_after_returns]]-tbl_profitability[[#This Row],[cogs]]-tbl_profitability[[#This Row],[operating_costs]] -> 20957.94 | I9: =(tbl_profitability[[#This Row],[gross_revenue]]-tbl_profitability[[#This Row],[cogs]])/tbl_profitability[[#This Row],[gross_revenue]] -> 0.58000011 | J9: =tbl_profitability[[#This Row],[net_profit]]/tbl_profitability[[#This Row],[gross_revenue]] -> 0.53866316 | K9: =(tbl_profitability[[#This Row],[cogs]]+tbl_profitability[[#This Row],[return_loss]]+tbl_profitability[[#This Row],[operating_costs]])/tbl_raw[[#This Row],[units_sold]] -> 472.35211 | L9: =tbl_raw[[#This Row],[decision]] -> EXIT
A10: =tbl_raw[[#This Row],[product_id]] -> 5f504b3a1c75b73d6151be81eb05bdc9 | B10: =tbl_raw[[#This Row],[category]] -> cool_stuff | C10: =tbl_raw[[#This Row],[gross_revenue]] -> 37733.9 | D10: =tbl_raw[[#This Row],[return_loss]] -> 22.68 | E10: =C10-D10 -> 37711.22 | F10: =tbl_raw[[#This Row],[cogs]] -> 16980.26 | G10: =SUM(tbl_raw[[#This Row],[storage_cost]:[freight_cost]]) -> 4306.91 | H10: =tbl_profitability[[#This Row],[net_revenue_after_returns]]-tbl_profitability[[#This Row],[cogs]]-tbl_profitability[[#This Row],[operating_costs]] -> 16424.05 | I10: =(tbl_profitability[[#This Row],[gross_revenue]]-tbl_profitability[[#This Row],[cogs]])/tbl_profitability[[#This Row],[gross_revenue]] -> 0.54999987 | J10: =tbl_profitability[[#This Row],[net_profit]]/tbl_profitability[[#This Row],[gross_revenue]] -> 0.43525981 | K10: =(tbl_profitability[[#This Row],[cogs]]+tbl_profitability[[#This Row],[return_loss]]+tbl_profitability[[#This Row],[operating_costs]])/tbl_raw[[#This Row],[units_sold]] -> 338.25159 | L10: =tbl_raw[[#This Row],[decision]] -> SCALE
A11: =tbl_raw[[#This Row],[product_id]] -> 53b36df67ebb7c41585e8d54d6772e08 | B11: =tbl_raw[[#This Row],[category]] -> watches_gifts | C11: =tbl_raw[[#This Row],[gross_revenue]] -> 37683.42 | D11: =tbl_raw[[#This Row],[return_loss]] -> 116.28 | E11: =C11-D11 -> 37567.14 | F11: =tbl_raw[[#This Row],[cogs]] -> 15827.04 | G11: =SUM(tbl_raw[[#This Row],[storage_cost]:[freight_cost]]) -> 3821.51 | H11: =tbl_profitability[[#This Row],[net_revenue_after_returns]]-tbl_profitability[[#This Row],[cogs]]-tbl_profitability[[#This Row],[operating_costs]] -> 17918.59 | I11: =(tbl_profitability[[#This Row],[gross_revenue]]-tbl_profitability[[#This Row],[cogs]])/tbl_profitability[[#This Row],[gross_revenue]] -> 0.5799999 | J11: =tbl_profitability[[#This Row],[net_profit]]/tbl_profitability[[#This Row],[gross_revenue]] -> 0.47550328 | K11: =(tbl_profitability[[#This Row],[cogs]]+tbl_profitability[[#This Row],[return_loss]]+tbl_profitability[[#This Row],[operating_costs]])/tbl_raw[[#This Row],[units_sold]] -> 61.191424 | L11: =tbl_raw[[#This Row],[decision]] -> SCALE
A12: =tbl_raw[[#This Row],[product_id]] -> aca2eb7d00ea1a7b8ebd4e68314663af | B12: =tbl_raw[[#This Row],[category]] -> furniture_decor | C12: =tbl_raw[[#This Row],[gross_revenue]] -> 37608.9 | D12: =tbl_raw[[#This Row],[return_loss]] -> 189.72 | E12: =C12-D12 -> 37419.18 | F12: =tbl_raw[[#This Row],[cogs]] -> 16924.01 | G12: =SUM(tbl_raw[[#This Row],[storage_cost]:[freight_cost]]) -> 14156.86 | H12: =tbl_profitability[[#This Row],[net_revenue_after_returns]]-tbl_profitability[[#This Row],[cogs]]-tbl_profitability[[#This Row],[operating_costs]] -> 6338.31 | I12: =(tbl_profitability[[#This Row],[gross_revenue]]-tbl_profitability[[#This Row],[cogs]])/tbl_profitability[[#This Row],[gross_revenue]] -> 0.54999987 | J12: =tbl_profitability[[#This Row],[net_profit]]/tbl_profitability[[#This Row],[gross_revenue]] -> 0.16853218 | K12: =(tbl_profitability[[#This Row],[cogs]]+tbl_profitability[[#This Row],[return_loss]]+tbl_profitability[[#This Row],[operating_costs]])/tbl_raw[[#This Row],[units_sold]] -> 59.336983 | L12: =tbl_raw[[#This Row],[decision]] -> OPTIMIZE
A13: =tbl_raw[[#This Row],[product_id]] -> e0d64dcfaa3b6db5c54ca298ae101d05 | B13: =tbl_raw[[#This Row],[category]] -> watches_gifts | C13: =tbl_raw[[#This Row],[gross_revenue]] -> 31786.82 | D13: =tbl_raw[[#This Row],[return_loss]] -> 69.84 | E13: =C13-D13 -> 31716.98 | F13: =tbl_raw[[#This Row],[cogs]] -> 13350.46 | G13: =SUM(tbl_raw[[#This Row],[storage_cost]:[freight_cost]]) -> 4527.27 | H13: =tbl_profitability[[#This Row],[net_revenue_after_returns]]-tbl_profitability[[#This Row],[cogs]]-tbl_profitability[[#This Row],[operating_costs]] -> 13839.25 | I13: =(tbl_profitability[[#This Row],[gross_revenue]]-tbl_profitability[[#This Row],[cogs]])/tbl_profitability[[#This Row],[gross_revenue]] -> 0.58000014 | J13: =tbl_profitability[[#This Row],[net_profit]]/tbl_profitability[[#This Row],[gross_revenue]] -> 0.43537699 | K13: =(tbl_profitability[[#This Row],[cogs]]+tbl_profitability[[#This Row],[return_loss]]+tbl_profitability[[#This Row],[operating_costs]])/tbl_raw[[#This Row],[units_sold]] -> 92.513247 | L13: =tbl_raw[[#This Row],[decision]] -> OPTIMIZE
A14: =tbl_raw[[#This Row],[product_id]] -> d285360f29ac7fd97640bf0baef03de0 | B14: =tbl_raw[[#This Row],[category]] -> watches_gifts | C14: =tbl_raw[[#This Row],[gross_revenue]] -> 31623.81 | D14: =tbl_raw[[#This Row],[return_loss]] -> 44.28 | E14: =C14-D14 -> 31579.53 | F14: =tbl_raw[[#This Row],[cogs]] -> 13282 | G14: =SUM(tbl_raw[[#This Row],[storage_cost]:[freight_cost]]) -> 2594.76 | H14: =tbl_profitability[[#This Row],[net_revenue_after_returns]]-tbl_profitability[[#This Row],[cogs]]-tbl_profitability[[#This Row],[operating_costs]] -> 15702.77 | I14: =(tbl_profitability[[#This Row],[gross_revenue]]-tbl_profitability[[#This Row],[cogs]])/tbl_profitability[[#This Row],[gross_revenue]] -> 0.58000001 | J14: =tbl_profitability[[#This Row],[net_profit]]/tbl_profitability[[#This Row],[gross_revenue]] -> 0.49654896 | K14: =(tbl_profitability[[#This Row],[cogs]]+tbl_profitability[[#This Row],[return_loss]]+tbl_profitability[[#This Row],[operating_costs]])/tbl_raw[[#This Row],[units_sold]] -> 129.43935 | L14: =tbl_raw[[#This Row],[decision]] -> OPTIMIZE
... A402: =tbl_raw[[#This Row],[product_id]] -> 6902c1962dd19d540807d0ab8fade5c6 | B402: =tbl_raw[[#This Row],[category]] -> watches_gifts | C402: =tbl_raw[[#This Row],[gross_revenue]] -> 3999.9 | D402: =tbl_raw[[#This Row],[return_loss]] -> 0.36 | E402: =C402-D402 -> 3999.54 | F402: =tbl_raw[[#This Row],[cogs]] -> 1679.96 | G402: =SUM(tbl_raw[[#This Row],[storage_cost]:[freight_cost]]) -> 22.01 | H402: =tbl_profitability[[#This Row],[net_revenue_after_returns]]-tbl_profitability[[#This Row],[cogs]]-tbl_profitability[[#This Row],[operating_costs]] -> 2297.57 | I402: =(tbl_profitability[[#This Row],[gross_revenue]]-tbl_profitability[[#This Row],[cogs]])/tbl_profitability[[#This Row],[gross_revenue]] -> 0.5799995 | J402: =tbl_profitability[[#This Row],[net_profit]]/tbl_profitability[[#This Row],[gross_revenue]] -> 0.57440686 | K402: =(tbl_profitability[[#This Row],[cogs]]+tbl_profitability[[#This Row],[return_loss]]+tbl_profitability[[#This Row],[operating_costs]])/tbl_raw[[#This Row],[units_sold]] -> 1702.33 | L402: =tbl_raw[[#This Row],[decision]] -> SCALE
A405: MODEL RECONCILIATION - Excel vs SQL Source of Truth
A407: Check | B407: Tolerance | C407: Result | D407: Status
A408: Max |Δ| Net Profit (BRL) | B408: < R$ 0.01 | C408: {=MAX(ABS(tbl_profitability[net_profit]-tbl_raw[net_profit_sql_check]))} -> 7.2759576e-12 | D408: =IF(C408<0.01,"✓ Pass","✗ Fail") -> ✓ Pass
A409: Max |Δ| Net Margin (pp) | B409: < 0.01% | C409: {=MAX(ABS(tbl_profitability[net_margin_pct]-tbl_raw[net_margin_pct_sql_check]))} -> 5e-05 | D409: =IF(C409<0.0001,"✓ Pass","✗ Fail") -> ✓ Pass
A410: Row count Excel vs SQL | B410: =400 -> 400 | C410: =ROWS(tbl_profitability[]) -> 400 | D410: =IF(C410=400,"✓ Pass","✗ Fail") -> ✓ Pass
A412: =IF(COUNTIF(D408:D410,"✓ Pass")=3,"✓ RECONCILED - Model ties to SQL source within tolerance.","✗ INVESTIGATE — One or more checks failed. Do not rely on downstream tabs until resolved.") -> ✓ RECONCILED - Model ties to SQL source within tolerance.

Sheet Scenario_Analysis
C1: Baseline | F1: Scenario A — COGS +% | J1: Scenario B — Returns +pp | N1: Scenario C — Price −% | R1: Stability | T1: Scenario | U1: Description
A2: product_id | B2: category | C2: net_profit | D2: net_margin_pct | E2: decision | F2: net_profit_A | G2: net_margin_A | H2: margin_delta_A | I2: decision_A | J2: net_profit_B | K2: net_margin_B | L2: margin_delta_B | M2: decision_B | N2: net_profit_C | O2: net_margin_C | P2: margin_delta_C | Q2: decision_C | R2: stability_flag | T2: Scenario A | U2: COGS increase — multiplier applied to cost of goods sold | Y2: 0.1
A3: =tbl_raw[[#This Row],[product_id]] -> bb50f2e236e5eea0100680137654686c | B3: =tbl_raw[[#This Row],[category]] -> health_beauty | C3: =tbl_profitability[[#This Row],[net_profit]] -> 32319 | D3: =tbl_profitability[[#This Row],[net_margin_pct]] -> 0.5058934 | E3: =tbl_profitability[[#This Row],[decision]] -> SCALE | F3: =tbl_raw[[#This Row],[gross_revenue]]-tbl_raw[[#This Row],[return_loss]]-tbl_raw[[#This Row],[cogs]]*(1+scn_A_cogs_up)-(tbl_raw[[#This Row],[storage_cost]]+tbl_raw[[#This Row],[fulfillment_cost]]+tbl_raw[[#This Row],[freight_cost]]) -> 29635.83 | G3: =tbl_scenarios[[#This Row],[net_profit_A]]/tbl_raw[[#This Row],[gross_revenue]] -> 0.4638934 | H3: =tbl_scenarios[[#This Row],[net_margin_A]]-tbl_scenarios[[#This Row],[net_margin_pct]] -> -0.042 | I3: =IF(OR(tbl_scenarios[[#This Row],[net_margin_A]]<0.1,tbl_raw[[#This Row],[avg_review_score]]<3),"EXIT",IF(AND(tbl_scenarios[[#This Row],[net_margin_A]]>=0.25,tbl_raw[[#This Row],[avg_review_score]]>=4),"SCALE","OPTIMIZE")) -> SCALE | J3: =tbl_raw[[#This Row],[gross_revenue]]-tbl_raw[[#This Row],[return_loss]]*(1+scn_B_returns_up/0.05)-tbl_raw[[#This Row],[cogs]]-(tbl_raw[[#This Row],[storage_cost]]+tbl_raw[[#This Row],[fulfillment_cost]]+tbl_raw[[#This Row],[freight_cost]]) -> 32248.8 | K3: =tbl_scenarios[[#This Row],[net_profit_B]]/tbl_raw[[#This Row],[gross_revenue]] -> 0.50479455 | L3: =tbl_scenarios[[#This Row],[net_margin_B]]-tbl_scenarios[[#This Row],[net_margin_pct]] -> -0.0010988495 | M3: =IF(OR(tbl_scenarios[[#This Row],[net_margin_B]]<0.1,tbl_raw[[#This Row],[avg_review_score]]<3),"EXIT",IF(AND(tbl_scenarios[[#This Row],[net_margin_B]]>=0.25,tbl_raw[[#This Row],[avg_review_score]]>=4),"SCALE","OPTIMIZE")) -> SCALE | N3: =tbl_raw[[#This Row],[gross_revenue]]*(1-scn_C_price_down)-tbl_raw[[#This Row],[return_loss]]-tbl_raw[[#This Row],[cogs]]-(tbl_raw[[#This Row],[storage_cost]]+tbl_raw[[#This Row],[fulfillment_cost]]+tbl_raw[[#This Row],[freight_cost]]) -> 29124.75 | O3: =tbl_scenarios[[#This Row],[net_profit_C]]/(tbl_raw[[#This Row],[gross_revenue]]*(1-scn_C_price_down)) -> 0.47988779 | P3: =tbl_scenarios[[#This Row],[net_margin_C]]-tbl_scenarios[[#This Row],[net_margin_pct]] -> -0.02600561 | Q3: =IF(OR(tbl_scenarios[[#This Row],[net_margin_C]]<0.1,tbl_raw[[#This Row],[avg_review_score]]<3),"EXIT",IF(AND(tbl_scenarios[[#This Row],[net_margin_C]]>=0.25,tbl_raw[[#This Row],[avg_review_score]]>=4),"SCALE","OPTIMIZE")) -> SCALE | R3: =IF(OR(tbl_scenarios[[#This Row],[decision_A]]<>tbl_scenarios[[#This Row],[decision]],tbl_scenarios[[#This Row],[decision_B]]<>tbl_scenarios[[#This Row],[decision]],tbl_scenarios[[#This Row],[decision_C]]<>tbl_scenarios[[#This Row],[decision]]),"Decision changes","Stable") -> Stable | T3: Scenario B | U3: Return-rate increase in percentage points (rate-derived: return_loss × (1 + Δ / 5%)) | Y3: 0.05
A4: =tbl_raw[[#This Row],[product_id]] -> 6cdd53843498f92890544667809f1595 | B4: =tbl_raw[[#This Row],[category]] -> health_beauty | C4: =tbl_profitability[[#This Row],[net_profit]] -> 26563.57 | D4: =tbl_profitability[[#This Row],[net_margin_pct]] -> 0.48535489 | E4: =tbl_profitability[[#This Row],[decision]] -> SCALE | F4: =tbl_raw[[#This Row],[gross_revenue]]-tbl_raw[[#This Row],[return_loss]]-tbl_raw[[#This Row],[cogs]]*(1+scn_A_cogs_up)-(tbl_raw[[#This Row],[storage_cost]]+tbl_raw[[#This Row],[fulfillment_cost]]+tbl_raw[[#This Row],[freight_cost]]) -> 24264.902 | G4: =tbl_scenarios[[#This Row],[net_profit_A]]/tbl_raw[[#This Row],[gross_revenue]] -> 0.44335489 | H4: =tbl_scenarios[[#This Row],[net_margin_A]]-tbl_scenarios[[#This Row],[net_margin_pct]] -> -0.041999993 | I4: =IF(OR(tbl_scenarios[[#This Row],[net_margin_A]]<0.1,tbl_raw[[#This Row],[avg_review_score]]<3),"EXIT",IF(AND(tbl_scenarios[[#This Row],[net_margin_A]]>=0.25,tbl_raw[[#This Row],[avg_review_score]]>=4),"SCALE","OPTIMIZE")) -> SCALE | J4: =tbl_raw[[#This Row],[gross_revenue]]-tbl_raw[[#This Row],[return_loss]]*(1+scn_B_returns_up/0.05)-tbl_raw[[#This Row],[cogs]]-(tbl_raw[[#This Row],[storage_cost]]+tbl_raw[[#This Row],[fulfillment_cost]]+tbl_raw[[#This Row],[freight_cost]]) -> 26507.41 | K4: =tbl_scenarios[[#This Row],[net_profit_B]]/tbl_raw[[#This Row],[gross_revenue]] -> 0.48432876 | L4: =tbl_scenarios[[#This Row],[net_margin_B]]-tbl_scenarios[[#This Row],[net_margin_pct]] -> -0.0010261245 | M4: =IF(OR(tbl_scenarios[[#This Row],[net_margin_B]]<0.1,tbl_raw[[#This Row],[avg_review_score]]<3),"EXIT",IF(AND(tbl_scenarios[[#This Row],[net_margin_B]]>=0.25,tbl_raw[[#This Row],[avg_review_score]]>=4),"SCALE","OPTIMIZE")) -> SCALE | N4: =tbl_raw[[#This Row],[gross_revenue]]*(1-scn_C_price_down)-tbl_raw[[#This Row],[return_loss]]-tbl_raw[[#This Row],[cogs]]-(tbl_raw[[#This Row],[storage_cost]]+tbl_raw[[#This Row],[fulfillment_cost]]+tbl_raw[[#This Row],[freight_cost]]) -> 23827.06 | O4: =tbl_scenarios[[#This Row],[net_profit_C]]/(tbl_raw[[#This Row],[gross_revenue]]*(1-scn_C_price_down)) -> 0.4582683 | P4: =tbl_scenarios[[#This Row],[net_margin_C]]-tbl_scenarios[[#This Row],[net_margin_pct]] -> -0.027086585 | Q4: =IF(OR(tbl_scenarios[[#This Row],[net_margin_C]]<0.1,tbl_raw[[#This Row],[avg_review_score]]<3),"EXIT",IF(AND(tbl_scenarios[[#This Row],[net_margin_C]]>=0.25,tbl_raw[[#This Row],[avg_review_score]]>=4),"SCALE","OPTIMIZE")) -> SCALE | R4: =IF(OR(tbl_scenarios[[#This Row],[decision_A]]<>tbl_scenarios[[#This Row],[decision]],tbl_scenarios[[#This Row],[decision_B]]<>tbl_scenarios[[#This Row],[decision]],tbl_scenarios[[#This Row],[decision_C]]<>tbl_scenarios[[#This Row],[decision]]),"Decision changes","Stable") -> Stable | T4: Scenario C | U4: Sale price reduction — multiplier on gross revenue | Y4: 0.05
A5: =tbl_raw[[#This Row],[product_id]] -> d6160fb7873f184099d9bc95e30376af | B5: =tbl_raw[[#This Row],[category]] -> computers | C5: =tbl_profitability[[#This Row],[net_profit]] -> 19139.63 | D5: =tbl_profitability[[#This Row],[net_margin_pct]] -> 0.39140876 | E5: =tbl_profitability[[#This Row],[decision]] -> SCALE | F5: =tbl_raw[[#This Row],[gross_revenue]]-tbl_raw[[#This Row],[return_loss]]-tbl_raw[[#This Row],[cogs]]*(1+scn_A_cogs_up)-(tbl_raw[[#This Row],[storage_cost]]+tbl_raw[[#This Row],[fulfillment_cost]]+tbl_raw[[#This Row],[freight_cost]]) -> 16352.368 | G5: =tbl_scenarios[[#This Row],[net_profit_A]]/tbl_raw[[#This Row],[gross_revenue]] -> 0.33440877 | H5: =tbl_scenarios[[#This Row],[net_margin_A]]-tbl_scenarios[[#This Row],[net_margin_pct]] -> -0.056999992 | I5: =IF(OR(tbl_scenarios[[#This Row],[net_margin_A]]<0.1,tbl_raw[[#This Row],[avg_review_score]]<3),"EXIT",IF(AND(tbl_scenarios[[#This Row],[net_margin_A]]>=0.25,tbl_raw[[#This Row],[avg_review_score]]>=4),"SCALE","OPTIMIZE")) -> SCALE | J5: =tbl_raw[[#This Row],[gross_revenue]]-tbl_raw[[#This Row],[return_loss]]*(1+scn_B_returns_up/0.05)-tbl_raw[[#This Row],[cogs]]-(tbl_raw[[#This Row],[storage_cost]]+tbl_raw[[#This Row],[fulfillment_cost]]+tbl_raw[[#This Row],[freight_cost]]) -> 19108.13 | K5: =tbl_scenarios[[#This Row],[net_profit_B]]/tbl_raw[[#This Row],[gross_revenue]] -> 0.39076458 | L5: =tbl_scenarios[[#This Row],[net_margin_B]]-tbl_scenarios[[#This Row],[net_margin_pct]] -> -0.00064418047 | M5: =IF(OR(tbl_scenarios[[#This Row],[net_margin_B]]<0.1,tbl_raw[[#This Row],[avg_review_score]]<3),"EXIT",IF(AND(tbl_scenarios[[#This Row],[net_margin_B]]>=0.25,tbl_raw[[#This Row],[avg_review_score]]>=4),"SCALE","OPTIMIZE")) -> SCALE | N5: =tbl_raw[[#This Row],[gross_revenue]]*(1-scn_C_price_down)-tbl_raw[[#This Row],[return_loss]]-tbl_raw[[#This Row],[cogs]]-(tbl_raw[[#This Row],[storage_cost]]+tbl_raw[[#This Row],[fulfillment_cost]]+tbl_raw[[#This Row],[freight_cost]]) -> 16694.663 | O5: =tbl_scenarios[[#This Row],[net_profit_C]]/(tbl_raw[[#This Row],[gross_revenue]]*(1-scn_C_price_down)) -> 0.35937764 | P5: =tbl_scenarios[[#This Row],[net_margin_C]]-tbl_scenarios[[#This Row],[net_margin_pct]] -> -0.032031118 | Q5: =IF(OR(tbl_scenarios[[#This Row],[net_margin_C]]<0.1,tbl_raw[[#This Row],[avg_review_score]]<3),"EXIT",IF(AND(tbl_scenarios[[#This Row],[net_margin_C]]>=0.25,tbl_raw[[#This Row],[avg_review_score]]>=4),"SCALE","OPTIMIZE")) -> SCALE | R5: =IF(OR(tbl_scenarios[[#This Row],[decision_A]]<>tbl_scenarios[[#This Row],[decision]],tbl_scenarios[[#This Row],[decision_B]]<>tbl_scenarios[[#This Row],[decision]],tbl_scenarios[[#This Row],[decision_C]]<>tbl_scenarios[[#This Row],[decision]]),"Decision changes","Stable") -> Stable
A6: =tbl_raw[[#This Row],[product_id]] -> d1c427060a0f73f6b889a5c7c61f2ac4 | B6: =tbl_raw[[#This Row],[category]] -> computers_accessories | C6: =tbl_profitability[[#This Row],[net_profit]] -> 2209.17 | D6: =tbl_profitability[[#This Row],[net_margin_pct]] -> 0.047087262 | E6: =tbl_profitability[[#This Row],[decision]] -> EXIT | F6: =tbl_raw[[#This Row],[gross_revenue]]-tbl_raw[[#This Row],[return_loss]]-tbl_raw[[#This Row],[cogs]]*(1+scn_A_cogs_up)-(tbl_raw[[#This Row],[storage_cost]]+tbl_raw[[#This Row],[fulfillment_cost]]+tbl_raw[[#This Row],[freight_cost]]) -> -465.071 | G6: =tbl_scenarios[[#This Row],[net_profit_A]]/tbl_raw[[#This Row],[gross_revenue]] -> -0.0099127365 | H6: =tbl_scenarios[[#This Row],[net_margin_A]]-tbl_scenarios[[#This Row],[net_margin_pct]] -> -0.056999999 | I6: =IF(OR(tbl_scenarios[[#This Row],[net_margin_A]]<0.1,tbl_raw[[#This Row],[avg_review_score]]<3),"EXIT",IF(AND(tbl_scenarios[[#This Row],[net_margin_A]]>=0.25,tbl_raw[[#This Row],[avg_review_score]]>=4),"SCALE","OPTIMIZE")) -> EXIT | J6: =tbl_raw[[#This Row],[gross_revenue]]-tbl_raw[[#This Row],[return_loss]]*(1+scn_B_returns_up/0.05)-tbl_raw[[#This Row],[cogs]]-(tbl_raw[[#This Row],[storage_cost]]+tbl_raw[[#This Row],[fulfillment_cost]]+tbl_raw[[#This Row],[freight_cost]]) -> 1902.27 | K6: =tbl_scenarios[[#This Row],[net_profit_B]]/tbl_raw[[#This Row],[gross_revenue]] -> 0.040545855 | L6: =tbl_scenarios[[#This Row],[net_margin_B]]-tbl_scenarios[[#This Row],[net_margin_pct]] -> -0.0065414073 | M6: =IF(OR(tbl_scenarios[[#This Row],[net_margin_B]]<0.1,tbl_raw[[#This Row],[avg_review_score]]<3),"EXIT",IF(AND(tbl_scenarios[[#This Row],[net_margin_B]]>=0.25,tbl_raw[[#This Row],[avg_review_score]]>=4),"SCALE","OPTIMIZE")) -> EXIT | N6: =tbl_raw[[#This Row],[gross_revenue]]*(1-scn_C_price_down)-tbl_raw[[#This Row],[return_loss]]-tbl_raw[[#This Row],[cogs]]-(tbl_raw[[#This Row],[storage_cost]]+tbl_raw[[#This Row],[fulfillment_cost]]+tbl_raw[[#This Row],[freight_cost]]) -> -136.6555 | O6: =tbl_scenarios[[#This Row],[net_profit_C]]/(tbl_raw[[#This Row],[gross_revenue]]*(1-scn_C_price_down)) -> -0.00306604 | P6: =tbl_scenarios[[#This Row],[net_margin_C]]-tbl_scenarios[[#This Row],[net_margin_pct]] -> -0.050153302 | Q6: =IF(OR(tbl_scenarios[[#This Row],[net_margin_C]]<0.1,tbl_raw[[#This Row],[avg_review_score]]<3),"EXIT",IF(AND(tbl_scenarios[[#This Row],[net_margin_C]]>=0.25,tbl_raw[[#This Row],[avg_review_score]]>=4),"SCALE","OPTIMIZE")) -> EXIT | R6: =IF(OR(tbl_scenarios[[#This Row],[decision_A]]<>tbl_scenarios[[#This Row],[decision]],tbl_scenarios[[#This Row],[decision_B]]<>tbl_scenarios[[#This Row],[decision]],tbl_scenarios[[#This Row],[decision_C]]<>tbl_scenarios[[#This Row],[decision]]),"Decision changes","Stable") -> Stable | T6: Note: scenarios are independent (not combined). Each scenario applies its shock while holding the other two variables at baseline. Edit the yellow cells above to change assumptions.
A7: =tbl_raw[[#This Row],[product_id]] -> 99a4788cb24856965c36a24e339b6058 | B7: =tbl_raw[[#This Row],[category]] -> bed_bath_table | C7: =tbl_profitability[[#This Row],[net_profit]] -> 11291.25 | D7: =tbl_profitability[[#This Row],[net_margin_pct]] -> 0.26296233 | E7: =tbl_profitability[[#This Row],[decision]] -> OPTIMIZE | F7: =tbl_raw[[#This Row],[gross_revenue]]-tbl_raw[[#This Row],[return_loss]]-tbl_raw[[#This Row],[cogs]]*(1+scn_A_cogs_up)-(tbl_raw[[#This Row],[storage_cost]]+tbl_raw[[#This Row],[fulfillment_cost]]+tbl_raw[[#This Row],[freight_cost]]) -> 9359.01 | G7: =tbl_scenarios[[#This Row],[net_profit_A]]/tbl_raw[[#This Row],[gross_revenue]] -> 0.21796232 | H7: =tbl_scenarios[[#This Row],[net_margin_A]]-tbl_scenarios[[#This Row],[net_margin_pct]] -> -0.045000007 | I7: =IF(OR(tbl_scenarios[[#This Row],[net_margin_A]]<0.1,tbl_raw[[#This Row],[avg_review_score]]<3),"EXIT",IF(AND(tbl_scenarios[[#This Row],[net_margin_A]]>=0.25,tbl_raw[[#This Row],[avg_review_score]]>=4),"SCALE","OPTIMIZE")) -> OPTIMIZE | J7: =tbl_raw[[#This Row],[gross_revenue]]-tbl_raw[[#This Row],[return_loss]]*(1+scn_B_returns_up/0.05)-tbl_raw[[#This Row],[cogs]]-(tbl_raw[[#This Row],[storage_cost]]+tbl_raw[[#This Row],[fulfillment_cost]]+tbl_raw[[#This Row],[freight_cost]]) -> 11115.93 | K7: =tbl_scenarios[[#This Row],[net_profit_B]]/tbl_raw[[#This Row],[gross_revenue]] -> 0.25887929 | L7: =tbl_scenarios[[#This Row],[net_margin_B]]-tbl_scenarios[[#This Row],[net_margin_pct]] -> -0.0040830338 | M7: =IF(OR(tbl_scenarios[[#This Row],[net_margin_B]]<0.1,tbl_raw[[#This Row],[avg_review_score]]<3),"EXIT",IF(AND(tbl_scenarios[[#This Row],[net_margin_B]]>=0.25,tbl_raw[[#This Row],[avg_review_score]]>=4),"SCALE","OPTIMIZE")) -> OPTIMIZE | N7: =tbl_raw[[#This Row],[gross_revenue]]*(1-scn_C_price_down)-tbl_raw[[#This Row],[return_loss]]-tbl_raw[[#This Row],[cogs]]-(tbl_raw[[#This Row],[storage_cost]]+tbl_raw[[#This Row],[fulfillment_cost]]+tbl_raw[[#This Row],[freight_cost]]) -> 9144.317 | O7: =tbl_scenarios[[#This Row],[net_profit_C]]/(tbl_raw[[#This Row],[gross_revenue]]*(1-scn_C_price_down)) -> 0.22417087 | P7: =tbl_scenarios[[#This Row],[net_margin_C]]-tbl_scenarios[[#This Row],[net_margin_pct]] -> -0.038791456 | Q7: =IF(OR(tbl_scenarios[[#This Row],[net_margin_C]]<0.1,tbl_raw[[#This Row],[avg_review_score]]<3),"EXIT",IF(AND(tbl_scenarios[[#This Row],[net_margin_C]]>=0.25,tbl_raw[[#This Row],[avg_review_score]]>=4),"SCALE","OPTIMIZE")) -> OPTIMIZE | R7: =IF(OR(tbl_scenarios[[#This Row],[decision_A]]<>tbl_scenarios[[#This Row],[decision]],tbl_scenarios[[#This Row],[decision_B]]<>tbl_scenarios[[#This Row],[decision]],tbl_scenarios[[#This Row],[decision_C]]<>tbl_scenarios[[#This Row],[decision]]),"Decision changes","Stable") -> Stable
A8: =tbl_raw[[#This Row],[product_id]] -> 3dd2a17168ec895c781a9191c1e95ad7 | B8: =tbl_raw[[#This Row],[category]] -> computers_accessories | C8: =tbl_profitability[[#This Row],[net_profit]] -> 7122.8 | D8: =tbl_profitability[[#This Row],[net_margin_pct]] -> 0.17337754 | E8: =tbl_profitability[[#This Row],[decision]] -> OPTIMIZE | F8: =tbl_raw[[#This Row],[gross_revenue]]-tbl_raw[[#This Row],[return_loss]]-tbl_raw[[#This Row],[cogs]]*(1+scn_A_cogs_up)-(tbl_raw[[#This Row],[storage_cost]]+tbl_raw[[#This Row],[fulfillment_cost]]+tbl_raw[[#This Row],[freight_cost]]) -> 4781.092 | G8: =tbl_scenarios[[#This Row],[net_profit_A]]/tbl_raw[[#This Row],[gross_revenue]] -> 0.11637754 | H8: =tbl_scenarios[[#This Row],[net_margin_A]]-tbl_scenarios[[#This Row],[net_margin_pct]] -> -0.056999995 | I8: =IF(OR(tbl_scenarios[[#This Row],[net_margin_A]]<0.1,tbl_raw[[#This Row],[avg_review_score]]<3),"EXIT",IF(AND(tbl_scenarios[[#This Row],[net_margin_A]]>=0.25,tbl_raw[[#This Row],[avg_review_score]]>=4),"SCALE","OPTIMIZE")) -> OPTIMIZE | J8: =tbl_raw[[#This Row],[gross_revenue]]-tbl_raw[[#This Row],[return_loss]]*(1+scn_B_returns_up/0.05)-tbl_raw[[#This Row],[cogs]]-(tbl_raw[[#This Row],[storage_cost]]+tbl_raw[[#This Row],[fulfillment_cost]]+tbl_raw[[#This Row],[freight_cost]]) -> 6876.2 | K8: =tbl_scenarios[[#This Row],[net_profit_B]]/tbl_raw[[#This Row],[gross_revenue]] -> 0.167375 | L8: =tbl_scenarios[[#This Row],[net_margin_B]]-tbl_scenarios[[#This Row],[net_margin_pct]] -> -0.0060025412 | M8: =IF(OR(tbl_scenarios[[#This Row],[net_margin_B]]<0.1,tbl_raw[[#This Row],[avg_review_score]]<3),"EXIT",IF(AND(tbl_scenarios[[#This Row],[net_margin_B]]>=0.25,tbl_raw[[#This Row],[avg_review_score]]>=4),"SCALE","OPTIMIZE")) -> OPTIMIZE | N8: =tbl_raw[[#This Row],[gross_revenue]]*(1-scn_C_price_down)-tbl_raw[[#This Row],[return_loss]]-tbl_raw[[#This Row],[cogs]]-(tbl_raw[[#This Row],[storage_cost]]+tbl_raw[[#This Row],[fulfillment_cost]]+tbl_raw[[#This Row],[freight_cost]]) -> 5068.67 | O8: =tbl_scenarios[[#This Row],[net_profit_C]]/(tbl_raw[[#This Row],[gross_revenue]]*(1-scn_C_price_down)) -> 0.12987109 | P8: =tbl_scenarios[[#This Row],[net_margin_C]]-tbl_scenarios[[#This Row],[net_margin_pct]] -> -0.043506445 | Q8: =IF(OR(tbl_scenarios[[#This Row],[net_margin_C]]<0.1,tbl_raw[[#This Row],[avg_review_score]]<3),"EXIT",IF(AND(tbl_scenarios[[#This Row],[net_margin_C]]>=0.25,tbl_raw[[#This Row],[avg_review_score]]>=4),"SCALE","OPTIMIZE")) -> OPTIMIZE | R8: =IF(OR(tbl_scenarios[[#This Row],[decision_A]]<>tbl_scenarios[[#This Row],[decision]],tbl_scenarios[[#This Row],[decision_B]]<>tbl_scenarios[[#This Row],[decision]],tbl_scenarios[[#This Row],[decision_C]]<>tbl_scenarios[[#This Row],[decision]]),"Decision changes","Stable") -> Stable
A9: =tbl_raw[[#This Row],[product_id]] -> 25c38557cf793876c5abdd5931f922db | B9: =tbl_raw[[#This Row],[category]] -> baby | C9: =tbl_profitability[[#This Row],[net_profit]] -> 20957.94 | D9: =tbl_profitability[[#This Row],[net_margin_pct]] -> 0.53866316 | E9: =tbl_profitability[[#This Row],[decision]] -> EXIT | F9: =tbl_raw[[#This Row],[gross_revenue]]-tbl_raw[[#This Row],[return_loss]]-tbl_raw[[#This Row],[cogs]]*(1+scn_A_cogs_up)-(tbl_raw[[#This Row],[storage_cost]]+tbl_raw[[#This Row],[fulfillment_cost]]+tbl_raw[[#This Row],[freight_cost]]) -> 19323.833 | G9: =tbl_scenarios[[#This Row],[net_profit_A]]/tbl_raw[[#This Row],[gross_revenue]] -> 0.49666317 | H9: =tbl_scenarios[[#This Row],[net_margin_A]]-tbl_scenarios[[#This Row],[net_margin_pct]] -> -0.041999989 | I9: =IF(OR(tbl_scenarios[[#This Row],[net_margin_A]]<0.1,tbl_raw[[#This Row],[avg_review_score]]<3),"EXIT",IF(AND(tbl_scenarios[[#This Row],[net_margin_A]]>=0.25,tbl_raw[[#This Row],[avg_review_score]]>=4),"SCALE","OPTIMIZE")) -> EXIT | J9: =tbl_raw[[#This Row],[gross_revenue]]-tbl_raw[[#This Row],[return_loss]]*(1+scn_B_returns_up/0.05)-tbl_raw[[#This Row],[cogs]]-(tbl_raw[[#This Row],[storage_cost]]+tbl_raw[[#This Row],[fulfillment_cost]]+tbl_raw[[#This Row],[freight_cost]]) -> 20944.26 | K9: =tbl_scenarios[[#This Row],[net_profit_B]]/tbl_raw[[#This Row],[gross_revenue]] -> 0.53831156 | L9: =tbl_scenarios[[#This Row],[net_margin_B]]-tbl_scenarios[[#This Row],[net_margin_pct]] -> -0.00035160479 | M9: =IF(OR(tbl_scenarios[[#This Row],[net_margin_B]]<0.1,tbl_raw[[#This Row],[avg_review_score]]<3),"EXIT",IF(AND(tbl_scenarios[[#This Row],[net_margin_B]]>=0.25,tbl_raw[[#This Row],[avg_review_score]]>=4),"SCALE","OPTIMIZE")) -> EXIT | N9: =tbl_raw[[#This Row],[gross_revenue]]*(1-scn_C_price_down)-tbl_raw[[#This Row],[return_loss]]-tbl_raw[[#This Row],[cogs]]-(tbl_raw[[#This Row],[storage_cost]]+tbl_raw[[#This Row],[fulfillment_cost]]+tbl_raw[[#This Row],[freight_cost]]) -> 19012.574 | O9: =tbl_scenarios[[#This Row],[net_profit_C]]/(tbl_raw[[#This Row],[gross_revenue]]*(1-scn_C_price_down)) -> 0.51438228 | P9: =tbl_scenarios[[#This Row],[net_margin_C]]-tbl_scenarios[[#This Row],[net_margin_pct]] -> -0.024280886 | Q9: =IF(OR(tbl_scenarios[[#This Row],[net_margin_C]]<0.1,tbl_raw[[#This Row],[avg_review_score]]<3),"EXIT",IF(AND(tbl_scenarios[[#This Row],[net_margin_C]]>=0.25,tbl_raw[[#This Row],[avg_review_score]]>=4),"SCALE","OPTIMIZE")) -> EXIT | R9: =IF(OR(tbl_scenarios[[#This Row],[decision_A]]<>tbl_scenarios[[#This Row],[decision]],tbl_scenarios[[#This Row],[decision_B]]<>tbl_scenarios[[#This Row],[decision]],tbl_scenarios[[#This Row],[decision_C]]<>tbl_scenarios[[#This Row],[decision]]),"Decision changes","Stable") -> Stable
A10: =tbl_raw[[#This Row],[product_id]] -> 5f504b3a1c75b73d6151be81eb05bdc9 | B10: =tbl_raw[[#This Row],[category]] -> cool_stuff | C10: =tbl_profitability[[#This Row],[net_profit]] -> 16424.05 | D10: =tbl_profitability[[#This Row],[net_margin_pct]] -> 0.43525981 | E10: =tbl_profitability[[#This Row],[decision]] -> SCALE | F10: =tbl_raw[[#This Row],[gross_revenue]]-tbl_raw[[#This Row],[return_loss]]-tbl_raw[[#This Row],[cogs]]*(1+scn_A_cogs_up)-(tbl_raw[[#This Row],[storage_cost]]+tbl_raw[[#This Row],[fulfillment_cost]]+tbl_raw[[#This Row],[freight_cost]]) -> 14726.024 | G10: =tbl_scenarios[[#This Row],[net_profit_A]]/tbl_raw[[#This Row],[gross_revenue]] -> 0.39025979 | H10: =tbl_scenarios[[#This Row],[net_margin_A]]-tbl_scenarios[[#This Row],[net_margin_pct]] -> -0.045000013 | I10: =IF(OR(tbl_scenarios[[#This Row],[net_margin_A]]<0.1,tbl_raw[[#This Row],[avg_review_score]]<3),"EXIT",IF(AND(tbl_scenarios[[#This Row],[net_margin_A]]>=0.25,tbl_raw[[#This Row],[avg_review_score]]>=4),"SCALE","OPTIMIZE")) -> SCALE | J10: =tbl_raw[[#This Row],[gross_revenue]]-tbl_raw[[#This Row],[return_loss]]*(1+scn_B_returns_up/0.05)-tbl_raw[[#This Row],[cogs]]-(tbl_raw[[#This Row],[storage_cost]]+tbl_raw[[#This Row],[fulfillment_cost]]+tbl_raw[[#This Row],[freight_cost]]) -> 16401.37 | K10: =tbl_scenarios[[#This Row],[net_profit_B]]/tbl_raw[[#This Row],[gross_revenue]] -> 0.43465876 | L10: =tbl_scenarios[[#This Row],[net_margin_B]]-tbl_scenarios[[#This Row],[net_margin_pct]] -> -0.00060105104 | M10: =IF(OR(tbl_scenarios[[#This Row],[net_margin_B]]<0.1,tbl_raw[[#This Row],[avg_review_score]]<3),"EXIT",IF(AND(tbl_scenarios[[#This Row],[net_margin_B]]>=0.25,tbl_raw[[#This Row],[avg_review_score]]>=4),"SCALE","OPTIMIZE")) -> SCALE | N10: =tbl_raw[[#This Row],[gross_revenue]]*(1-scn_C_price_down)-tbl_raw[[#This Row],[return_loss]]-tbl_raw[[#This Row],[cogs]]-(tbl_raw[[#This Row],[storage_cost]]+tbl_raw[[#This Row],[fulfillment_cost]]+tbl_raw[[#This Row],[freight_cost]]) -> 14537.355 | O10: =tbl_scenarios[[#This Row],[net_profit_C]]/(tbl_raw[[#This Row],[gross_revenue]]*(1-scn_C_price_down)) -> 0.40553664 | P10: =tbl_scenarios[[#This Row],[net_margin_C]]-tbl_scenarios[[#This Row],[net_margin_pct]] -> -0.029723168 | Q10: =IF(OR(tbl_scenarios[[#This Row],[net_margin_C]]<0.1,tbl_raw[[#This Row],[avg_review_score]]<3),"EXIT",IF(AND(tbl_scenarios[[#This Row],[net_margin_C]]>=0.25,tbl_raw[[#This Row],[avg_review_score]]>=4),"SCALE","OPTIMIZE")) -> SCALE | R10: =IF(OR(tbl_scenarios[[#This Row],[decision_A]]<>tbl_scenarios[[#This Row],[decision]],tbl_scenarios[[#This Row],[decision_B]]<>tbl_scenarios[[#This Row],[decision]],tbl_scenarios[[#This Row],[decision_C]]<>tbl_scenarios[[#This Row],[decision]]),"Decision changes","Stable") -> Stable
A11: =tbl_raw[[#This Row],[product_id]] -> 53b36df67ebb7c41585e8d54d6772e08 | B11: =tbl_raw[[#This Row],[category]] -> watches_gifts | C11: =tbl_profitability[[#This Row],[net_profit]] -> 17918.59 | D11: =tbl_profitability[[#This Row],[net_margin_pct]] -> 0.47550328 | E11: =tbl_profitability[[#This Row],[decision]] -> SCALE | F11: =tbl_raw[[#This Row],[gross_revenue]]-tbl_raw[[#This Row],[return_loss]]-tbl_raw[[#This Row],[cogs]]*(1+scn_A_cogs_up)-(tbl_raw[[#This Row],[storage_cost]]+tbl_raw[[#This Row],[fulfillment_cost]]+tbl_raw[[#This Row],[freight_cost]]) -> 16335.886 | G11: =tbl_scenarios[[#This Row],[net_profit_A]]/tbl_raw[[#This Row],[gross_revenue]] -> 0.43350328 | H11: =tbl_scenarios[[#This Row],[net_margin_A]]-tbl_scenarios[[#This Row],[net_margin_pct]] -> -0.04200001 | I11: =IF(OR(tbl_scenarios[[#This Row],[net_margin_A]]<0.1,tbl_raw[[#This Row],[avg_review_score]]<3),"EXIT",IF(AND(tbl_scenarios[[#This Row],[net_margin_A]]>=0.25,tbl_raw[[#This Row],[avg_review_score]]>=4),"SCALE","OPTIMIZE")) -> SCALE | J11: =tbl_raw[[#This Row],[gross_revenue]]-tbl_raw[[#This Row],[return_loss]]*(1+scn_B_returns_up/0.05)-tbl_raw[[#This Row],[cogs]]-(tbl_raw[[#This Row],[storage_cost]]+tbl_raw[[#This Row],[fulfillment_cost]]+tbl_raw[[#This Row],[freight_cost]]) -> 17802.31 | K11: =tbl_scenarios[[#This Row],[net_profit_B]]/tbl_raw[[#This Row],[gross_revenue]] -> 0.47241758 | L11: =tbl_scenarios[[#This Row],[net_margin_B]]-tbl_scenarios[[#This Row],[net_margin_pct]] -> -0.0030857072 | M11: =IF(OR(tbl_scenarios[[#This Row],[net_margin_B]]<0.1,tbl_raw[[#This Row],[avg_review_score]]<3),"EXIT",IF(AND(tbl_scenarios[[#This Row],[net_margin_B]]>=0.25,tbl_raw[[#This Row],[avg_review_score]]>=4),"SCALE","OPTIMIZE")) -> SCALE | N11: =tbl_raw[[#This Row],[gross_revenue]]*(1-scn_C_price_down)-tbl_raw[[#This Row],[return_loss]]-tbl_raw[[#This Row],[cogs]]-(tbl_raw[[#This Row],[storage_cost]]+tbl_raw[[#This Row],[fulfillment_cost]]+tbl_raw[[#This Row],[freight_cost]]) -> 16034.419 | O11: =tbl_scenarios[[#This Row],[net_profit_C]]/(tbl_raw[[#This Row],[gross_revenue]]*(1-scn_C_price_down)) -> 0.44789819 | P11: =tbl_scenarios[[#This Row],[net_margin_C]]-tbl_scenarios[[#This Row],[net_margin_pct]] -> -0.02760509 | Q11: =IF(OR(tbl_scenarios[[#This Row],[net_margin_C]]<0.1,tbl_raw[[#This Row],[avg_review_score]]<3),"EXIT",IF(AND(tbl_scenarios[[#This Row],[net_margin_C]]>=0.25,tbl_raw[[#This Row],[avg_review_score]]>=4),"SCALE","OPTIMIZE")) -> SCALE | R11: =IF(OR(tbl_scenarios[[#This Row],[decision_A]]<>tbl_scenarios[[#This Row],[decision]],tbl_scenarios[[#This Row],[decision_B]]<>tbl_scenarios[[#This Row],[decision]],tbl_scenarios[[#This Row],[decision_C]]<>tbl_scenarios[[#This Row],[decision]]),"Decision changes","Stable") -> Stable
A12: =tbl_raw[[#This Row],[product_id]] -> aca2eb7d00ea1a7b8ebd4e68314663af | B12: =tbl_raw[[#This Row],[category]] -> furniture_decor | C12: =tbl_profitability[[#This Row],[net_profit]] -> 6338.31 | D12: =tbl_profitability[[#This Row],[net_margin_pct]] -> 0.16853218 | E12: =tbl_profitability[[#This Row],[decision]] -> OPTIMIZE | F12: =tbl_raw[[#This Row],[gross_revenue]]-tbl_raw[[#This Row],[return_loss]]-tbl_raw[[#This Row],[cogs]]*(1+scn_A_cogs_up)-(tbl_raw[[#This Row],[storage_cost]]+tbl_raw[[#This Row],[fulfillment_cost]]+tbl_raw[[#This Row],[freight_cost]]) -> 4645.909 | G12: =tbl_scenarios[[#This Row],[net_profit_A]]/tbl_raw[[#This Row],[gross_revenue]] -> 0.12353217 | H12: =tbl_scenarios[[#This Row],[net_margin_A]]-tbl_scenarios[[#This Row],[net_margin_pct]] -> -0.045000013 | I12: =IF(OR(tbl_scenarios[[#This Row],[net_margin_A]]<0.1,tbl_raw[[#This Row],[avg_review_score]]<3),"EXIT",IF(AND(tbl_scenarios[[#This Row],[net_margin_A]]>=0.25,tbl_raw[[#This Row],[avg_review_score]]>=4),"SCALE","OPTIMIZE")) -> OPTIMIZE | J12: =tbl_raw[[#This Row],[gross_revenue]]-tbl_raw[[#This Row],[return_loss]]*(1+scn_B_returns_up/0.05)-tbl_raw[[#This Row],[cogs]]-(tbl_raw[[#This Row],[storage_cost]]+tbl_raw[[#This Row],[fulfillment_cost]]+tbl_raw[[#This Row],[freight_cost]]) -> 6148.59 | K12: =tbl_scenarios[[#This Row],[net_profit_B]]/tbl_raw[[#This Row],[gross_revenue]] -> 0.16348763 | L12: =tbl_scenarios[[#This Row],[net_margin_B]]-tbl_scenarios[[#This Row],[net_margin_pct]] -> -0.0050445506 | M12: =IF(OR(tbl_scenarios[[#This Row],[net_margin_B]]<0.1,tbl_raw[[#This Row],[avg_review_score]]<3),"EXIT",IF(AND(tbl_scenarios[[#This Row],[net_margin_B]]>=0.25,tbl_raw[[#This Row],[avg_review_score]]>=4),"SCALE","OPTIMIZE")) -> OPTIMIZE | N12: =tbl_raw[[#This Row],[gross_revenue]]*(1-scn_C_price_down)-tbl_raw[[#This Row],[return_loss]]-tbl_raw[[#This Row],[cogs]]-(tbl_raw[[#This Row],[storage_cost]]+tbl_raw[[#This Row],[fulfillment_cost]]+tbl_raw[[#This Row],[freight_cost]]) -> 4457.865 | O12: =tbl_scenarios[[#This Row],[net_profit_C]]/(tbl_raw[[#This Row],[gross_revenue]]*(1-scn_C_price_down)) -> 0.12477072 | P12: =tbl_scenarios[[#This Row],[net_margin_C]]-tbl_scenarios[[#This Row],[net_margin_pct]] -> -0.043761464 | Q12: =IF(OR(tbl_scenarios[[#This Row],[net_margin_C]]<0.1,tbl_raw[[#This Row],[avg_review_score]]<3),"EXIT",IF(AND(tbl_scenarios[[#This Row],[net_margin_C]]>=0.25,tbl_raw[[#This Row],[avg_review_score]]>=4),"SCALE","OPTIMIZE")) -> OPTIMIZE | R12: =IF(OR(tbl_scenarios[[#This Row],[decision_A]]<>tbl_scenarios[[#This Row],[decision]],tbl_scenarios[[#This Row],[decision_B]]<>tbl_scenarios[[#This Row],[decision]],tbl_scenarios[[#This Row],[decision_C]]<>tbl_scenarios[[#This Row],[decision]]),"Decision changes","Stable") -> Stable
A13: =tbl_raw[[#This Row],[product_id]] -> e0d64dcfaa3b6db5c54ca298ae101d05 | B13: =tbl_raw[[#This Row],[category]] -> watches_gifts | C13: =tbl_profitability[[#This Row],[net_profit]] -> 13839.25 | D13: =tbl_profitability[[#This Row],[net_margin_pct]] -> 0.43537699 | E13: =tbl_profitability[[#This Row],[decision]] -> OPTIMIZE | F13: =tbl_raw[[#This Row],[gross_revenue]]-tbl_raw[[#This Row],[return_loss]]-tbl_raw[[#This Row],[cogs]]*(1+scn_A_cogs_up)-(tbl_raw[[#This Row],[storage_cost]]+tbl_raw[[#This Row],[fulfillment_cost]]+tbl_raw[[#This Row],[freight_cost]]) -> 12504.204 | G13: =tbl_scenarios[[#This Row],[net_profit_A]]/tbl_raw[[#This Row],[gross_revenue]] -> 0.393377 | H13: =tbl_scenarios[[#This Row],[net_margin_A]]-tbl_scenarios[[#This Row],[net_margin_pct]] -> -0.041999986 | I13: =IF(OR(tbl_scenarios[[#This Row],[net_margin_A]]<0.1,tbl_raw[[#This Row],[avg_review_score]]<3),"EXIT",IF(AND(tbl_scenarios[[#This Row],[net_margin_A]]>=0.25,tbl_raw[[#This Row],[avg_review_score]]>=4),"SCALE","OPTIMIZE")) -> OPTIMIZE | J13: =tbl_raw[[#This Row],[gross_revenue]]-tbl_raw[[#This Row],[return_loss]]*(1+scn_B_returns_up/0.05)-tbl_raw[[#This Row],[cogs]]-(tbl_raw[[#This Row],[storage_cost]]+tbl_raw[[#This Row],[fulfillment_cost]]+tbl_raw[[#This Row],[freight_cost]]) -> 13769.41 | K13: =tbl_scenarios[[#This Row],[net_profit_B]]/tbl_raw[[#This Row],[gross_revenue]] -> 0.43317985 | L13: =tbl_scenarios[[#This Row],[net_margin_B]]-tbl_scenarios[[#This Row],[net_margin_pct]] -> -0.0021971371 | M13: =IF(OR(tbl_scenarios[[#This Row],[net_margin_B]]<0.1,tbl_raw[[#This Row],[avg_review_score]]<3),"EXIT",IF(AND(tbl_scenarios[[#This Row],[net_margin_B]]>=0.25,tbl_raw[[#This Row],[avg_review_score]]>=4),"SCALE","OPTIMIZE")) -> OPTIMIZE | N13: =tbl_raw[[#This Row],[gross_revenue]]*(1-scn_C_price_down)-tbl_raw[[#This Row],[return_loss]]-tbl_raw[[#This Row],[cogs]]-(tbl_raw[[#This Row],[storage_cost]]+tbl_raw[[#This Row],[fulfillment_cost]]+tbl_raw[[#This Row],[freight_cost]]) -> 12249.909 | O13: =tbl_scenarios[[#This Row],[net_profit_C]]/(tbl_raw[[#This Row],[gross_revenue]]*(1-scn_C_price_down)) -> 0.40565999 | P13: =tbl_scenarios[[#This Row],[net_margin_C]]-tbl_scenarios[[#This Row],[net_margin_pct]] -> -0.029717001 | Q13: =IF(OR(tbl_scenarios[[#This Row],[net_margin_C]]<0.1,tbl_raw[[#This Row],[avg_review_score]]<3),"EXIT",IF(AND(tbl_scenarios[[#This Row],[net_margin_C]]>=0.25,tbl_raw[[#This Row],[avg_review_score]]>=4),"SCALE","OPTIMIZE")) -> OPTIMIZE | R13: =IF(OR(tbl_scenarios[[#This Row],[decision_A]]<>tbl_scenarios[[#This Row],[decision]],tbl_scenarios[[#This Row],[decision_B]]<>tbl_scenarios[[#This Row],[decision]],tbl_scenarios[[#This Row],[decision_C]]<>tbl_scenarios[[#This Row],[decision]]),"Decision changes","Stable") -> Stable
A14: =tbl_raw[[#This Row],[product_id]] -> d285360f29ac7fd97640bf0baef03de0 | B14: =tbl_raw[[#This Row],[category]] -> watches_gifts | C14: =tbl_profitability[[#This Row],[net_profit]] -> 15702.77 | D14: =tbl_profitability[[#This Row],[net_margin_pct]] -> 0.49654896 | E14: =tbl_profitability[[#This Row],[decision]] -> OPTIMIZE | F14: =tbl_raw[[#This Row],[gross_revenue]]-tbl_raw[[#This Row],[return_loss]]-tbl_raw[[#This Row],[cogs]]*(1+scn_A_cogs_up)-(tbl_raw[[#This Row],[storage_cost]]+tbl_raw[[#This Row],[fulfillment_cost]]+tbl_raw[[#This Row],[freight_cost]]) -> 14374.57 | G14: =tbl_scenarios[[#This Row],[net_profit_A]]/tbl_raw[[#This Row],[gross_revenue]] -> 0.45454896 | H14: =tbl_scenarios[[#This Row],[net_margin_A]]-tbl_scenarios[[#This Row],[net_margin_pct]] -> -0.041999999 | I14: =IF(OR(tbl_scenarios[[#This Row],[net_margin_A]]<0.1,tbl_raw[[#This Row],[avg_review_score]]<3),"EXIT",IF(AND(tbl_scenarios[[#This Row],[net_margin_A]]>=0.25,tbl_raw[[#This Row],[avg_review_score]]>=4),"SCALE","OPTIMIZE")) -> OPTIMIZE | J14: =tbl_raw[[#This Row],[gross_revenue]]-tbl_raw[[#This Row],[return_loss]]*(1+scn_B_returns_up/0.05)-tbl_raw[[#This Row],[cogs]]-(tbl_raw[[#This Row],[storage_cost]]+tbl_raw[[#This Row],[fulfillment_cost]]+tbl_raw[[#This Row],[freight_cost]]) -> 15658.49 | K14: =tbl_scenarios[[#This Row],[net_profit_B]]/tbl_raw[[#This Row],[gross_revenue]] -> 0.49514875 | L14: =tbl_scenarios[[#This Row],[net_margin_B]]-tbl_scenarios[[#This Row],[net_margin_pct]] -> -0.0014002108 | M14: =IF(OR(tbl_scenarios[[#This Row],[net_margin_B]]<0.1,tbl_raw[[#This Row],[avg_review_score]]<3),"EXIT",IF(AND(tbl_scenarios[[#This Row],[net_margin_B]]>=0.25,tbl_raw[[#This Row],[avg_review_score]]>=4),"SCALE","OPTIMIZE")) -> OPTIMIZE | N14: =tbl_raw[[#This Row],[gross_revenue]]*(1-scn_C_price_down)-tbl_raw[[#This Row],[return_loss]]-tbl_raw[[#This Row],[cogs]]-(tbl_raw[[#This Row],[storage_cost]]+tbl_raw[[#This Row],[fulfillment_cost]]+tbl_raw[[#This Row],[freight_cost]]) -> 14121.58 | O14: =tbl_scenarios[[#This Row],[net_profit_C]]/(tbl_raw[[#This Row],[gross_revenue]]*(1-scn_C_price_down)) -> 0.47005154 | P14: =tbl_scenarios[[#This Row],[net_margin_C]]-tbl_scenarios[[#This Row],[net_margin_pct]] -> -0.026497423 | Q14: =IF(OR(tbl_scenarios[[#This Row],[net_margin_C]]<0.1,tbl_raw[[#This Row],[avg_review_score]]<3),"EXIT",IF(AND(tbl_scenarios[[#This Row],[net_margin_C]]>=0.25,tbl_raw[[#This Row],[avg_review_score]]>=4),"SCALE","OPTIMIZE")) -> OPTIMIZE | R14: =IF(OR(tbl_scenarios[[#This Row],[decision_A]]<>tbl_scenarios[[#This Row],[decision]],tbl_scenarios[[#This Row],[decision_B]]<>tbl_scenarios[[#This Row],[decision]],tbl_scenarios[[#This Row],[decision_C]]<>tbl_scenarios[[#This Row],[decision]]),"Decision changes","Stable") -> Stable
A15: =tbl_raw[[#This Row],[product_id]] -> 7a10781637204d8d10485c71a6108a2e | B15: =tbl_raw[[#This Row],[category]] -> watches_gifts | C15: =tbl_profitability[[#This Row],[net_profit]] -> 14585.43 | D15: =tbl_profitability[[#This Row],[net_margin_pct]] -> 0.47872093 | E15: =tbl_profitability[[#This Row],[decision]] -> SCALE | F15: =tbl_raw[[#This Row],[gross_revenue]]-tbl_raw[[#This Row],[return_loss]]-tbl_raw[[#This Row],[cogs]]*(1+scn_A_cogs_up)-(tbl_raw[[#This Row],[storage_cost]]+tbl_raw[[#This Row],[fulfillment_cost]]+tbl_raw[[#This Row],[freight_cost]]) -> 13305.795 | G15: =tbl_scenarios[[#This Row],[net_profit_A]]/tbl_raw[[#This Row],[gross_revenue]] -> 0.43672093 | H15: =tbl_scenarios[[#This Row],[net_margin_A]]-tbl_scenarios[[#This Row],[net_margin_pct]] -> -0.042 | I15: =IF(OR(tbl_scenarios[[#This Row],[net_margin_A]]<0.1,tbl_raw[[#This Row],[avg_review_score]]<3),"EXIT",IF(AND(tbl_scenarios[[#This Row],[net_margin_A]]>=0.25,tbl_raw[[#This Row],[avg_review_score]]>=4),"SCALE","OPTIMIZE")) -> SCALE | J15: =tbl_raw[[#This Row],[gross_revenue]]-tbl_raw[[#This Row],[return_loss]]*(1+scn_B_returns_up/0.05)-tbl_raw[[#This Row],[cogs]]-(tbl_raw[[#This Row],[storage_cost]]+tbl_raw[[#This Row],[fulfillment_cost]]+tbl_raw[[#This Row],[freight_cost]]) -> 14533.95 | K15: =tbl_scenarios[[#This Row],[net_profit_B]]/tbl_raw[[#This Row],[gross_revenue]] -> 0.47703126 | L15: =tbl_scenarios[[#This Row],[net_margin_B]]-tbl_scenarios[[#This Row],[net_margin_pct]] -> -0.0016896693 | M15: =IF(OR(tbl_scenarios[[#This Row],[net_margin_B]]<0.1,tbl_raw[[#This Row],[avg_review_score]]<3),"EXIT",IF(AND(tbl_scenarios[[#This Row],[net_margin_B]]>=0.25,tbl_raw[[#This Row],[avg_review_score]]>=4),"SCALE","OPTIMIZE")) -> SCALE | N15: =tbl_raw[[#This Row],[gross_revenue]]*(1-scn_C_price_down)-tbl_raw[[#This Row],[return_loss]]-tbl_raw[[#This Row],[cogs]]-(tbl_raw[[#This Row],[storage_cost]]+tbl_raw[[#This Row],[fulfillment_cost]]+tbl_raw[[#This Row],[freight_cost]]) -> 13062.055 | O15: =tbl_scenarios[[#This Row],[net_profit_C]]/(tbl_raw[[#This Row],[gross_revenue]]*(1-scn_C_price_down)) -> 0.45128519 | P15: =tbl_scenarios[[#This Row],[net_margin_C]]-tbl_scenarios[[#This Row],[net_margin_pct]] -> -0.02743574 | Q15: =IF(OR(tbl_scenarios[[#This Row],[net_margin_C]]<0.1,tbl_raw[[#This Row],[avg_review_score]]<3),"EXIT",IF(AND(tbl_scenarios[[#This Row],[net_margin_C]]>=0.25,tbl_raw[[#This Row],[avg_review_score]]>=4),"SCALE","OPTIMIZE")) -> SCALE | R15: =IF(OR(tbl_scenarios[[#This Row],[decision_A]]<>tbl_scenarios[[#This Row],[decision]],tbl_scenarios[[#This Row],[decision_B]]<>tbl_scenarios[[#This Row],[decision]],tbl_scenarios[[#This Row],[decision_C]]<>tbl_scenarios[[#This Row],[decision]]),"Decision changes","Stable") -> Stable
A16: =tbl_raw[[#This Row],[product_id]] -> f1c7f353075ce59d8a6f3cf58f419c9c | B16: =tbl_raw[[#This Row],[category]] -> bed_bath_table | C16: =tbl_profitability[[#This Row],[net_profit]] -> 11802.21 | D16: =tbl_profitability[[#This Row],[net_margin_pct]] -> 0.39344162 | E16: =tbl_profitability[[#This Row],[decision]] -> SCALE | F16: =tbl_raw[[#This Row],[gross_revenue]]-tbl_raw[[#This Row],[return_loss]]-tbl_raw[[#This Row],[cogs]]*(1+scn_A_cogs_up)-(tbl_raw[[#This Row],[storage_cost]]+tbl_raw[[#This Row],[fulfillment_cost]]+tbl_raw[[#This Row],[freight_cost]]) -> 10452.329 | G16: =tbl_scenarios[[#This Row],[net_profit_A]]/tbl_raw[[#This Row],[gross_revenue]] -> 0.34844163 | H16: =tbl_scenarios[[#This Row],[net_margin_A]]-tbl_scenarios[[#This Row],[net_margin_pct]] -> -0.044999993 | I16: =IF(OR(tbl_scenarios[[#This Row],[net_margin_A]]<0.1,tbl_raw[[#This Row],[avg_review_score]]<3),"EXIT",IF(AND(tbl_scenarios[[#This Row],[net_margin_A]]>=0.25,tbl_raw[[#This Row],[avg_review_score]]>=4),"SCALE","OPTIMIZE")) -> SCALE | J16: =tbl_raw[[#This Row],[gross_revenue]]-tbl_raw[[#This Row],[return_loss]]*(1+scn_B_returns_up/0.05)-tbl_raw[[#This Row],[cogs]]-(tbl_raw[[#This Row],[storage_cost]]+tbl_raw[[#This Row],[fulfillment_cost]]+tbl_raw[[#This Row],[freight_cost]]) -> 11746.77 | K16: =tbl_scenarios[[#This Row],[net_profit_B]]/tbl_raw[[#This Row],[gross_revenue]] -> 0.39159346 | L16: =tbl_scenarios[[#This Row],[net_margin_B]]-tbl_scenarios[[#This Row],[net_margin_pct]] -> -0.0018481626 | M16: =IF(OR(tbl_scenarios[[#This Row],[net_margin_B]]<0.1,tbl_raw[[#This Row],[avg_review_score]]<3),"EXIT",IF(AND(tbl_scenarios[[#This Row],[net_margin_B]]>=0.25,tbl_raw[[#This Row],[avg_review_score]]>=4),"SCALE","OPTIMIZE")) -> SCALE | N16: =tbl_raw[[#This Row],[gross_revenue]]*(1-scn_C_price_down)-tbl_raw[[#This Row],[return_loss]]-tbl_raw[[#This Row],[cogs]]-(tbl_raw[[#This Row],[storage_cost]]+tbl_raw[[#This Row],[fulfillment_cost]]+tbl_raw[[#This Row],[freight_cost]]) -> 10302.342 | O16: =tbl_scenarios[[#This Row],[net_profit_C]]/(tbl_raw[[#This Row],[gross_revenue]]*(1-scn_C_price_down)) -> 0.3615175 | P16: =tbl_scenarios[[#This Row],[net_margin_C]]-tbl_scenarios[[#This Row],[net_margin_pct]] -> -0.031924125 | Q16: =IF(OR(tbl_scenarios[[#This Row],[net_margin_C]]<0.1,tbl_raw[[#This Row],[avg_review_score]]<3),"EXIT",IF(AND(tbl_scenarios[[#This Row],[net_margin_C]]>=0.25,tbl_raw[[#This Row],[avg_review_score]]>=4),"SCALE","OPTIMIZE")) -> SCALE | R16: =IF(OR(tbl_scenarios[[#This Row],[decision_A]]<>tbl_scenarios[[#This Row],[decision]],tbl_scenarios[[#This Row],[decision_B]]<>tbl_scenarios[[#This Row],[decision]],tbl_scenarios[[#This Row],[decision_C]]<>tbl_scenarios[[#This Row],[decision]]),"Decision changes","Stable") -> Stable
A17: =tbl_raw[[#This Row],[product_id]] -> f819f0c84a64f02d3a5606ca95edd272 | B17: =tbl_raw[[#This Row],[category]] -> watches_gifts | C17: =tbl_profitability[[#This Row],[net_profit]] -> 15167.79 | D17: =tbl_profitability[[#This Row],[net_margin_pct]] -> 0.52258611 | E17: =tbl_profitability[[#This Row],[decision]] -> SCALE | F17: =tbl_raw[[#This Row],[gross_revenue]]-tbl_raw[[#This Row],[return_loss]]-tbl_raw[[#This Row],[cogs]]*(1+scn_A_cogs_up)-(tbl_raw[[#This Row],[storage_cost]]+tbl_raw[[#This Row],[fulfillment_cost]]+tbl_raw[[#This Row],[freight_cost]]) -> 13948.762 | G17: =tbl_scenarios[[#This Row],[net_profit_A]]/tbl_raw[[#This Row],[gross_revenue]] -> 0.48058611 | H17: =tbl_scenarios[[#This Row],[net_margin_A]]-tbl_scenarios[[#This Row],[net_margin_pct]] -> -0.041999994 | I17: =IF(OR(tbl_scenarios[[#This Row],[net_margin_A]]<0.1,tbl_raw[[#This Row],[avg_review_score]]<3),"EXIT",IF(AND(tbl_scenarios[[#This Row],[net_margin_A]]>=0.25,tbl_raw[[#This Row],[avg_review_score]]>=4),"SCALE","OPTIMIZE")) -> SCALE | J17: =tbl_raw[[#This Row],[gross_revenue]]-tbl_raw[[#This Row],[return_loss]]*(1+scn_B_returns_up/0.05)-tbl_raw[[#This Row],[cogs]]-(tbl_raw[[#This Row],[storage_cost]]+tbl_raw[[#This Row],[fulfillment_cost]]+tbl_raw[[#This Row],[freight_cost]]) -> 15151.59 | K17: =tbl_scenarios[[#This Row],[net_profit_B]]/tbl_raw[[#This Row],[gross_revenue]] -> 0.52202796 | L17: =tbl_scenarios[[#This Row],[net_margin_B]]-tbl_scenarios[[#This Row],[net_margin_pct]] -> -0.00055814953 | M17: =IF(OR(tbl_scenarios[[#This Row],[net_margin_B]]<0.1,tbl_raw[[#This Row],[avg_review_score]]<3),"EXIT",IF(AND(tbl_scenarios[[#This Row],[net_margin_B]]>=0.25,tbl_raw[[#This Row],[avg_review_score]]>=4),"SCALE","OPTIMIZE")) -> SCALE | N17: =tbl_raw[[#This Row],[gross_revenue]]*(1-scn_C_price_down)-tbl_raw[[#This Row],[return_loss]]-tbl_raw[[#This Row],[cogs]]-(tbl_raw[[#This Row],[storage_cost]]+tbl_raw[[#This Row],[fulfillment_cost]]+tbl_raw[[#This Row],[freight_cost]]) -> 13716.566 | O17: =tbl_scenarios[[#This Row],[net_profit_C]]/(tbl_raw[[#This Row],[gross_revenue]]*(1-scn_C_price_down)) -> 0.49745906 | P17: =tbl_scenarios[[#This Row],[net_margin_C]]-tbl_scenarios[[#This Row],[net_margin_pct]] -> -0.025127047 | Q17: =IF(OR(tbl_scenarios[[#This Row],[net_margin_C]]<0.1,tbl_raw[[#This Row],[avg_review_score]]<3),"EXIT",IF(AND(tbl_scenarios[[#This Row],[net_margin_C]]>=0.25,tbl_raw[[#This Row],[avg_review_score]]>=4),"SCALE","OPTIMIZE")) -> SCALE | R17: =IF(OR(tbl_scenarios[[#This Row],[decision_A]]<>tbl_scenarios[[#This Row],[decision]],tbl_scenarios[[#This Row],[decision_B]]<>tbl_scenarios[[#This Row],[decision]],tbl_scenarios[[#This Row],[decision_C]]<>tbl_scenarios[[#This Row],[decision]]),"Decision changes","Stable") -> Stable
A18: =tbl_raw[[#This Row],[product_id]] -> 588531f8ec37e7d5ff5b7b22ea0488f8 | B18: =tbl_raw[[#This Row],[category]] -> computers | C18: =tbl_profitability[[#This Row],[net_profit]] -> 11124.34 | D18: =tbl_profitability[[#This Row],[net_margin_pct]] -> 0.39319751 | E18: =tbl_profitability[[#This Row],[decision]] -> SCALE | F18: =tbl_raw[[#This Row],[gross_revenue]]-tbl_raw[[#This Row],[return_loss]]-tbl_raw[[#This Row],[cogs]]*(1+scn_A_cogs_up)-(tbl_raw[[#This Row],[storage_cost]]+tbl_raw[[#This Row],[fulfillment_cost]]+tbl_raw[[#This Row],[freight_cost]]) -> 9511.697 | G18: =tbl_scenarios[[#This Row],[net_profit_A]]/tbl_raw[[#This Row],[gross_revenue]] -> 0.33619752 | H18: =tbl_scenarios[[#This Row],[net_margin_A]]-tbl_scenarios[[#This Row],[net_margin_pct]] -> -0.056999985 | I18: =IF(OR(tbl_scenarios[[#This Row],[net_margin_A]]<0.1,tbl_raw[[#This Row],[avg_review_score]]<3),"EXIT",IF(AND(tbl_scenarios[[#This Row],[net_margin_A]]>=0.25,tbl_raw[[#This Row],[avg_review_score]]>=4),"SCALE","OPTIMIZE")) -> SCALE | J18: =tbl_raw[[#This Row],[gross_revenue]]-tbl_raw[[#This Row],[return_loss]]*(1+scn_B_returns_up/0.05)-tbl_raw[[#This Row],[cogs]]-(tbl_raw[[#This Row],[storage_cost]]+tbl_raw[[#This Row],[fulfillment_cost]]+tbl_raw[[#This Row],[freight_cost]]) -> 11106.34 | K18: =tbl_scenarios[[#This Row],[net_profit_B]]/tbl_raw[[#This Row],[gross_revenue]] -> 0.39256129 | L18: =tbl_scenarios[[#This Row],[net_margin_B]]-tbl_scenarios[[#This Row],[net_margin_pct]] -> -0.00063622248 | M18: =IF(OR(tbl_scenarios[[#This Row],[net_margin_B]]<0.1,tbl_raw[[#This Row],[avg_review_score]]<3),"EXIT",IF(AND(tbl_scenarios[[#This Row],[net_margin_B]]>=0.25,tbl_raw[[#This Row],[avg_review_score]]>=4),"SCALE","OPTIMIZE")) -> SCALE | N18: =tbl_raw[[#This Row],[gross_revenue]]*(1-scn_C_price_down)-tbl_raw[[#This Row],[return_loss]]-tbl_raw[[#This Row],[cogs]]-(tbl_raw[[#This Row],[storage_cost]]+tbl_raw[[#This Row],[fulfillment_cost]]+tbl_raw[[#This Row],[freight_cost]]) -> 9709.7405 | O18: =tbl_scenarios[[#This Row],[net_profit_C]]/(tbl_raw[[#This Row],[gross_revenue]]*(1-scn_C_price_down)) -> 0.36126054 | P18: =tbl_scenarios[[#This Row],[net_margin_C]]-tbl_scenarios[[#This Row],[net_margin_pct]] -> -0.031936973 | Q18: =IF(OR(tbl_scenarios[[#This Row],[net_margin_C]]<0.1,tbl_raw[[#This Row],[avg_review_score]]<3),"EXIT",IF(AND(tbl_scenarios[[#This Row],[net_margin_C]]>=0.25,tbl_raw[[#This Row],[avg_review_score]]>=4),"SCALE","OPTIMIZE")) -> SCALE | R18: =IF(OR(tbl_scenarios[[#This Row],[decision_A]]<>tbl_scenarios[[#This Row],[decision]],tbl_scenarios[[#This Row],[decision_B]]<>tbl_scenarios[[#This Row],[decision]],tbl_scenarios[[#This Row],[decision_C]]<>tbl_scenarios[[#This Row],[decision]]),"Decision changes","Stable") -> Stable
... A402: =tbl_raw[[#This Row],[product_id]] -> 6902c1962dd19d540807d0ab8fade5c6 | B402: =tbl_raw[[#This Row],[category]] -> watches_gifts | C402: =tbl_profitability[[#This Row],[net_profit]] -> 2297.57 | D402: =tbl_profitability[[#This Row],[net_margin_pct]] -> 0.57440686 | E402: =tbl_profitability[[#This Row],[decision]] -> SCALE | F402: =tbl_raw[[#This Row],[gross_revenue]]-tbl_raw[[#This Row],[return_loss]]-tbl_raw[[#This Row],[cogs]]*(1+scn_A_cogs_up)-(tbl_raw[[#This Row],[storage_cost]]+tbl_raw[[#This Row],[fulfillment_cost]]+tbl_raw[[#This Row],[freight_cost]]) -> 2129.574 | G402: =tbl_scenarios[[#This Row],[net_profit_A]]/tbl_raw[[#This Row],[gross_revenue]] -> 0.53240681 | H402: =tbl_scenarios[[#This Row],[net_margin_A]]-tbl_scenarios[[#This Row],[net_margin_pct]] -> -0.04200005 | I402: =IF(OR(tbl_scenarios[[#This Row],[net_margin_A]]<0.1,tbl_raw[[#This Row],[avg_review_score]]<3),"EXIT",IF(AND(tbl_scenarios[[#This Row],[net_margin_A]]>=0.25,tbl_raw[[#This Row],[avg_review_score]]>=4),"SCALE","OPTIMIZE")) -> SCALE | J402: =tbl_raw[[#This Row],[gross_revenue]]-tbl_raw[[#This Row],[return_loss]]*(1+scn_B_returns_up/0.05)-tbl_raw[[#This Row],[cogs]]-(tbl_raw[[#This Row],[storage_cost]]+tbl_raw[[#This Row],[fulfillment_cost]]+tbl_raw[[#This Row],[freight_cost]]) -> 2297.21 | K402: =tbl_scenarios[[#This Row],[net_profit_B]]/tbl_raw[[#This Row],[gross_revenue]] -> 0.57431686 | L402: =tbl_scenarios[[#This Row],[net_margin_B]]-tbl_scenarios[[#This Row],[net_margin_pct]] -> -9.000225e-05 | M402: =IF(OR(tbl_scenarios[[#This Row],[net_margin_B]]<0.1,tbl_raw[[#This Row],[avg_review_score]]<3),"EXIT",IF(AND(tbl_scenarios[[#This Row],[net_margin_B]]>=0.25,tbl_raw[[#This Row],[avg_review_score]]>=4),"SCALE","OPTIMIZE")) -> SCALE | N402: =tbl_raw[[#This Row],[gross_revenue]]*(1-scn_C_price_down)-tbl_raw[[#This Row],[return_loss]]-tbl_raw[[#This Row],[cogs]]-(tbl_raw[[#This Row],[storage_cost]]+tbl_raw[[#This Row],[fulfillment_cost]]+tbl_raw[[#This Row],[freight_cost]]) -> 2097.575 | O402: =tbl_scenarios[[#This Row],[net_profit_C]]/(tbl_raw[[#This Row],[gross_revenue]]*(1-scn_C_price_down)) -> 0.55200722 | P402: =tbl_scenarios[[#This Row],[net_margin_C]]-tbl_scenarios[[#This Row],[net_margin_pct]] -> -0.022399639 | Q402: =IF(OR(tbl_scenarios[[#This Row],[net_margin_C]]<0.1,tbl_raw[[#This Row],[avg_review_score]]<3),"EXIT",IF(AND(tbl_scenarios[[#This Row],[net_margin_C]]>=0.25,tbl_raw[[#This Row],[avg_review_score]]>=4),"SCALE","OPTIMIZE")) -> SCALE | R402: =IF(OR(tbl_scenarios[[#This Row],[decision_A]]<>tbl_scenarios[[#This Row],[decision]],tbl_scenarios[[#This Row],[decision_B]]<>tbl_scenarios[[#This Row],[decision]],tbl_scenarios[[#This Row],[decision_C]]<>tbl_scenarios[[#This Row],[decision]]),"Decision changes","Stable") -> Stable

Sheet Sensitivity_Analysis
A1: SENSITIVITY TABLE — Portfolio Average Net Margin
A2: Average net margin across all 400 SKUs at each combination of COGS uplift (horizontal: cogs × (1 + Δ)) and return-rate uplift (vertical: return_loss × (1 + Δ/5%), where Δ is interpreted as percentage points on a 5% baseline rate).
C3: COGS rate change (horizontal) →
B4: Return Δ ↓ / COGS Δ → | C4: 0 | D4: 0.05 | E4: 0.1 | F4: 0.15 | G4: 0.2
B5: 0 | C5: {=SUMPRODUCT(tbl_raw[gross_revenue]-tbl_raw[return_loss]*(1+$B5/0.05)-tbl_raw[cogs]*(1+C$4)-(tbl_raw[storage_cost]+tbl_raw[fulfillment_cost]+tbl_raw[freight_cost]))/SUM(tbl_raw[gross_revenue])} -> 0.35980985 | D5: {=SUMPRODUCT(tbl_raw[gross_revenue]-tbl_raw[return_loss]*(1+$B5/0.05)-tbl_raw[cogs]*(1+D$4)-(tbl_raw[storage_cost]+tbl_raw[fulfillment_cost]+tbl_raw[freight_cost]))/SUM(tbl_raw[gross_revenue])} -> 0.33648742 | E5: {=SUMPRODUCT(tbl_raw[gross_revenue]-tbl_raw[return_loss]*(1+$B5/0.05)-tbl_raw[cogs]*(1+E$4)-(tbl_raw[storage_cost]+tbl_raw[fulfillment_cost]+tbl_raw[freight_cost]))/SUM(tbl_raw[gross_revenue])} -> 0.313165 | F5: {=SUMPRODUCT(tbl_raw[gross_revenue]-tbl_raw[return_loss]*(1+$B5/0.05)-tbl_raw[cogs]*(1+F$4)-(tbl_raw[storage_cost]+tbl_raw[fulfillment_cost]+tbl_raw[freight_cost]))/SUM(tbl_raw[gross_revenue])} -> 0.28984257 | G5: {=SUMPRODUCT(tbl_raw[gross_revenue]-tbl_raw[return_loss]*(1+$B5/0.05)-tbl_raw[cogs]*(1+G$4)-(tbl_raw[storage_cost]+tbl_raw[fulfillment_cost]+tbl_raw[freight_cost]))/SUM(tbl_raw[gross_revenue])} -> 0.26652015
B6: 0.025 | C6: {=SUMPRODUCT(tbl_raw[gross_revenue]-tbl_raw[return_loss]*(1+$B6/0.05)-tbl_raw[cogs]*(1+C$4)-(tbl_raw[storage_cost]+tbl_raw[fulfillment_cost]+tbl_raw[freight_cost]))/SUM(tbl_raw[gross_revenue])} -> 0.35860992 | D6: {=SUMPRODUCT(tbl_raw[gross_revenue]-tbl_raw[return_loss]*(1+$B6/0.05)-tbl_raw[cogs]*(1+D$4)-(tbl_raw[storage_cost]+tbl_raw[fulfillment_cost]+tbl_raw[freight_cost]))/SUM(tbl_raw[gross_revenue])} -> 0.3352875 | E6: {=SUMPRODUCT(tbl_raw[gross_revenue]-tbl_raw[return_loss]*(1+$B6/0.05)-tbl_raw[cogs]*(1+E$4)-(tbl_raw[storage_cost]+tbl_raw[fulfillment_cost]+tbl_raw[freight_cost]))/SUM(tbl_raw[gross_revenue])} -> 0.31196507 | F6: {=SUMPRODUCT(tbl_raw[gross_revenue]-tbl_raw[return_loss]*(1+$B6/0.05)-tbl_raw[cogs]*(1+F$4)-(tbl_raw[storage_cost]+tbl_raw[fulfillment_cost]+tbl_raw[freight_cost]))/SUM(tbl_raw[gross_revenue])} -> 0.28864265 | G6: {=SUMPRODUCT(tbl_raw[gross_revenue]-tbl_raw[return_loss]*(1+$B6/0.05)-tbl_raw[cogs]*(1+G$4)-(tbl_raw[storage_cost]+tbl_raw[fulfillment_cost]+tbl_raw[freight_cost]))/SUM(tbl_raw[gross_revenue])} -> 0.26532022
B7: 0.05 | C7: {=SUMPRODUCT(tbl_raw[gross_revenue]-tbl_raw[return_loss]*(1+$B7/0.05)-tbl_raw[cogs]*(1+C$4)-(tbl_raw[storage_cost]+tbl_raw[fulfillment_cost]+tbl_raw[freight_cost]))/SUM(tbl_raw[gross_revenue])} -> 0.35741 | D7: {=SUMPRODUCT(tbl_raw[gross_revenue]-tbl_raw[return_loss]*(1+$B7/0.05)-tbl_raw[cogs]*(1+D$4)-(tbl_raw[storage_cost]+tbl_raw[fulfillment_cost]+tbl_raw[freight_cost]))/SUM(tbl_raw[gross_revenue])} -> 0.33408757 | E7: {=SUMPRODUCT(tbl_raw[gross_revenue]-tbl_raw[return_loss]*(1+$B7/0.05)-tbl_raw[cogs]*(1+E$4)-(tbl_raw[storage_cost]+tbl_raw[fulfillment_cost]+tbl_raw[freight_cost]))/SUM(tbl_raw[gross_revenue])} -> 0.31076515 | F7: {=SUMPRODUCT(tbl_raw[gross_revenue]-tbl_raw[return_loss]*(1+$B7/0.05)-tbl_raw[cogs]*(1+F$4)-(tbl_raw[storage_cost]+tbl_raw[fulfillment_cost]+tbl_raw[freight_cost]))/SUM(tbl_raw[gross_revenue])} -> 0.28744272 | G7: {=SUMPRODUCT(tbl_raw[gross_revenue]-tbl_raw[return_loss]*(1+$B7/0.05)-tbl_raw[cogs]*(1+G$4)-(tbl_raw[storage_cost]+tbl_raw[fulfillment_cost]+tbl_raw[freight_cost]))/SUM(tbl_raw[gross_revenue])} -> 0.2641203
B8: 0.075 | C8: {=SUMPRODUCT(tbl_raw[gross_revenue]-tbl_raw[return_loss]*(1+$B8/0.05)-tbl_raw[cogs]*(1+C$4)-(tbl_raw[storage_cost]+tbl_raw[fulfillment_cost]+tbl_raw[freight_cost]))/SUM(tbl_raw[gross_revenue])} -> 0.35621007 | D8: {=SUMPRODUCT(tbl_raw[gross_revenue]-tbl_raw[return_loss]*(1+$B8/0.05)-tbl_raw[cogs]*(1+D$4)-(tbl_raw[storage_cost]+tbl_raw[fulfillment_cost]+tbl_raw[freight_cost]))/SUM(tbl_raw[gross_revenue])} -> 0.33288765 | E8: {=SUMPRODUCT(tbl_raw[gross_revenue]-tbl_raw[return_loss]*(1+$B8/0.05)-tbl_raw[cogs]*(1+E$4)-(tbl_raw[storage_cost]+tbl_raw[fulfillment_cost]+tbl_raw[freight_cost]))/SUM(tbl_raw[gross_revenue])} -> 0.30956522 | F8: {=SUMPRODUCT(tbl_raw[gross_revenue]-tbl_raw[return_loss]*(1+$B8/0.05)-tbl_raw[cogs]*(1+F$4)-(tbl_raw[storage_cost]+tbl_raw[fulfillment_cost]+tbl_raw[freight_cost]))/SUM(tbl_raw[gross_revenue])} -> 0.2862428 | G8: {=SUMPRODUCT(tbl_raw[gross_revenue]-tbl_raw[return_loss]*(1+$B8/0.05)-tbl_raw[cogs]*(1+G$4)-(tbl_raw[storage_cost]+tbl_raw[fulfillment_cost]+tbl_raw[freight_cost]))/SUM(tbl_raw[gross_revenue])} -> 0.26292037
B9: 0.1 | C9: {=SUMPRODUCT(tbl_raw[gross_revenue]-tbl_raw[return_loss]*(1+$B9/0.05)-tbl_raw[cogs]*(1+C$4)-(tbl_raw[storage_cost]+tbl_raw[fulfillment_cost]+tbl_raw[freight_cost]))/SUM(tbl_raw[gross_revenue])} -> 0.35501015 | D9: {=SUMPRODUCT(tbl_raw[gross_revenue]-tbl_raw[return_loss]*(1+$B9/0.05)-tbl_raw[cogs]*(1+D$4)-(tbl_raw[storage_cost]+tbl_raw[fulfillment_cost]+tbl_raw[freight_cost]))/SUM(tbl_raw[gross_revenue])} -> 0.33168772 | E9: {=SUMPRODUCT(tbl_raw[gross_revenue]-tbl_raw[return_loss]*(1+$B9/0.05)-tbl_raw[cogs]*(1+E$4)-(tbl_raw[storage_cost]+tbl_raw[fulfillment_cost]+tbl_raw[freight_cost]))/SUM(tbl_raw[gross_revenue])} -> 0.3083653 | F9: {=SUMPRODUCT(tbl_raw[gross_revenue]-tbl_raw[return_loss]*(1+$B9/0.05)-tbl_raw[cogs]*(1+F$4)-(tbl_raw[storage_cost]+tbl_raw[fulfillment_cost]+tbl_raw[freight_cost]))/SUM(tbl_raw[gross_revenue])} -> 0.28504287 | G9: {=SUMPRODUCT(tbl_raw[gross_revenue]-tbl_raw[return_loss]*(1+$B9/0.05)-tbl_raw[cogs]*(1+G$4)-(tbl_raw[storage_cost]+tbl_raw[fulfillment_cost]+tbl_raw[freight_cost]))/SUM(tbl_raw[gross_revenue])} -> 0.26172045
B12: Note: values represent portfolio averages across all 400 SKUs. Individual SKU outcomes will vary — some SKUs remain profitable even at the worst combination, and others become unprofitable well before the average crosses a threshold. Use Tab 3 (Scenario_Analysis) and Tab 5 (SKU_Decision_Summary) for per-SKU views.
B14: Legend: | C14: ≥ 25% (healthy) | D14: 10–24.9% (caution) | E14: < 10% (critical)

Sheet SKU_Decision_Summary
A1: SKU DECISION SUMMARY — Baseline + Scenario Outcomes for All 400 SKUs
A3: product_id | B3: category | C3: baseline_margin | D3: baseline_decision | E3: scenario_A_margin | F3: scenario_A_decision | G3: scenario_B_margin | H3: scenario_B_decision | I3: scenario_C_margin | J3: scenario_C_decision | K3: stability_flag
A4: =Scenario_Analysis!A6 -> d1c427060a0f73f6b889a5c7c61f2ac4 | B4: =Scenario_Analysis!B6 -> computers_accessories | C4: =Scenario_Analysis!D6 -> 0.047087262 | D4: =Scenario_Analysis!E6 -> EXIT | E4: =Scenario_Analysis!G6 -> -0.0099127365 | F4: =Scenario_Analysis!I6 -> EXIT | G4: =Scenario_Analysis!K6 -> 0.040545855 | H4: =Scenario_Analysis!M6 -> EXIT | I4: =Scenario_Analysis!O6 -> -0.00306604 | J4: =Scenario_Analysis!Q6 -> EXIT | K4: =Scenario_Analysis!R6 -> Stable
A5: =Scenario_Analysis!A9 -> 25c38557cf793876c5abdd5931f922db | B5: =Scenario_Analysis!B9 -> baby | C5: =Scenario_Analysis!D9 -> 0.53866316 | D5: =Scenario_Analysis!E9 -> EXIT | E5: =Scenario_Analysis!G9 -> 0.49666317 | F5: =Scenario_Analysis!I9 -> EXIT | G5: =Scenario_Analysis!K9 -> 0.53831156 | H5: =Scenario_Analysis!M9 -> EXIT | I5: =Scenario_Analysis!O9 -> 0.51438228 | J5: =Scenario_Analysis!Q9 -> EXIT | K5: =Scenario_Analysis!R9 -> Stable
A6: =Scenario_Analysis!A19 -> 422879e10f46682990de24d770e7f83d | B6: =Scenario_Analysis!B19 -> garden_tools | C6: =Scenario_Analysis!D19 -> 0.033080586 | D6: =Scenario_Analysis!E19 -> EXIT | E6: =Scenario_Analysis!G19 -> -0.011919418 | F6: =Scenario_Analysis!I19 -> EXIT | G6: =Scenario_Analysis!K19 -> 0.026524595 | H6: =Scenario_Analysis!M19 -> EXIT | I6: =Scenario_Analysis!O19 -> -0.01780991 | J6: =Scenario_Analysis!Q19 -> EXIT | K6: =Scenario_Analysis!R19 -> Stable
A7: =Scenario_Analysis!A25 -> 389d119b48cf3043d311335e499d9c6b | B7: =Scenario_Analysis!B25 -> garden_tools | C7: =Scenario_Analysis!D25 -> -0.030638095 | D7: =Scenario_Analysis!E25 -> EXIT | E7: =Scenario_Analysis!G25 -> -0.075638093 | F7: =Scenario_Analysis!I25 -> EXIT | G7: =Scenario_Analysis!K25 -> -0.037218528 | H7: =Scenario_Analysis!M25 -> EXIT | I7: =Scenario_Analysis!O25 -> -0.084882206 | J7: =Scenario_Analysis!Q25 -> EXIT | K7: =Scenario_Analysis!R25 -> Stable
A8: =Scenario_Analysis!A26 -> 368c6c730842d78016ad823897a372db | B8: =Scenario_Analysis!B26 -> garden_tools | C8: =Scenario_Analysis!D26 -> -0.01595874 | D8: =Scenario_Analysis!E26 -> EXIT | E8: =Scenario_Analysis!G26 -> -0.06095874 | F8: =Scenario_Analysis!I26 -> EXIT | G8: =Scenario_Analysis!K26 -> -0.022592227 | H8: =Scenario_Analysis!M26 -> EXIT | I8: =Scenario_Analysis!O26 -> -0.069430253 | J8: =Scenario_Analysis!Q26 -> EXIT | K8: =Scenario_Analysis!R26 -> Stable
A9: =Scenario_Analysis!A29 -> 53759a2ecddad2bb87a079a1f1519f73 | B9: =Scenario_Analysis!B29 -> garden_tools | C9: =Scenario_Analysis!D29 -> -0.026357224 | D9: =Scenario_Analysis!E29 -> EXIT | E9: =Scenario_Analysis!G29 -> -0.071357224 | F9: =Scenario_Analysis!I29 -> EXIT | G9: =Scenario_Analysis!K29 -> -0.03294371 | H9: =Scenario_Analysis!M29 -> EXIT | I9: =Scenario_Analysis!O29 -> -0.080376025 | J9: =Scenario_Analysis!Q29 -> EXIT | K9: =Scenario_Analysis!R29 -> Stable
A10: =Scenario_Analysis!A30 -> fd0065af7f09af4b82a0ca8f3eed1852 | B10: =Scenario_Analysis!B30 -> auto | C10: =Scenario_Analysis!D30 -> 0.52837264 | D10: =Scenario_Analysis!E30 -> EXIT | E10: =Scenario_Analysis!G30 -> 0.48337262 | F10: =Scenario_Analysis!I30 -> EXIT | G10: =Scenario_Analysis!K30 -> 0.52819264 | H10: =Scenario_Analysis!M30 -> EXIT | I10: =Scenario_Analysis!O30 -> 0.50355015 | J10: =Scenario_Analysis!Q30 -> EXIT | K10: =Scenario_Analysis!R30 -> Stable
A11: =Scenario_Analysis!A31 -> 1dec4c88c685d5a07bf01dcb0f8bf9f8 | B11: =Scenario_Analysis!B31 -> auto | C11: =Scenario_Analysis!D31 -> 0.42065565 | D11: =Scenario_Analysis!E31 -> EXIT | E11: =Scenario_Analysis!G31 -> 0.37565565 | F11: =Scenario_Analysis!I31 -> EXIT | G11: =Scenario_Analysis!K31 -> 0.42002454 | H11: =Scenario_Analysis!M31 -> EXIT | I11: =Scenario_Analysis!O31 -> 0.39016384 | J11: =Scenario_Analysis!Q31 -> EXIT | K11: =Scenario_Analysis!R31 -> Stable
A12: =Scenario_Analysis!A36 -> fb01a5fc09b9b9563c2ee41a22f07d54 | B12: =Scenario_Analysis!B36 -> consoles_games | C12: =Scenario_Analysis!D36 -> 0.37622155 | D12: =Scenario_Analysis!E36 -> EXIT | E12: =Scenario_Analysis!G36 -> 0.31922155 | F12: =Scenario_Analysis!I36 -> EXIT | G12: =Scenario_Analysis!K36 -> 0.37570517 | H12: =Scenario_Analysis!M36 -> EXIT | I12: =Scenario_Analysis!O36 -> 0.34339111 | J12: =Scenario_Analysis!Q36 -> EXIT | K12: =Scenario_Analysis!R36 -> Stable
A13: =Scenario_Analysis!A39 -> e53e557d5a159f5aa2c5e995dfdf244b | B13: =Scenario_Analysis!B39 -> computers_accessories | C13: =Scenario_Analysis!D39 -> 0.099225027 | D13: =Scenario_Analysis!E39 -> EXIT | E13: =Scenario_Analysis!G39 -> 0.042225043 | F13: =Scenario_Analysis!I39 -> EXIT | G13: =Scenario_Analysis!K39 -> 0.08855741 | H13: =Scenario_Analysis!M39 -> EXIT | I13: =Scenario_Analysis!O39 -> 0.051815818 | J13: =Scenario_Analysis!Q39 -> EXIT | K13: =Scenario_Analysis!R39 -> Stable
A14: =Scenario_Analysis!A43 -> c4baedd846ed09b85f78a781b522f126 | B14: =Scenario_Analysis!B43 -> garden_tools | C14: =Scenario_Analysis!D43 -> 0.0036525584 | D14: =Scenario_Analysis!E43 -> EXIT | E14: =Scenario_Analysis!G43 -> -0.041347418 | F14: =Scenario_Analysis!I43 -> EXIT | G14: =Scenario_Analysis!K43 -> 6.9271499e-05 | H14: =Scenario_Analysis!M43 -> EXIT | I14: =Scenario_Analysis!O43 -> -0.048786781 | J14: =Scenario_Analysis!Q43 -> EXIT | K14: =Scenario_Analysis!R43 -> Stable
A15: =Scenario_Analysis!A48 -> 8c591ab0ca519558779df02023177f44 | B15: =Scenario_Analysis!B48 -> garden_tools | C15: =Scenario_Analysis!D48 -> 0.028132491 | D15: =Scenario_Analysis!E48 -> EXIT | E15: =Scenario_Analysis!G48 -> -0.016867488 | F15: =Scenario_Analysis!I48 -> EXIT | G15: =Scenario_Analysis!K48 -> 0.024629903 | H15: =Scenario_Analysis!M48 -> EXIT | I15: =Scenario_Analysis!O48 -> -0.02301843 | J15: =Scenario_Analysis!Q48 -> EXIT | K15: =Scenario_Analysis!R48 -> Stable
A16: =Scenario_Analysis!A56 -> 5769ef0a239114ac3a854af00df129e4 | B16: =Scenario_Analysis!B56 -> fixed_telephony | C16: =Scenario_Analysis!D56 -> 0.41189881 | D16: =Scenario_Analysis!E56 -> EXIT | E16: =Scenario_Analysis!G56 -> 0.35489881 | F16: =Scenario_Analysis!I56 -> EXIT | G16: =Scenario_Analysis!K56 -> 0.4113631 | H16: =Scenario_Analysis!M56 -> EXIT | I16: =Scenario_Analysis!O56 -> 0.38094612 | J16: =Scenario_Analysis!Q56 -> EXIT | K16: =Scenario_Analysis!R56 -> Stable
A17: =Scenario_Analysis!A78 -> 42a2c92a0979a949ca4ea89ec5c7b934 | B17: =Scenario_Analysis!B78 -> housewares | C17: =Scenario_Analysis!D78 -> 0.098624668 | D17: =Scenario_Analysis!E78 -> EXIT | E17: =Scenario_Analysis!G78 -> 0.053624714 | F17: =Scenario_Analysis!I78 -> EXIT | G17: =Scenario_Analysis!K78 -> 0.092564006 | H17: =Scenario_Analysis!M78 -> EXIT | I17: =Scenario_Analysis!O78 -> 0.051183861 | J17: =Scenario_Analysis!Q78 -> EXIT | K17: =Scenario_Analysis!R78 -> Stable
A18: =Scenario_Analysis!A83 -> 08574b074924071f4e201e151b152b4e | B18: =Scenario_Analysis!B83 -> garden_tools | C18: =Scenario_Analysis!D83 -> -0.011023022 | D18: =Scenario_Analysis!E83 -> EXIT | E18: =Scenario_Analysis!G83 -> -0.056023068 | F18: =Scenario_Analysis!I83 -> EXIT | G18: =Scenario_Analysis!K83 -> -0.014803937 | H18: =Scenario_Analysis!M83 -> EXIT | I18: =Scenario_Analysis!O83 -> -0.06423476 | J18: =Scenario_Analysis!Q83 -> EXIT | K18: =Scenario_Analysis!R83 -> Stable
A19: =Scenario_Analysis!A86 -> 19936fa4f614ee0590d3b77ac83fd648 | B19: =Scenario_Analysis!B86 -> fixed_telephony | C19: =Scenario_Analysis!D86 -> 0.41159465 | D19: =Scenario_Analysis!E86 -> EXIT | E19: =Scenario_Analysis!G86 -> 0.35459465 | F19: =Scenario_Analysis!I86 -> EXIT | G19: =Scenario_Analysis!K86 -> 0.41107839 | H19: =Scenario_Analysis!M86 -> EXIT | I19: =Scenario_Analysis!O86 -> 0.38062594 | J19: =Scenario_Analysis!Q86 -> EXIT | K19: =Scenario_Analysis!R86 -> Stable
A20: =Scenario_Analysis!A103 -> b4436da747c3a53ab07ac0e71de17dcd | B20: =Scenario_Analysis!B103 -> sports_leisure | C20: =Scenario_Analysis!D103 -> 0.52649364 | D20: =Scenario_Analysis!E103 -> EXIT | E20: =Scenario_Analysis!G103 -> 0.48449364 | F20: =Scenario_Analysis!I103 -> EXIT | G20: =Scenario_Analysis!K103 -> 0.5262685 | H20: =Scenario_Analysis!M103 -> EXIT | I20: =Scenario_Analysis!O103 -> 0.50157225 | J20: =Scenario_Analysis!Q103 -> EXIT | K20: =Scenario_Analysis!R103 -> Stable
A21: =Scenario_Analysis!A148 -> b5e13c9a353102f79c6206ff5cb61a50 | B21: =Scenario_Analysis!B148 -> toys | C21: =Scenario_Analysis!D148 -> 0.32228296 | D21: =Scenario_Analysis!E148 -> EXIT | E21: =Scenario_Analysis!G148 -> 0.28028294 | F21: =Scenario_Analysis!I148 -> EXIT | G21: =Scenario_Analysis!K148 -> 0.31808882 | H21: =Scenario_Analysis!M148 -> EXIT | I21: =Scenario_Analysis!O148 -> 0.28661365 | J21: =Scenario_Analysis!Q148 -> EXIT | K21: =Scenario_Analysis!R148 -> Stable
A22: =Scenario_Analysis!A151 -> 09481a6dfe9eb590dc8b265b54dc4c97 | B22: =Scenario_Analysis!B151 -> computers_accessories | C22: =Scenario_Analysis!D151 -> 0.35387404 | D22: =Scenario_Analysis!E151 -> EXIT | E22: =Scenario_Analysis!G151 -> 0.29687401 | F22: =Scenario_Analysis!I151 -> EXIT | G22: =Scenario_Analysis!K151 -> 0.35293865 | H22: =Scenario_Analysis!M151 -> EXIT | I22: =Scenario_Analysis!O151 -> 0.31986741 | J22: =Scenario_Analysis!Q151 -> EXIT | K22: =Scenario_Analysis!R151 -> Stable
A23: =Scenario_Analysis!A155 -> 3f14d740544f37ece8a9e7bc8349797e | B23: =Scenario_Analysis!B155 -> computers_accessories | C23: =Scenario_Analysis!D155 -> 0.085849264 | D23: =Scenario_Analysis!E155 -> EXIT | E23: =Scenario_Analysis!G155 -> 0.028849199 | F23: =Scenario_Analysis!I155 -> EXIT | G23: =Scenario_Analysis!K155 -> 0.075255873 | H23: =Scenario_Analysis!M155 -> EXIT | I23: =Scenario_Analysis!O155 -> 0.037736067 | J23: =Scenario_Analysis!Q155 -> EXIT | K23: =Scenario_Analysis!R155 -> Stable
A24: =Scenario_Analysis!A157 -> b0961721fd839e9982420e807758a2a6 | B24: =Scenario_Analysis!B157 -> garden_tools | C24: =Scenario_Analysis!D157 -> -0.064376781 | D24: =Scenario_Analysis!E157 -> EXIT | E24: =Scenario_Analysis!G157 -> -0.10937671 | F24: =Scenario_Analysis!I157 -> EXIT | G24: =Scenario_Analysis!K157 -> -0.070611015 | H24: =Scenario_Analysis!M157 -> EXIT | I24: =Scenario_Analysis!O157 -> -0.12039661 | J24: =Scenario_Analysis!Q157 -> EXIT | K24: =Scenario_Analysis!R157 -> Stable
A25: =Scenario_Analysis!A170 -> 8b52d90d2e8716dad633486c6cc94ecf | B25: =Scenario_Analysis!B170 -> telephony | C25: =Scenario_Analysis!D170 -> 0.40089557 | D25: =Scenario_Analysis!E170 -> EXIT | E25: =Scenario_Analysis!G170 -> 0.34389557 | F25: =Scenario_Analysis!I170 -> EXIT | G25: =Scenario_Analysis!K170 -> 0.39998556 | H25: =Scenario_Analysis!M170 -> EXIT | I25: =Scenario_Analysis!O170 -> 0.36936375 | J25: =Scenario_Analysis!Q170 -> EXIT | K25: =Scenario_Analysis!R170 -> Stable
A26: =Scenario_Analysis!A208 -> 154e7e31ebfa092203795c972e5804a6 | B26: =Scenario_Analysis!B208 -> health_beauty | C26: =Scenario_Analysis!D208 -> -0.24148998 | D26: =Scenario_Analysis!E208 -> EXIT | E26: =Scenario_Analysis!G208 -> -0.28348998 | F26: =Scenario_Analysis!I208 -> EXIT | G26: =Scenario_Analysis!K208 -> -0.25748317 | H26: =Scenario_Analysis!M208 -> EXIT | I26: =Scenario_Analysis!O208 -> -0.30683156 | J26: =Scenario_Analysis!Q208 -> EXIT | K26: =Scenario_Analysis!R208 -> Stable
A27: =Scenario_Analysis!A215 -> 0bcc3eeca39e1064258aa1e932269894 | B27: =Scenario_Analysis!B215 -> garden_tools | C27: =Scenario_Analysis!D215 -> -0.044684853 | D27: =Scenario_Analysis!E215 -> EXIT | E27: =Scenario_Analysis!G215 -> -0.089684772 | F27: =Scenario_Analysis!I215 -> EXIT | G27: =Scenario_Analysis!K215 -> -0.051339838 | H27: =Scenario_Analysis!M215 -> EXIT | I27: =Scenario_Analysis!O215 -> -0.099668266 | J27: =Scenario_Analysis!Q215 -> EXIT | K27: =Scenario_Analysis!R215 -> Stable
A28: =Scenario_Analysis!A218 -> b532349fe46b38fbc7bb3914c1bdae07 | B28: =Scenario_Analysis!B218 -> furniture_decor | C28: =Scenario_Analysis!D218 -> -0.13398657 | D28: =Scenario_Analysis!E218 -> EXIT | E28: =Scenario_Analysis!G218 -> -0.17898658 | F28: =Scenario_Analysis!I218 -> EXIT | G28: =Scenario_Analysis!K218 -> -0.14385981 | H28: =Scenario_Analysis!M218 -> EXIT | I28: =Scenario_Analysis!O218 -> -0.19367008 | J28: =Scenario_Analysis!Q218 -> EXIT | K28: =Scenario_Analysis!R218 -> Stable
A29: =Scenario_Analysis!A230 -> ec2d43cc59763ec91694573b31f1c29a | B29: =Scenario_Analysis!B230 -> bed_bath_table | C29: =Scenario_Analysis!D230 -> 0.058781357 | D29: =Scenario_Analysis!E230 -> EXIT | E29: =Scenario_Analysis!G230 -> 0.013781299 | F29: =Scenario_Analysis!I230 -> EXIT | G29: =Scenario_Analysis!K230 -> 0.050936746 | H29: =Scenario_Analysis!M230 -> EXIT | I29: =Scenario_Analysis!O230 -> 0.0092435339 | J29: =Scenario_Analysis!Q230 -> EXIT | K29: =Scenario_Analysis!R230 -> Stable
A30: =Scenario_Analysis!A238 -> c183fd5d2abf05873fa6e1014ed9e06c | B30: =Scenario_Analysis!B238 -> agro_industry_and_commerce | C30: =Scenario_Analysis!D238 -> 0.52319112 | D30: =Scenario_Analysis!E238 -> EXIT | E30: =Scenario_Analysis!G238 -> 0.47819112 | F30: =Scenario_Analysis!I238 -> EXIT | G30: =Scenario_Analysis!K238 -> 0.52282715 | H30: =Scenario_Analysis!M238 -> EXIT | I30: =Scenario_Analysis!O238 -> 0.49809591 | J30: =Scenario_Analysis!Q238 -> EXIT | K30: =Scenario_Analysis!R238 -> Stable
A31: =Scenario_Analysis!A239 -> d04857e7b4b708ee8b8b9921163edba3 | B31: =Scenario_Analysis!B239 -> computers_accessories | C31: =Scenario_Analysis!D239 -> 0.020928766 | D31: =Scenario_Analysis!E239 -> EXIT | E31: =Scenario_Analysis!G239 -> -0.036071214 | F31: =Scenario_Analysis!I239 -> EXIT | G31: =Scenario_Analysis!K239 -> 0.0081782242 | H31: =Scenario_Analysis!M239 -> EXIT | I31: =Scenario_Analysis!O239 -> -0.030601299 | J31: =Scenario_Analysis!Q239 -> EXIT | K31: =Scenario_Analysis!R239 -> Stable
A32: =Scenario_Analysis!A242 -> 06edb72f1e0c64b14c5b79353f7abea3 | B32: =Scenario_Analysis!B242 -> bed_bath_table | C32: =Scenario_Analysis!D242 -> -0.023546882 | D32: =Scenario_Analysis!E242 -> EXIT | E32: =Scenario_Analysis!G242 -> -0.068546942 | F32: =Scenario_Analysis!I242 -> EXIT | G32: =Scenario_Analysis!K242 -> -0.032374391 | H32: =Scenario_Analysis!M242 -> EXIT | I32: =Scenario_Analysis!O242 -> -0.077417771 | J32: =Scenario_Analysis!Q242 -> EXIT | K32: =Scenario_Analysis!R242 -> Stable
A33: =Scenario_Analysis!A252 -> 145028037adecb27b1a58cf9597676cc | B33: =Scenario_Analysis!B252 -> office_furniture | C33: =Scenario_Analysis!D252 -> 0.4038686 | D33: =Scenario_Analysis!E252 -> EXIT | E33: =Scenario_Analysis!G252 -> 0.3588686 | F33: =Scenario_Analysis!I252 -> EXIT | G33: =Scenario_Analysis!K252 -> 0.40296634 | H33: =Scenario_Analysis!M252 -> EXIT | I33: =Scenario_Analysis!O252 -> 0.37249326 | J33: =Scenario_Analysis!Q252 -> EXIT | K33: =Scenario_Analysis!R252 -> Stable
A34: =Scenario_Analysis!A265 -> 89b121bee266dcd25688a1ba72eefb61 | B34: =Scenario_Analysis!B265 -> computers_accessories | C34: =Scenario_Analysis!D265 -> 0.12382206 | D34: =Scenario_Analysis!E265 -> EXIT | E34: =Scenario_Analysis!G265 -> 0.066822131 | F34: =Scenario_Analysis!I265 -> EXIT | G34: =Scenario_Analysis!K265 -> 0.11255798 | H34: =Scenario_Analysis!M265 -> EXIT | I34: =Scenario_Analysis!O265 -> 0.077707428 | J34: =Scenario_Analysis!Q265 -> EXIT | K34: =Scenario_Analysis!R265 -> Stable
A35: =Scenario_Analysis!A266 -> 5cd07c84a1c25575ac2fc3fa73f1d952 | B35: =Scenario_Analysis!B266 -> toys | C35: =Scenario_Analysis!D266 -> 0.53467883 | D35: =Scenario_Analysis!E266 -> EXIT | E35: =Scenario_Analysis!G266 -> 0.49267887 | F35: =Scenario_Analysis!I266 -> EXIT | G35: =Scenario_Analysis!K266 -> 0.53408029 | H35: =Scenario_Analysis!M266 -> EXIT | I35: =Scenario_Analysis!O266 -> 0.51018825 | J35: =Scenario_Analysis!Q266 -> EXIT | K35: =Scenario_Analysis!R266 -> Stable
A36: =Scenario_Analysis!A283 -> 130482add9fd75ccb6c57ba007694a2d | B36: =Scenario_Analysis!B283 -> computers_accessories | C36: =Scenario_Analysis!D283 -> 0.056750243 | D36: =Scenario_Analysis!E283 -> EXIT | E36: =Scenario_Analysis!G283 -> -0.00024975705 | F36: =Scenario_Analysis!I283 -> EXIT | G36: =Scenario_Analysis!K283 -> 0.048178814 | H36: =Scenario_Analysis!M283 -> EXIT | I36: =Scenario_Analysis!O283 -> 0.0071055189 | J36: =Scenario_Analysis!Q283 -> EXIT | K36: =Scenario_Analysis!R283 -> Stable
A37: =Scenario_Analysis!A286 -> 63085bb4366ded27bcb63cbb59b4103a | B37: =Scenario_Analysis!B286 -> baby | C37: =Scenario_Analysis!D286 -> 0.49354366 | D37: =Scenario_Analysis!E286 -> EXIT | E37: =Scenario_Analysis!G286 -> 0.45154362 | F37: =Scenario_Analysis!I286 -> EXIT | G37: =Scenario_Analysis!K286 -> 0.49262886 | H37: =Scenario_Analysis!M286 -> EXIT | I37: =Scenario_Analysis!O286 -> 0.46688806 | J37: =Scenario_Analysis!Q286 -> EXIT | K37: =Scenario_Analysis!R286 -> Stable
A38: =Scenario_Analysis!A295 -> 0d85c435fd60b277ffb9e9b0f88f927a | B38: =Scenario_Analysis!B295 -> computers_accessories | C38: =Scenario_Analysis!D295 -> 0.02476449 | D38: =Scenario_Analysis!E295 -> EXIT | E38: =Scenario_Analysis!G295 -> -0.03223555 | F38: =Scenario_Analysis!I295 -> EXIT | G38: =Scenario_Analysis!K295 -> 0.012011017 | H38: =Scenario_Analysis!M295 -> EXIT | I38: =Scenario_Analysis!O295 -> -0.026563695 | J38: =Scenario_Analysis!Q295 -> EXIT | K38: =Scenario_Analysis!R295 -> Stable
A39: =Scenario_Analysis!A297 -> 38dcb9ae53c258cfba73583f9454d721 | B39: =Scenario_Analysis!B297 -> garden_tools | C39: =Scenario_Analysis!D297 -> 0.50615 | D39: =Scenario_Analysis!E297 -> EXIT | E39: =Scenario_Analysis!G297 -> 0.46115 | F39: =Scenario_Analysis!I297 -> EXIT | G39: =Scenario_Analysis!K297 -> 0.505862 | H39: =Scenario_Analysis!M297 -> EXIT | I39: =Scenario_Analysis!O297 -> 0.48015789 | J39: =Scenario_Analysis!Q297 -> EXIT | K39: =Scenario_Analysis!R297 -> Stable
A40: =Scenario_Analysis!A305 -> cb460986a447ed00da792526bf6189e4 | B40: =Scenario_Analysis!B305 -> sports_leisure | C40: =Scenario_Analysis!D305 -> 0.55358693 | D40: =Scenario_Analysis!E305 -> EXIT | E40: =Scenario_Analysis!G305 -> 0.51158693 | F40: =Scenario_Analysis!I305 -> EXIT | G40: =Scenario_Analysis!K305 -> 0.55336782 | H40: =Scenario_Analysis!M305 -> EXIT | I40: =Scenario_Analysis!O305 -> 0.53009151 | J40: =Scenario_Analysis!Q305 -> EXIT | K40: =Scenario_Analysis!R305 -> Stable
A41: =Scenario_Analysis!A315 -> 038e3a669bb495e56d9d609d874fb668 | B41: =Scenario_Analysis!B315 -> sports_leisure | C41: =Scenario_Analysis!D315 -> 0.51161976 | D41: =Scenario_Analysis!E315 -> EXIT | E41: =Scenario_Analysis!G315 -> 0.46961976 | F41: =Scenario_Analysis!I315 -> EXIT | G41: =Scenario_Analysis!K315 -> 0.51139462 | H41: =Scenario_Analysis!M315 -> EXIT | I41: =Scenario_Analysis!O315 -> 0.48591554 | J41: =Scenario_Analysis!Q315 -> EXIT | K41: =Scenario_Analysis!R315 -> Stable
A42: =Scenario_Analysis!A316 -> e74384c9363e768848854356a37c73f4 | B42: =Scenario_Analysis!B316 -> consoles_games | C42: =Scenario_Analysis!D316 -> 0.40930165 | D42: =Scenario_Analysis!E316 -> EXIT | E42: =Scenario_Analysis!G316 -> 0.35230165 | F42: =Scenario_Analysis!I316 -> EXIT | G42: =Scenario_Analysis!K316 -> 0.40907651 | H42: =Scenario_Analysis!M316 -> EXIT | I42: =Scenario_Analysis!O316 -> 0.37821226 | J42: =Scenario_Analysis!Q316 -> EXIT | K42: =Scenario_Analysis!R316 -> Stable
A43: =Scenario_Analysis!A325 -> 3eef0cb94ba82de806bb30ab743c7655 | B43: =Scenario_Analysis!B325 -> office_furniture | C43: =Scenario_Analysis!D325 -> 0.055730566 | D43: =Scenario_Analysis!E325 -> EXIT | E43: =Scenario_Analysis!G325 -> 0.010730661 | F43: =Scenario_Analysis!I325 -> EXIT | G43: =Scenario_Analysis!K325 -> 0.051248995 | H43: =Scenario_Analysis!M325 -> EXIT | I43: =Scenario_Analysis!O325 -> 0.0060321743 | J43: =Scenario_Analysis!Q325 -> EXIT | K43: =Scenario_Analysis!R325 -> Stable
A44: =Scenario_Analysis!A340 -> cd48f265a63e13b762601f5f794c5fca | B44: =Scenario_Analysis!B340 -> drinks | C44: =Scenario_Analysis!D340 -> 0.096161947 | D44: =Scenario_Analysis!E340 -> EXIT | E44: =Scenario_Analysis!G340 -> 0.051161892 | F44: =Scenario_Analysis!I340 -> EXIT | G44: =Scenario_Analysis!K340 -> 0.094132155 | H44: =Scenario_Analysis!M340 -> EXIT | I44: =Scenario_Analysis!O340 -> 0.048591523 | J44: =Scenario_Analysis!Q340 -> EXIT | K44: =Scenario_Analysis!R340 -> Stable
A45: =Scenario_Analysis!A341 -> ada6a9116c85d8e56232e0a4265d7db9 | B45: =Scenario_Analysis!B341 -> home_appliances_2 | C45: =Scenario_Analysis!D341 -> 0.37748195 | D45: =Scenario_Analysis!E341 -> EXIT | E45: =Scenario_Analysis!G341 -> 0.32048195 | F45: =Scenario_Analysis!I341 -> EXIT | G45: =Scenario_Analysis!K341 -> 0.37732444 | H45: =Scenario_Analysis!M341 -> EXIT | I45: =Scenario_Analysis!O341 -> 0.34471784 | J45: =Scenario_Analysis!Q341 -> EXIT | K45: =Scenario_Analysis!R341 -> Stable
A46: =Scenario_Analysis!A353 -> 9ad75bd7267e5c724cb42c71ac56ca72 | B46: =Scenario_Analysis!B353 -> bed_bath_table | C46: =Scenario_Analysis!D353 -> 0.29006875 | D46: =Scenario_Analysis!E353 -> EXIT | E46: =Scenario_Analysis!G353 -> 0.24506863 | F46: =Scenario_Analysis!I353 -> EXIT | G46: =Scenario_Analysis!K353 -> 0.28660232 | H46: =Scenario_Analysis!M353 -> EXIT | I46: =Scenario_Analysis!O353 -> 0.25270394 | J46: =Scenario_Analysis!Q353 -> EXIT | K46: =Scenario_Analysis!R353 -> Stable
A47: =Scenario_Analysis!A376 -> a56af7192032f295ac582a2d70e4caba | B47: =Scenario_Analysis!B376 -> telephony | C47: =Scenario_Analysis!D376 -> 0.39932103 | D47: =Scenario_Analysis!E376 -> EXIT | E47: =Scenario_Analysis!G376 -> 0.34232103 | F47: =Scenario_Analysis!I376 -> EXIT | G47: =Scenario_Analysis!K376 -> 0.39804353 | H47: =Scenario_Analysis!M376 -> EXIT | I47: =Scenario_Analysis!O376 -> 0.36770635 | J47: =Scenario_Analysis!Q376 -> EXIT | K47: =Scenario_Analysis!R376 -> Stable
A48: =Scenario_Analysis!A377 -> cda8b19a05af621d957a97a979b6fa9a | B48: =Scenario_Analysis!B377 -> baby | C48: =Scenario_Analysis!D377 -> 0.48141232 | D48: =Scenario_Analysis!E377 -> EXIT | E48: =Scenario_Analysis!G377 -> 0.43941232 | F48: =Scenario_Analysis!I377 -> EXIT | G48: =Scenario_Analysis!K377 -> 0.48124171 | H48: =Scenario_Analysis!M377 -> EXIT | I48: =Scenario_Analysis!O377 -> 0.45411823 | J48: =Scenario_Analysis!Q377 -> EXIT | K48: =Scenario_Analysis!R377 -> Stable
A49: =Scenario_Analysis!A393 -> e0cf79767c5b016251fe139915c59a26 | B49: =Scenario_Analysis!B393 -> health_beauty | C49: =Scenario_Analysis!D393 -> 0.067587823 | D49: =Scenario_Analysis!E393 -> EXIT | E49: =Scenario_Analysis!G393 -> 0.025587726 | F49: =Scenario_Analysis!I393 -> EXIT | G49: =Scenario_Analysis!K393 -> 0.055547689 | H49: =Scenario_Analysis!M393 -> EXIT | I49: =Scenario_Analysis!O393 -> 0.018513498 | J49: =Scenario_Analysis!Q393 -> EXIT | K49: =Scenario_Analysis!R393 -> Stable
A50: =Scenario_Analysis!A7 -> 99a4788cb24856965c36a24e339b6058 | B50: =Scenario_Analysis!B7 -> bed_bath_table | C50: =Scenario_Analysis!D7 -> 0.26296233 | D50: =Scenario_Analysis!E7 -> OPTIMIZE | E50: =Scenario_Analysis!G7 -> 0.21796232 | F50: =Scenario_Analysis!I7 -> OPTIMIZE | G50: =Scenario_Analysis!K7 -> 0.25887929 | H50: =Scenario_Analysis!M7 -> OPTIMIZE | I50: =Scenario_Analysis!O7 -> 0.22417087 | J50: =Scenario_Analysis!Q7 -> OPTIMIZE | K50: =Scenario_Analysis!R7 -> Stable
A51: =Scenario_Analysis!A8 -> 3dd2a17168ec895c781a9191c1e95ad7 | B51: =Scenario_Analysis!B8 -> computers_accessories | C51: =Scenario_Analysis!D8 -> 0.17337754 | D51: =Scenario_Analysis!E8 -> OPTIMIZE | E51: =Scenario_Analysis!G8 -> 0.11637754 | F51: =Scenario_Analysis!I8 -> OPTIMIZE | G51: =Scenario_Analysis!K8 -> 0.167375 | H51: =Scenario_Analysis!M8 -> OPTIMIZE | I51: =Scenario_Analysis!O8 -> 0.12987109 | J51: =Scenario_Analysis!Q8 -> OPTIMIZE | K51: =Scenario_Analysis!R8 -> Stable
A52: =Scenario_Analysis!A12 -> aca2eb7d00ea1a7b8ebd4e68314663af | B52: =Scenario_Analysis!B12 -> furniture_decor | C52: =Scenario_Analysis!D12 -> 0.16853218 | D52: =Scenario_Analysis!E12 -> OPTIMIZE | E52: =Scenario_Analysis!G12 -> 0.12353217 | F52: =Scenario_Analysis!I12 -> OPTIMIZE | G52: =Scenario_Analysis!K12 -> 0.16348763 | H52: =Scenario_Analysis!M12 -> OPTIMIZE | I52: =Scenario_Analysis!O12 -> 0.12477072 | J52: =Scenario_Analysis!Q12 -> OPTIMIZE | K52: =Scenario_Analysis!R12 -> Stable
A53: =Scenario_Analysis!A13 -> e0d64dcfaa3b6db5c54ca298ae101d05 | B53: =Scenario_Analysis!B13 -> watches_gifts | C53: =Scenario_Analysis!D13 -> 0.43537699 | D53: =Scenario_Analysis!E13 -> OPTIMIZE | E53: =Scenario_Analysis!G13 -> 0.393377 | F53: =Scenario_Analysis!I13 -> OPTIMIZE | G53: =Scenario_Analysis!K13 -> 0.43317985 | H53: =Scenario_Analysis!M13 -> OPTIMIZE | I53: =Scenario_Analysis!O13 -> 0.40565999 | J53: =Scenario_Analysis!Q13 -> OPTIMIZE | K53: =Scenario_Analysis!R13 -> Stable
A54: =Scenario_Analysis!A14 -> d285360f29ac7fd97640bf0baef03de0 | B54: =Scenario_Analysis!B14 -> watches_gifts | C54: =Scenario_Analysis!D14 -> 0.49654896 | D54: =Scenario_Analysis!E14 -> OPTIMIZE | E54: =Scenario_Analysis!G14 -> 0.45454896 | F54: =Scenario_Analysis!I14 -> OPTIMIZE | G54: =Scenario_Analysis!K14 -> 0.49514875 | H54: =Scenario_Analysis!M14 -> OPTIMIZE | I54: =Scenario_Analysis!O14 -> 0.47005154 | J54: =Scenario_Analysis!Q14 -> OPTIMIZE | K54: =Scenario_Analysis!R14 -> Stable
A55: =Scenario_Analysis!A21 -> a62e25e09e05e6faf31d90c6ec1aa3d1 | B55: =Scenario_Analysis!B21 -> watches_gifts | C55: =Scenario_Analysis!D21 -> 0.37447939 | D55: =Scenario_Analysis!E21 -> OPTIMIZE | E55: =Scenario_Analysis!G21 -> 0.33247939 | F55: =Scenario_Analysis!I21 -> OPTIMIZE | G55: =Scenario_Analysis!K21 -> 0.37109635 | H55: =Scenario_Analysis!M21 -> OPTIMIZE | I55: =Scenario_Analysis!O21 -> 0.34155725 | J55: =Scenario_Analysis!Q21 -> OPTIMIZE | K55: =Scenario_Analysis!R21 -> Stable
A56: =Scenario_Analysis!A27 -> 461f43be3bdf8844e65b62d9ac2c7a5a | B56: =Scenario_Analysis!B27 -> watches_gifts | C56: =Scenario_Analysis!D27 -> 0.41503466 | D56: =Scenario_Analysis!E27 -> OPTIMIZE | E56: =Scenario_Analysis!G27 -> 0.37303467 | F56: =Scenario_Analysis!I27 -> OPTIMIZE | G56: =Scenario_Analysis!K27 -> 0.41248236 | H56: =Scenario_Analysis!M27 -> OPTIMIZE | I56: =Scenario_Analysis!O27 -> 0.38424701 | J56: =Scenario_Analysis!Q27 -> OPTIMIZE | K56: =Scenario_Analysis!R27 -> Stable
A57: =Scenario_Analysis!A28 -> 52c80cedd4e90108bf4fa6a206ef6b03 | B57: =Scenario_Analysis!B28 -> garden_tools | C57: =Scenario_Analysis!D28 -> 0.20050099 | D57: =Scenario_Analysis!E28 -> OPTIMIZE | E57: =Scenario_Analysis!G28 -> 0.155501 | F57: =Scenario_Analysis!I28 -> OPTIMIZE | G57: =Scenario_Analysis!K28 -> 0.19842834 | H57: =Scenario_Analysis!M28 -> OPTIMIZE | I57: =Scenario_Analysis!O28 -> 0.15842209 | J57: =Scenario_Analysis!Q28 -> OPTIMIZE | K57: =Scenario_Analysis!R28 -> Stable
A58: =Scenario_Analysis!A33 -> 19c91ef95d509ea33eda93495c4d3481 | B58: =Scenario_Analysis!B33 -> health_beauty | C58: =Scenario_Analysis!D33 -> 0.24812329 | D58: =Scenario_Analysis!E33 -> OPTIMIZE | E58: =Scenario_Analysis!G33 -> 0.20612332 | F58: =Scenario_Analysis!I33 -> OPTIMIZE | G58: =Scenario_Analysis!K33 -> 0.2451502 | H58: =Scenario_Analysis!M33 -> OPTIMIZE | I58: =Scenario_Analysis!O33 -> 0.20855083 | J58: =Scenario_Analysis!Q33 -> OPTIMIZE | K58: =Scenario_Analysis!R33 -> Stable
A59: =Scenario_Analysis!A35 -> 165f86fe8b799a708a20ee4ba125c289 | B59: =Scenario_Analysis!B35 -> cool_stuff | C59: =Scenario_Analysis!D35 -> 0.37815009 | D59: =Scenario_Analysis!E35 -> OPTIMIZE | E59: =Scenario_Analysis!G35 -> 0.33315012 | F59: =Scenario_Analysis!I35 -> OPTIMIZE | G59: =Scenario_Analysis!K35 -> 0.3759465 | H59: =Scenario_Analysis!M35 -> OPTIMIZE | I59: =Scenario_Analysis!O35 -> 0.34542115 | J59: =Scenario_Analysis!Q35 -> OPTIMIZE | K59: =Scenario_Analysis!R35 -> Stable
A60: =Scenario_Analysis!A37 -> e7cc48a9daff5436f63d3aad9426f28b | B60: =Scenario_Analysis!B37 -> telephony | C60: =Scenario_Analysis!D37 -> 0.25986433 | D60: =Scenario_Analysis!E37 -> OPTIMIZE | E60: =Scenario_Analysis!G37 -> 0.20286433 | F60: =Scenario_Analysis!I37 -> OPTIMIZE | G60: =Scenario_Analysis!K37 -> 0.25470276 | H60: =Scenario_Analysis!M37 -> OPTIMIZE | I60: =Scenario_Analysis!O37 -> 0.22090982 | J60: =Scenario_Analysis!Q37 -> OPTIMIZE | K60: =Scenario_Analysis!R37 -> Stable
A61: =Scenario_Analysis!A38 -> a04087ab6a96ffa041f8a2701a72b616 | B61: =Scenario_Analysis!B38 -> computers | C61: =Scenario_Analysis!D38 -> 0.30875895 | D61: =Scenario_Analysis!E38 -> OPTIMIZE | E61: =Scenario_Analysis!G38 -> 0.25175895 | F61: =Scenario_Analysis!I38 -> OPTIMIZE | G61: =Scenario_Analysis!K38 -> 0.30733354 | H61: =Scenario_Analysis!M38 -> OPTIMIZE | I61: =Scenario_Analysis!O38 -> 0.27237784 | J61: =Scenario_Analysis!Q38 -> OPTIMIZE | K61: =Scenario_Analysis!R38 -> Stable
A62: =Scenario_Analysis!A41 -> d5991653e037ccb7af6ed7d94246b249 | B62: =Scenario_Analysis!B41 -> computers_accessories | C62: =Scenario_Analysis!D41 -> 0.17501797 | D62: =Scenario_Analysis!E41 -> OPTIMIZE | E62: =Scenario_Analysis!G41 -> 0.11801795 | F62: =Scenario_Analysis!I41 -> OPTIMIZE | G62: =Scenario_Analysis!K41 -> 0.1688837 | H62: =Scenario_Analysis!M41 -> OPTIMIZE | I62: =Scenario_Analysis!O41 -> 0.13159786 | J62: =Scenario_Analysis!Q41 -> OPTIMIZE | K62: =Scenario_Analysis!R41 -> Stable
A63: =Scenario_Analysis!A45 -> 7814c273ab16783d73a9863ebfa8b141 | B63: =Scenario_Analysis!B45 -> furniture_decor | C63: =Scenario_Analysis!D45 -> 0.25123206 | D63: =Scenario_Analysis!E45 -> OPTIMIZE | E63: =Scenario_Analysis!G45 -> 0.20623206 | F63: =Scenario_Analysis!I45 -> OPTIMIZE | G63: =Scenario_Analysis!K45 -> 0.24972109 | H63: =Scenario_Analysis!M45 -> OPTIMIZE | I63: =Scenario_Analysis!O45 -> 0.21182322 | J63: =Scenario_Analysis!Q45 -> OPTIMIZE | K63: =Scenario_Analysis!R45 -> Stable
A64: =Scenario_Analysis!A49 -> 35afc973633aaeb6b877ff57b2793310 | B64: =Scenario_Analysis!B49 -> home_confort | C64: =Scenario_Analysis!D49 -> 0.26926266 | D64: =Scenario_Analysis!E49 -> OPTIMIZE | E64: =Scenario_Analysis!G49 -> 0.22426266 | F64: =Scenario_Analysis!I49 -> OPTIMIZE | G64: =Scenario_Analysis!K49 -> 0.26516183 | H64: =Scenario_Analysis!M49 -> OPTIMIZE | I64: =Scenario_Analysis!O49 -> 0.2308028 | J64: =Scenario_Analysis!Q49 -> OPTIMIZE | K64: =Scenario_Analysis!R49 -> Stable
A65: =Scenario_Analysis!A51 -> 7c1bd920dbdf22470b68bde975dd3ccf | B65: =Scenario_Analysis!B51 -> health_beauty | C65: =Scenario_Analysis!D51 -> 0.22252823 | D65: =Scenario_Analysis!E51 -> OPTIMIZE | E65: =Scenario_Analysis!G51 -> 0.18052823 | F65: =Scenario_Analysis!I51 -> OPTIMIZE | G65: =Scenario_Analysis!K51 -> 0.21653113 | H65: =Scenario_Analysis!M51 -> OPTIMIZE | I65: =Scenario_Analysis!O51 -> 0.18160866 | J65: =Scenario_Analysis!Q51 -> OPTIMIZE | K65: =Scenario_Analysis!R51 -> Stable
A66: =Scenario_Analysis!A59 -> 13db47eae724e2848e12b71a617a3a41 | B66: =Scenario_Analysis!B59 -> audio | C66: =Scenario_Analysis!D59 -> 0.37218735 | D66: =Scenario_Analysis!E59 -> OPTIMIZE | E66: =Scenario_Analysis!G59 -> 0.31518736 | F66: =Scenario_Analysis!I59 -> OPTIMIZE | G66: =Scenario_Analysis!K59 -> 0.37038633 | H66: =Scenario_Analysis!M59 -> OPTIMIZE | I66: =Scenario_Analysis!O59 -> 0.33914458 | J66: =Scenario_Analysis!Q59 -> OPTIMIZE | K66: =Scenario_Analysis!R59 -> Stable
A67: =Scenario_Analysis!A60 -> 8ed094bfe076c568f6bb10feada3f75d | B67: =Scenario_Analysis!B60 -> office_furniture | C67: =Scenario_Analysis!D60 -> 0.17230513 | D67: =Scenario_Analysis!E60 -> OPTIMIZE | E67: =Scenario_Analysis!G60 -> 0.12730513 | F67: =Scenario_Analysis!I60 -> OPTIMIZE | G67: =Scenario_Analysis!K60 -> 0.17035874 | H67: =Scenario_Analysis!M60 -> OPTIMIZE | I67: =Scenario_Analysis!O60 -> 0.12874224 | J67: =Scenario_Analysis!Q60 -> OPTIMIZE | K67: =Scenario_Analysis!R60 -> Stable
A68: =Scenario_Analysis!A63 -> 44fc450365728c413fefc547592626be | B68: =Scenario_Analysis!B63 -> small_appliances | C68: =Scenario_Analysis!D63 -> 0.39280263 | D68: =Scenario_Analysis!E63 -> OPTIMIZE | E68: =Scenario_Analysis!G63 -> 0.33580263 | F68: =Scenario_Analysis!I63 -> OPTIMIZE | G68: =Scenario_Analysis!K63 -> 0.39238036 | H68: =Scenario_Analysis!M63 -> OPTIMIZE | I68: =Scenario_Analysis!O63 -> 0.36084487 | J68: =Scenario_Analysis!Q63 -> OPTIMIZE | K68: =Scenario_Analysis!R63 -> Stable
A69: =Scenario_Analysis!A66 -> a92930c327948861c015c919a0bcb4a8 | B69: =Scenario_Analysis!B66 -> watches_gifts | C69: =Scenario_Analysis!D66 -> 0.3110517 | D69: =Scenario_Analysis!E66 -> OPTIMIZE | E69: =Scenario_Analysis!G66 -> 0.2690517 | F69: =Scenario_Analysis!I66 -> OPTIMIZE | G69: =Scenario_Analysis!K66 -> 0.30643447 | H69: =Scenario_Analysis!M66 -> OPTIMIZE | I69: =Scenario_Analysis!O66 -> 0.27479127 | J69: =Scenario_Analysis!Q66 -> OPTIMIZE | K69: =Scenario_Analysis!R66 -> Stable
A70: =Scenario_Analysis!A67 -> 4298b7e67dc399c200662b569563a2b2 | B70: =Scenario_Analysis!B67 -> computers_accessories | C70: =Scenario_Analysis!D67 -> 0.2134844 | D70: =Scenario_Analysis!E67 -> OPTIMIZE | E70: =Scenario_Analysis!G67 -> 0.15648437 | F70: =Scenario_Analysis!I67 -> OPTIMIZE | G70: =Scenario_Analysis!K67 -> 0.20713394 | H70: =Scenario_Analysis!M67 -> OPTIMIZE | I70: =Scenario_Analysis!O67 -> 0.17208885 | J70: =Scenario_Analysis!Q67 -> OPTIMIZE | K70: =Scenario_Analysis!R67 -> Stable
A71: =Scenario_Analysis!A68 -> 656e0eca68dcecf6a31b8ececfabe3e8 | B71: =Scenario_Analysis!B68 -> computers_accessories | C71: =Scenario_Analysis!D68 -> 0.1309787 | D71: =Scenario_Analysis!E68 -> OPTIMIZE | E71: =Scenario_Analysis!G68 -> 0.073978716 | F71: =Scenario_Analysis!I68 -> EXIT | G71: =Scenario_Analysis!K68 -> 0.1208136 | H71: =Scenario_Analysis!M68 -> OPTIMIZE | I71: =Scenario_Analysis!O68 -> 0.085240739 | J71: =Scenario_Analysis!Q68 -> EXIT | K71: =Scenario_Analysis!R68 -> Decision changes
A72: =Scenario_Analysis!A70 -> 0a57f7d2c983bcf8188589a5fea4a8da | B72: =Scenario_Analysis!B70 -> watches_gifts | C72: =Scenario_Analysis!D70 -> 0.40221967 | D72: =Scenario_Analysis!E70 -> OPTIMIZE | E72: =Scenario_Analysis!G70 -> 0.3602197 | F72: =Scenario_Analysis!I70 -> OPTIMIZE | G72: =Scenario_Analysis!K70 -> 0.39907535 | H72: =Scenario_Analysis!M70 -> OPTIMIZE | I72: =Scenario_Analysis!O70 -> 0.37075754 | J72: =Scenario_Analysis!Q70 -> OPTIMIZE | K72: =Scenario_Analysis!R70 -> Stable
A73: =Scenario_Analysis!A71 -> 5237739bb5fee495dbd337755a138660 | B73: =Scenario_Analysis!B71 -> watches_gifts | C73: =Scenario_Analysis!D71 -> 0.54359805 | D73: =Scenario_Analysis!E71 -> OPTIMIZE | E73: =Scenario_Analysis!G71 -> 0.50159806 | F73: =Scenario_Analysis!I71 -> OPTIMIZE | G73: =Scenario_Analysis!K71 -> 0.54320428 | H73: =Scenario_Analysis!M71 -> OPTIMIZE | I73: =Scenario_Analysis!O71 -> 0.51957689 | J73: =Scenario_Analysis!Q71 -> OPTIMIZE | K73: =Scenario_Analysis!R71 -> Stable
A74: =Scenario_Analysis!A73 -> af0a99476d96dcc1a1baa7c0d9ff6b9d | B74: =Scenario_Analysis!B73 -> health_beauty | C74: =Scenario_Analysis!D73 -> 0.51842014 | D74: =Scenario_Analysis!E73 -> OPTIMIZE | E74: =Scenario_Analysis!G73 -> 0.47642011 | F74: =Scenario_Analysis!I73 -> OPTIMIZE | G74: =Scenario_Analysis!K73 -> 0.51775124 | H74: =Scenario_Analysis!M73 -> OPTIMIZE | I74: =Scenario_Analysis!O73 -> 0.49307383 | J74: =Scenario_Analysis!Q73 -> OPTIMIZE | K74: =Scenario_Analysis!R73 -> Stable
A75: =Scenario_Analysis!A76 -> 36f60d45225e60c7da4558b070ce4b60 | B75: =Scenario_Analysis!B76 -> computers_accessories | C75: =Scenario_Analysis!D76 -> 0.15535239 | D75: =Scenario_Analysis!E76 -> OPTIMIZE | E75: =Scenario_Analysis!G76 -> 0.098352365 | F75: =Scenario_Analysis!I76 -> EXIT | G75: =Scenario_Analysis!K76 -> 0.14518422 | H75: =Scenario_Analysis!M76 -> OPTIMIZE | I75: =Scenario_Analysis!O76 -> 0.11089725 | J75: =Scenario_Analysis!Q76 -> OPTIMIZE | K75: =Scenario_Analysis!R76 -> Decision changes
A76: =Scenario_Analysis!A77 -> 2ffdf10e724b958c0f7ea69e97d32f64 | B76: =Scenario_Analysis!B77 -> watches_gifts | C76: =Scenario_Analysis!D77 -> 0.46078724 | D76: =Scenario_Analysis!E77 -> OPTIMIZE | E76: =Scenario_Analysis!G77 -> 0.41878726 | F76: =Scenario_Analysis!I77 -> OPTIMIZE | G76: =Scenario_Analysis!K77 -> 0.45907242 | H76: =Scenario_Analysis!M77 -> OPTIMIZE | I76: =Scenario_Analysis!O77 -> 0.43240762 | J76: =Scenario_Analysis!Q77 -> OPTIMIZE | K76: =Scenario_Analysis!R77 -> Stable
A77: =Scenario_Analysis!A81 -> 4fe644d766c7566dbc46fb851363cb3b | B77: =Scenario_Analysis!B81 -> art | C77: =Scenario_Analysis!D81 -> 0.35767402 | D77: =Scenario_Analysis!E81 -> OPTIMIZE | E77: =Scenario_Analysis!G81 -> 0.317674 | F77: =Scenario_Analysis!I81 -> OPTIMIZE | G77: =Scenario_Analysis!K81 -> 0.35410858 | H77: =Scenario_Analysis!M81 -> OPTIMIZE | I77: =Scenario_Analysis!O81 -> 0.32386739 | J77: =Scenario_Analysis!Q81 -> OPTIMIZE | K77: =Scenario_Analysis!R81 -> Stable
A78: =Scenario_Analysis!A87 -> 4c2394abfbac7ff59ec7a420918562fa | B78: =Scenario_Analysis!B87 -> health_beauty | C78: =Scenario_Analysis!D87 -> 0.32177556 | D78: =Scenario_Analysis!E87 -> OPTIMIZE | E78: =Scenario_Analysis!G87 -> 0.27977554 | F78: =Scenario_Analysis!I87 -> OPTIMIZE | G78: =Scenario_Analysis!K87 -> 0.31753977 | H78: =Scenario_Analysis!M87 -> OPTIMIZE | I78: =Scenario_Analysis!O87 -> 0.28607954 | J78: =Scenario_Analysis!Q87 -> OPTIMIZE | K78: =Scenario_Analysis!R87 -> Stable
A79: =Scenario_Analysis!A88 -> 3225c54bb2785c33f49f50398fcdb88c | B79: =Scenario_Analysis!B88 -> watches_gifts | C79: =Scenario_Analysis!D88 -> 0.50186385 | D79: =Scenario_Analysis!E88 -> OPTIMIZE | E79: =Scenario_Analysis!G88 -> 0.45986388 | F79: =Scenario_Analysis!I88 -> OPTIMIZE | G79: =Scenario_Analysis!K88 -> 0.5005745 | H79: =Scenario_Analysis!M88 -> OPTIMIZE | I79: =Scenario_Analysis!O88 -> 0.47564616 | J79: =Scenario_Analysis!Q88 -> OPTIMIZE | K79: =Scenario_Analysis!R88 -> Stable
A80: =Scenario_Analysis!A89 -> 84f456958365164420cfc80fbe4c7fab | B80: =Scenario_Analysis!B89 -> bed_bath_table | C80: =Scenario_Analysis!D89 -> 0.27496759 | D80: =Scenario_Analysis!E89 -> OPTIMIZE | E80: =Scenario_Analysis!G89 -> 0.22996761 | F80: =Scenario_Analysis!I89 -> OPTIMIZE | G80: =Scenario_Analysis!K89 -> 0.27108984 | H80: =Scenario_Analysis!M89 -> OPTIMIZE | I80: =Scenario_Analysis!O89 -> 0.23680799 | J80: =Scenario_Analysis!Q89 -> OPTIMIZE | K80: =Scenario_Analysis!R89 -> Stable
A81: =Scenario_Analysis!A91 -> 53ea9da485f6aed8a6f03a85831fe021 | B81: =Scenario_Analysis!B91 -> watches_gifts | C81: =Scenario_Analysis!D91 -> 0.48724113 | D81: =Scenario_Analysis!E91 -> OPTIMIZE | E81: =Scenario_Analysis!G91 -> 0.44524111 | F81: =Scenario_Analysis!I91 -> OPTIMIZE | G81: =Scenario_Analysis!K91 -> 0.48584115 | H81: =Scenario_Analysis!M91 -> OPTIMIZE | I81: =Scenario_Analysis!O91 -> 0.46025382 | J81: =Scenario_Analysis!Q91 -> OPTIMIZE | K81: =Scenario_Analysis!R91 -> Stable
A82: =Scenario_Analysis!A96 -> 3fbc0ef745950c7932d5f2a446189725 | B82: =Scenario_Analysis!B96 -> health_beauty | C82: =Scenario_Analysis!D96 -> 0.10444613 | D82: =Scenario_Analysis!E96 -> OPTIMIZE | E82: =Scenario_Analysis!G96 -> 0.062446134 | F82: =Scenario_Analysis!I96 -> EXIT | G82: =Scenario_Analysis!K96 -> 0.098970849 | H82: =Scenario_Analysis!M96 -> EXIT | I82: =Scenario_Analysis!O96 -> 0.05731172 | J82: =Scenario_Analysis!Q96 -> EXIT | K82: =Scenario_Analysis!R96 -> Decision changes
A83: =Scenario_Analysis!A99 -> 933f4f76eae38d2a97ecfb7c6355f0bc | B83: =Scenario_Analysis!B99 -> health_beauty | C83: =Scenario_Analysis!D99 -> 0.54306162 | D83: =Scenario_Analysis!E99 -> OPTIMIZE | E83: =Scenario_Analysis!G99 -> 0.50106163 | F83: =Scenario_Analysis!I99 -> OPTIMIZE | G83: =Scenario_Analysis!K99 -> 0.542801 | H83: =Scenario_Analysis!M99 -> OPTIMIZE | I83: =Scenario_Analysis!O99 -> 0.51901224 | J83: =Scenario_Analysis!Q99 -> OPTIMIZE | K83: =Scenario_Analysis!R99 -> Stable
A84: =Scenario_Analysis!A101 -> 78efe838c04bbc568be034082200ac20 | B84: =Scenario_Analysis!B101 -> furniture_decor | C84: =Scenario_Analysis!D101 -> 0.143386 | D84: =Scenario_Analysis!E101 -> OPTIMIZE | E84: =Scenario_Analysis!G101 -> 0.098385997 | F84: =Scenario_Analysis!I101 -> EXIT | G84: =Scenario_Analysis!K101 -> 0.13961664 | H84: =Scenario_Analysis!M101 -> OPTIMIZE | I84: =Scenario_Analysis!O101 -> 0.098301049 | J84: =Scenario_Analysis!Q101 -> EXIT | K84: =Scenario_Analysis!R101 -> Decision changes
A85: =Scenario_Analysis!A107 -> db5efde3ad0cc579b130d71c4b2db522 | B85: =Scenario_Analysis!B107 -> audio | C85: =Scenario_Analysis!D107 -> 0.3017554 | D85: =Scenario_Analysis!E107 -> OPTIMIZE | E85: =Scenario_Analysis!G107 -> 0.24475545 | F85: =Scenario_Analysis!I107 -> OPTIMIZE | G85: =Scenario_Analysis!K107 -> 0.29717222 | H85: =Scenario_Analysis!M107 -> OPTIMIZE | I85: =Scenario_Analysis!O107 -> 0.26500568 | J85: =Scenario_Analysis!Q107 -> OPTIMIZE | K85: =Scenario_Analysis!R107 -> Stable
A86: =Scenario_Analysis!A108 -> 2a5806f10d0f00e5ad032dd2e3c8806e | B86: =Scenario_Analysis!B108 -> office_furniture | C86: =Scenario_Analysis!D108 -> 0.20883728 | D86: =Scenario_Analysis!E108 -> OPTIMIZE | E86: =Scenario_Analysis!G108 -> 0.16383731 | F86: =Scenario_Analysis!I108 -> OPTIMIZE | G86: =Scenario_Analysis!K108 -> 0.20673569 | H86: =Scenario_Analysis!M108 -> OPTIMIZE | I86: =Scenario_Analysis!O108 -> 0.16719714 | J86: =Scenario_Analysis!Q108 -> OPTIMIZE | K86: =Scenario_Analysis!R108 -> Stable
A87: =Scenario_Analysis!A112 -> fe59a1e006df3ac42bf0ceb876d70969 | B87: =Scenario_Analysis!B112 -> computers_accessories | C87: =Scenario_Analysis!D112 -> 0.35286031 | D87: =Scenario_Analysis!E112 -> OPTIMIZE | E87: =Scenario_Analysis!G112 -> 0.29586028 | F87: =Scenario_Analysis!I112 -> OPTIMIZE | G87: =Scenario_Analysis!K112 -> 0.35167922 | H87: =Scenario_Analysis!M112 -> OPTIMIZE | I87: =Scenario_Analysis!O112 -> 0.31880033 | J87: =Scenario_Analysis!Q112 -> OPTIMIZE | K87: =Scenario_Analysis!R112 -> Stable
A88: =Scenario_Analysis!A116 -> e59dd207c69d86e890febadc796d1078 | B88: =Scenario_Analysis!B116 -> cool_stuff | C88: =Scenario_Analysis!D116 -> 0.40509235 | D88: =Scenario_Analysis!E116 -> OPTIMIZE | E88: =Scenario_Analysis!G116 -> 0.36009231 | F88: =Scenario_Analysis!I116 -> OPTIMIZE | G88: =Scenario_Analysis!K116 -> 0.40262424 | H88: =Scenario_Analysis!M116 -> OPTIMIZE | I88: =Scenario_Analysis!O116 -> 0.37378142 | J88: =Scenario_Analysis!Q116 -> OPTIMIZE | K88: =Scenario_Analysis!R116 -> Stable
A89: =Scenario_Analysis!A118 -> c1ad8ac66c91ad301cefc322ba2adf31 | B89: =Scenario_Analysis!B118 -> watches_gifts | C89: =Scenario_Analysis!D118 -> 0.53936518 | D89: =Scenario_Analysis!E118 -> OPTIMIZE | E89: =Scenario_Analysis!G118 -> 0.49736518 | F89: =Scenario_Analysis!I118 -> OPTIMIZE | G89: =Scenario_Analysis!K118 -> 0.53875251 | H89: =Scenario_Analysis!M118 -> OPTIMIZE | I89: =Scenario_Analysis!O118 -> 0.51512125 | J89: =Scenario_Analysis!Q118 -> OPTIMIZE | K89: =Scenario_Analysis!R118 -> Stable
A90: =Scenario_Analysis!A122 -> fbce4c4cb307679d89a3bf3d3bb353b9 | B90: =Scenario_Analysis!B122 -> bed_bath_table | C90: =Scenario_Analysis!D122 -> 0.22033803 | D90: =Scenario_Analysis!E122 -> OPTIMIZE | E90: =Scenario_Analysis!G122 -> 0.17533803 | F90: =Scenario_Analysis!I122 -> OPTIMIZE | G90: =Scenario_Analysis!K122 -> 0.21780282 | H90: =Scenario_Analysis!M122 -> OPTIMIZE | I90: =Scenario_Analysis!O122 -> 0.17930319 | J90: =Scenario_Analysis!Q122 -> OPTIMIZE | K90: =Scenario_Analysis!R122 -> Stable
A91: =Scenario_Analysis!A127 -> b114bf337c0626166abe574eee9e3f32 | B91: =Scenario_Analysis!B127 -> office_furniture | C91: =Scenario_Analysis!D127 -> 0.25005151 | D91: =Scenario_Analysis!E127 -> OPTIMIZE | E91: =Scenario_Analysis!G127 -> 0.20505151 | F91: =Scenario_Analysis!I127 -> OPTIMIZE | G91: =Scenario_Analysis!K127 -> 0.24772281 | H91: =Scenario_Analysis!M127 -> OPTIMIZE | I91: =Scenario_Analysis!O127 -> 0.21058054 | J91: =Scenario_Analysis!Q127 -> OPTIMIZE | K91: =Scenario_Analysis!R127 -> Stable
A92: =Scenario_Analysis!A131 -> 657247f6f60543b93e3cc708a8e6329c | B92: =Scenario_Analysis!B131 -> luggage_accessories | C92: =Scenario_Analysis!D131 -> 0.31997358 | D92: =Scenario_Analysis!E131 -> OPTIMIZE | E92: =Scenario_Analysis!G131 -> 0.27797353 | F92: =Scenario_Analysis!I131 -> OPTIMIZE | G92: =Scenario_Analysis!K131 -> 0.31857513 | H92: =Scenario_Analysis!M131 -> OPTIMIZE | I92: =Scenario_Analysis!O131 -> 0.28418272 | J92: =Scenario_Analysis!Q131 -> OPTIMIZE | K92: =Scenario_Analysis!R131 -> Stable
A93: =Scenario_Analysis!A132 -> 928e52a9ad53a294fdcc91bcf59d1751 | B93: =Scenario_Analysis!B132 -> housewares | C93: =Scenario_Analysis!D132 -> 0.36626994 | D93: =Scenario_Analysis!E132 -> OPTIMIZE | E93: =Scenario_Analysis!G132 -> 0.32126994 | F93: =Scenario_Analysis!I132 -> OPTIMIZE | G93: =Scenario_Analysis!K132 -> 0.36361963 | H93: =Scenario_Analysis!M132 -> OPTIMIZE | I93: =Scenario_Analysis!O132 -> 0.33291572 | J93: =Scenario_Analysis!Q132 -> OPTIMIZE | K93: =Scenario_Analysis!R132 -> Stable
A94: =Scenario_Analysis!A135 -> 2948658cb6abc82847412be7201bfc4c | B94: =Scenario_Analysis!B135 -> health_beauty | C94: =Scenario_Analysis!D135 -> 0.2929321 | D94: =Scenario_Analysis!E135 -> OPTIMIZE | E94: =Scenario_Analysis!G135 -> 0.2509321 | F94: =Scenario_Analysis!I135 -> OPTIMIZE | G94: =Scenario_Analysis!K135 -> 0.28977654 | H94: =Scenario_Analysis!M135 -> OPTIMIZE | I94: =Scenario_Analysis!O135 -> 0.255718 | J94: =Scenario_Analysis!Q135 -> OPTIMIZE | K94: =Scenario_Analysis!R135 -> Stable
A95: =Scenario_Analysis!A136 -> 4413a608a42bd21bbf9d5abbd58c249a | B95: =Scenario_Analysis!B136 -> cool_stuff | C95: =Scenario_Analysis!D136 -> 0.38006351 | D95: =Scenario_Analysis!E136 -> OPTIMIZE | E95: =Scenario_Analysis!G136 -> 0.33506352 | F95: =Scenario_Analysis!I136 -> OPTIMIZE | G95: =Scenario_Analysis!K136 -> 0.3777939 | H95: =Scenario_Analysis!M136 -> OPTIMIZE | I95: =Scenario_Analysis!O136 -> 0.34743528 | J95: =Scenario_Analysis!Q136 -> OPTIMIZE | K95: =Scenario_Analysis!R136 -> Stable
A96: =Scenario_Analysis!A138 -> 8b5227e28272123eefd613a10ffd7704 | B96: =Scenario_Analysis!B138 -> watches_gifts | C96: =Scenario_Analysis!D138 -> 0.53638617 | D96: =Scenario_Analysis!E138 -> OPTIMIZE | E96: =Scenario_Analysis!G138 -> 0.49438617 | F96: =Scenario_Analysis!I138 -> OPTIMIZE | G96: =Scenario_Analysis!K138 -> 0.53567233 | H96: =Scenario_Analysis!M138 -> OPTIMIZE | I96: =Scenario_Analysis!O138 -> 0.51198544 | J96: =Scenario_Analysis!Q138 -> OPTIMIZE | K96: =Scenario_Analysis!R138 -> Stable
A97: =Scenario_Analysis!A141 -> 5183344b5357029cfd88c7f511ed876d | B97: =Scenario_Analysis!B141 -> musical_instruments | C97: =Scenario_Analysis!D141 -> 0.57195848 | D97: =Scenario_Analysis!E141 -> OPTIMIZE | E97: =Scenario_Analysis!G141 -> 0.53195848 | F97: =Scenario_Analysis!I141 -> OPTIMIZE | G97: =Scenario_Analysis!K141 -> 0.57190845 | H97: =Scenario_Analysis!M141 -> OPTIMIZE | I97: =Scenario_Analysis!O141 -> 0.54942998 | J97: =Scenario_Analysis!Q141 -> OPTIMIZE | K97: =Scenario_Analysis!R141 -> Stable
A98: =Scenario_Analysis!A146 -> 3ecf69ee1fe21cfd40b30cbea549e563 | B98: =Scenario_Analysis!B146 -> small_appliances | C98: =Scenario_Analysis!D146 -> 0.4146543 | D98: =Scenario_Analysis!E146 -> OPTIMIZE | E98: =Scenario_Analysis!G146 -> 0.3576543 | F98: =Scenario_Analysis!I146 -> OPTIMIZE | G98: =Scenario_Analysis!K146 -> 0.41451703 | H98: =Scenario_Analysis!M146 -> OPTIMIZE | I98: =Scenario_Analysis!O146 -> 0.38384663 | J98: =Scenario_Analysis!Q146 -> OPTIMIZE | K98: =Scenario_Analysis!R146 -> Stable
A99: =Scenario_Analysis!A147 -> 679d1a26cc192f14e7e30ae397f8b089 | B99: =Scenario_Analysis!B147 -> health_beauty | C99: =Scenario_Analysis!D147 -> 0.54953597 | D99: =Scenario_Analysis!E147 -> OPTIMIZE | E99: =Scenario_Analysis!G147 -> 0.50753597 | F99: =Scenario_Analysis!I147 -> OPTIMIZE | G99: =Scenario_Analysis!K147 -> 0.54912196 | H99: =Scenario_Analysis!M147 -> OPTIMIZE | I99: =Scenario_Analysis!O147 -> 0.52582733 | J99: =Scenario_Analysis!Q147 -> OPTIMIZE | K99: =Scenario_Analysis!R147 -> Stable
A100: =Scenario_Analysis!A149 -> 437c05a395e9e47f9762e677a7068ce7 | B100: =Scenario_Analysis!B149 -> health_beauty | C100: =Scenario_Analysis!D149 -> 0.24590515 | D100: =Scenario_Analysis!E149 -> OPTIMIZE | E100: =Scenario_Analysis!G149 -> 0.20390518 | F100: =Scenario_Analysis!I149 -> OPTIMIZE | G100: =Scenario_Analysis!K149 -> 0.23871249 | H100: =Scenario_Analysis!M149 -> OPTIMIZE | I100: =Scenario_Analysis!O149 -> 0.20621594 | J100: =Scenario_Analysis!Q149 -> OPTIMIZE | K100: =Scenario_Analysis!R149 -> Stable
A101: =Scenario_Analysis!A152 -> 2028bf1b01cafb2d2b1901fca4083222 | B101: =Scenario_Analysis!B152 -> perfumery | C101: =Scenario_Analysis!D152 -> 0.24476199 | D101: =Scenario_Analysis!E152 -> OPTIMIZE | E101: =Scenario_Analysis!G152 -> 0.20276199 | F101: =Scenario_Analysis!I152 -> OPTIMIZE | G101: =Scenario_Analysis!K152 -> 0.23828955 | H101: =Scenario_Analysis!M152 -> OPTIMIZE | I101: =Scenario_Analysis!O152 -> 0.20501262 | J101: =Scenario_Analysis!Q152 -> OPTIMIZE | K101: =Scenario_Analysis!R152 -> Stable
...

Sheet Dashboard
B2: TOP 400 SKU's PROFITABILITY | EXECUTIVE DASHBOARD | M2: FORMULA VIEW | T2: 📋 FORMULA INSPECTOR (set Q5 = TRUE to reveal)
B3: Portfolio analytics across 400 SKUs — Revenue, Profit, Scenario & Sensitivity views | M3: =IF(Q5=TRUE(),"● ON (formulas visible in column S)","○ OFF (set Q5 = TRUE to reveal formulas)") -> ○ OFF (set Q5 = TRUE to reveal formulas) | T3: Every visible KPI / metric is computed live from source tabs — click any cell to see its underlying logic
Q5: FALSE
T6: METRIC | U6: FORMULA
C7: TOTAL GROSS REVENUE | G7: TOTAL NET PROFIT | K7: AVG NET MARGIN | O7: SKUs FLAGGED 'EXIT' | T7: KPI · Total Gross Revenue | U7: =IF($Q$5=TRUE(), IFERROR(_xludf.formulatext(C8), "=SUMIFS(Profitability_Model!C:C,Profitability_Model!A:A,""<>product_id"",Profitability_Model!C:C,"">0"")"), "— toggle Q5=TRUE to reveal —") -> — toggle Q5=TRUE to reveal —
C8: =SUMIFS(Profitability_Model!C:C,Profitability_Model!A:A,"<>product_id",Profitability_Model!C:C,">0") -> 3590972.7 | G8: =SUM(Profitability_Model!H2:H402) -> 1291923.4 | K8: =AVERAGE(Profitability_Model!J2:J402) -> 0.36744704 | O8: =COUNTIF(Profitability_Model!L2:L402,"EXIT") -> 46 | T8: KPI · Total Net Profit | U8: =IF($Q$5=TRUE(), IFERROR(_xlfn.SINGLE(_xlfn.FORMULATEXT(G8)), "=SUM(Profitability_Model!H2:H402)"), "— toggle Q5=TRUE to reveal —") -> — toggle Q5=TRUE to reveal —
C9: =" "&TEXT(COUNTIF(Profitability_Model!L2:L402,"<>"),"#,##0")&" SKUs analysed" -> 401 SKUs analysed | G9: =" Margin "&TEXT(SUM(Profitability_Model!H2:H402)/SUM(Profitability_Model!C2:C402),"0.0%") -> Margin 36.0% | K9: =" Min "&TEXT(MIN(Profitability_Model!J2:J402),"0.0%")&" Max "&TEXT(MAX(Profitability_Model!J2:J402),"0.0%") -> Min -24.1% Max 57.5% | O9: =" "&TEXT(COUNTIF(Profitability_Model!L2:L402,"EXIT")/400,"0.0%")&" of portfolio" -> 11.5% of portfolio | T9: KPI · Average Net Margin | U9: =IF($Q$5=TRUE(), IFERROR(_xlfn.SINGLE(_xlfn.FORMULATEXT(K8)), "=AVERAGE(Profitability_Model!J2:J402)"), "— toggle Q5=TRUE to reveal —") -> — toggle Q5=TRUE to reveal —
T10: KPI · SKUs Flagged EXIT | U10: =IF($Q$5=TRUE(), IFERROR(_xlfn.SINGLE(_xlfn.FORMULATEXT(O8)), "=COUNTIF(Profitability_Model!L2:L402,""EXIT"")"), "— toggle Q5=TRUE to reveal —") -> — toggle Q5=TRUE to reveal —
B11: STRATEGIC DECISION MIX | H11: REVENUE → PROFIT FLOW | N11: PORTFOLIO STABILITY | T11: Decision Mix · SCALE count | U11: =IF($Q$5=TRUE(), IFERROR(_xlfn.SINGLE(_xlfn.FORMULATEXT(C14)), "=COUNTIF(Profitability_Model!L2:L402,""SCALE"")"), "— toggle Q5=TRUE to reveal —") -> — toggle Q5=TRUE to reveal —
T12: Decision Mix · SCALE % of total | U12: =IF($Q$5=TRUE(), IFERROR(_xludf.formulatext(D14), "=C14/SUM($C$14:$C$16)"), "— toggle Q5=TRUE to reveal —") -> — toggle Q5=TRUE to reveal —
B13: Decision | C13: SKUs | D13: % of total | E13: Revenue | F13: Net Profit | H13: Gross Revenue | I13: =SUM(Profitability_Model!C2:C402) -> 3590572.7 | K13: =I13/$I$13 -> 1 | N13: Decision robustness under stress | T13: Decision Mix · SCALE revenue | U13: =IF($Q$5=TRUE(), IFERROR(_xlfn.SINGLE(_xlfn.FORMULATEXT(E14)), "=SUMIF(Profitability_Model!L2:L402,""SCALE"",Profitability_Model!C2:C402)"), "— toggle Q5=TRUE to reveal —") -> — toggle Q5=TRUE to reveal —
B14: ● SCALE | C14: =COUNTIF(Profitability_Model!L2:L402,"SCALE") -> 216 | D14: =C14/SUM($C$14:$C$16) -> 0.54 | E14: =SUMIF(Profitability_Model!L2:L402,"SCALE",Profitability_Model!C2:C402) -> 1900025.6 | F14: =SUMIF(Profitability_Model!L2:L402,"SCALE",Profitability_Model!H2:H402) -> 799944.14 | H14: (−) Return Loss | I14: =-SUM(Profitability_Model!D2:D402) -> -8616.84 | K14: =I14/$I$13 -> -0.0023998511 | T14: Decision Mix · SCALE profit | U14: =IF($Q$5=TRUE(), IFERROR(_xlfn.SINGLE(_xlfn.FORMULATEXT(F14)), "=SUMIF(Profitability_Model!L2:L402,""SCALE"",Profitability_Model!H2:H402)"), "— toggle Q5=TRUE to reveal —") -> — toggle Q5=TRUE to reveal —
B15: ● OPTIMIZE | C15: =COUNTIF(Profitability_Model!L2:L402,"OPTIMIZE") -> 138 | D15: =C15/SUM($C$14:$C$16) -> 0.345 | E15: =SUMIF(Profitability_Model!L2:L402,"OPTIMIZE",Profitability_Model!C2:C402) -> 1196906.3 | F15: =SUMIF(Profitability_Model!L2:L402,"OPTIMIZE",Profitability_Model!H2:H402) -> 391198 | H15: Net Revenue | I15: =SUM(Profitability_Model!E2:E402) -> 3581955.9 | K15: =I15/$I$13 -> 0.99760015 | N15: =COUNTIF(Scenario_Analysis!R2:R402,"Stable") -> 372 | T15: P&L Flow · Gross Revenue | U15: =IF($Q$5=TRUE(), IFERROR(_xlfn.SINGLE(_xlfn.FORMULATEXT(I13)), "=SUM(Profitability_Model!C2:C402)"), "— toggle Q5=TRUE to reveal —") -> — toggle Q5=TRUE to reveal —
B16: ● EXIT | C16: =COUNTIF(Profitability_Model!L2:L402,"EXIT") -> 46 | D16: =C16/SUM($C$14:$C$16) -> 0.115 | E16: =SUMIF(Profitability_Model!L2:L402,"EXIT",Profitability_Model!C2:C402) -> 493640.87 | F16: =SUMIF(Profitability_Model!L2:L402,"EXIT",Profitability_Model!H2:H402) -> 100781.29 | H16: (−) COGS | I16: =-SUM(Profitability_Model!F2:F402) -> -1674817.3 | K16: =I16/$I$13 -> -0.4664485 | N16: STABLE SKUs | T16: P&L Flow · COGS | U16: =IF($Q$5=TRUE(), IFERROR(_xlfn.SINGLE(_xlfn.FORMULATEXT(I16)), "=-SUM(Profitability_Model!F2:F402)"), "— toggle Q5=TRUE to reveal —") -> — toggle Q5=TRUE to reveal —
B17: TOTAL | C17: =SUM(C14:C16) -> 400 | D17: =SUM(D14:D16) -> 1 | E17: =SUM(E14:E16) -> 3590572.7 | F17: =SUM(F14:F16) -> 1291923.4 | H17: (−) Operating Costs | I17: =-SUM(Profitability_Model!G2:G402) -> -615215.18 | K17: =I17/$I$13 -> -0.1713418 | N17: ="(decision unchanged across all 3 stress scenarios)" -> (decision unchanged across all 3 stress scenarios) | T17: P&L Flow · Net Profit | U17: =IF($Q$5=TRUE(), IFERROR(_xlfn.SINGLE(_xlfn.FORMULATEXT(I18)), "=SUM(Profitability_Model!H2:H402)"), "— toggle Q5=TRUE to reveal —") -> — toggle Q5=TRUE to reveal —
H18: Net Profit | I18: =SUM(Profitability_Model!H2:H402) -> 1291923.4 | K18: =I18/$I$13 -> 0.35980985 | T18: P&L Flow · COGS as % revenue | U18: =IF($Q$5=TRUE(), IFERROR(_xludf.formulatext(K16), "=I16/$I$13"), "— toggle Q5=TRUE to reveal —") -> — toggle Q5=TRUE to reveal —
N19: =COUNTIF(Scenario_Analysis!R2:R402,"Decision changes") -> 28 | T19: Stability · Stable SKU count | U19: =IF($Q$5=TRUE(), IFERROR(_xlfn.SINGLE(_xlfn.FORMULATEXT(N15)), "=COUNTIF(Scenario_Analysis!R2:R402,""Stable"")"), "— toggle Q5=TRUE to reveal —") -> — toggle Q5=TRUE to reveal —
H20: 💡 KEY INSIGHTS | N20: SENSITIVE SKUs | T20: Stability · Stability rate | U20: =IF($Q$5=TRUE(), IFERROR(_xlfn.SINGLE(_xlfn.FORMULATEXT(N24)), "=COUNTIF(Scenario_Analysis!R2:R402,""Stable"")/400"), "— toggle Q5=TRUE to reveal —") -> — toggle Q5=TRUE to reveal —
H21: ="• COGS represents "&TEXT(SUM(Profitability_Model!F2:F402)/SUM(Profitability_Model!C2:C402),"0.0%")&" of gross revenue — largest cost driver" -> • COGS represents 46.6% of gross revenue — largest cost driver | N21: ="(require monitoring — flip categories under stress)" -> (require monitoring — flip categories under stress) | T21: Top Categories · Rank | U21: =IF($Q$5=TRUE(), IFERROR(_xludf.formulatext(B35), "=RANK(G35,$G$35:$G$44)"), "— toggle Q5=TRUE to reveal —") -> — toggle Q5=TRUE to reveal —
H22: ="• Operating costs absorb "&TEXT(SUM(Profitability_Model!G2:G402)/SUM(Profitability_Model!C2:C402),"0.0%")&" of revenue" -> • Operating costs absorb 17.1% of revenue | T22: Top Categories · SKU count | U22: =IF($Q$5=TRUE(), IFERROR(_xlfn.SINGLE(_xlfn.FORMULATEXT(E35)), "=COUNTIF(Profitability_Model!B2:B402,""health_beauty"")"), "— toggle Q5=TRUE to reveal —") -> — toggle Q5=TRUE to reveal —
H23: ="• Returns are minimal at "&TEXT(SUM(Profitability_Model!D2:D402)/SUM(Profitability_Model!C2:C402),"0.00%")&" — low quality risk" -> • Returns are minimal at 0.24% — low quality risk | N23: Stability Rate | T23: Top Categories · Revenue | U23: =IF($Q$5=TRUE(), IFERROR(_xlfn.SINGLE(_xlfn.FORMULATEXT(F35)), "=SUMIF(Profitability_Model!B2:B402,""health_beauty"",Profitability_Model!C2:C402)"), "— toggle Q5=TRUE to reveal —") -> — toggle Q5=TRUE to reveal —
H24: ="• SCALE SKUs ("&COUNTIF(Profitability_Model!L2:L402,"SCALE")&") generate "&TEXT(SUMIF(Profitability_Model!L2:L402,"SCALE",Profitability_Model!H2:H402)/SUM(Profitability_Model!H2:H402),"0.0%")&" of total profit" -> • SCALE SKUs (216) generate 61.9% of total profit | N24: =COUNTIF(Scenario_Analysis!R2:R402,"Stable")/400 -> 0.93 | T24: Top Categories · Net Profit | U24: =IF($Q$5=TRUE(), IFERROR(_xlfn.SINGLE(_xlfn.FORMULATEXT(G35)), "=SUMIF(Profitability_Model!B2:B402,""health_beauty"",Profitability_Model!H2:H402)"), "— toggle Q5=TRUE to reveal —") -> — toggle Q5=TRUE to reveal —
H25: ="• EXIT SKUs contribute only "&TEXT(SUMIF(Profitability_Model!L2:L402,"EXIT",Profitability_Model!H2:H402)/SUM(Profitability_Model!H2:H402),"0.0%")&" of profit" -> • EXIT SKUs contribute only 7.8% of profit | T25: Top Categories · Margin | U25: =IF($Q$5=TRUE(), IFERROR(_xludf.formulatext(H35), "=IFERROR(G35/F35,0)"), "— toggle Q5=TRUE to reveal —") -> — toggle Q5=TRUE to reveal —
T26: Top Categories · Profit share | U26: =IF($Q$5=TRUE(), IFERROR(_xlfn.SINGLE(_xlfn.FORMULATEXT(I35)), "=G35/SUM(Profitability_Model!H2:H402)"), "— toggle Q5=TRUE to reveal —") -> — toggle Q5=TRUE to reveal —
T27: Top SKUs · Product ID lookup | U27: =IF($Q$5=TRUE(), IFERROR(_xlfn.SINGLE(_xlfn.FORMULATEXT(K35)), "=LEFT(INDEX(Profitability_Model!A2:A402,MATCH(LARGE(Profitability_Model!H2:H402,1),Profitability_Model!H2:H402,0)),16)&""..."""), "— toggle Q5=TRUE to reveal —") -> — toggle Q5=TRUE to reveal —
T28: Top SKUs · Category lookup | U28: =IF($Q$5=TRUE(), IFERROR(_xlfn.SINGLE(_xlfn.FORMULATEXT(M35)), "=INDEX(Profitability_Model!B2:B402,MATCH(LARGE(Profitability_Model!H2:H402,1),Profitability_Model!H2:H402,0))"), "— toggle Q5=TRUE to reveal —") -> — toggle Q5=TRUE to reveal —
T29: Top SKUs · Net Profit (LARGE) | U29: =IF($Q$5=TRUE(), IFERROR(_xlfn.SINGLE(_xlfn.FORMULATEXT(O35)), "=LARGE(Profitability_Model!H2:H402,1)"), "— toggle Q5=TRUE to reveal —") -> — toggle Q5=TRUE to reveal —
T30: Top SKUs · Decision lookup | U30: =IF($Q$5=TRUE(), IFERROR(_xlfn.SINGLE(_xlfn.FORMULATEXT(Q35)), "=INDEX(Profitability_Model!L2:L402,MATCH(LARGE(Profitability_Model!H2:H402,1),Profitability_Model!H2:H402,0))"), "— toggle Q5=TRUE to reveal —") -> — toggle Q5=TRUE to reveal —
T31: Scenario · Baseline avg margin | U31: =IF($Q$5=TRUE(), IFERROR(_xlfn.SINGLE(_xlfn.FORMULATEXT(E50)), "=AVERAGE(Scenario_Analysis!D2:D402)"), "— toggle Q5=TRUE to reveal —") -> — toggle Q5=TRUE to reveal —
B32: TOP CATEGORIES BY NET PROFIT | J32: TOP 10 SKUs BY NET PROFIT | T32: Scenario · Scenario A margin | U32: =IF($Q$5=TRUE(), IFERROR(_xlfn.SINGLE(_xlfn.FORMULATEXT(E51)), "=AVERAGE(Scenario_Analysis!G2:G402)"), "— toggle Q5=TRUE to reveal —") -> — toggle Q5=TRUE to reveal —
T33: Scenario · Δ vs Baseline | U33: =IF($Q$5=TRUE(), IFERROR(_xludf.formulatext(F51), "=E51-$E$50"), "— toggle Q5=TRUE to reveal —") -> — toggle Q5=TRUE to reveal —
B34: Rank | C34: Category | E34: SKUs | F34: Revenue | G34: Net Profit | H34: Margin | I34: Profit Share | J34: Rank | K34: Product ID | M34: Category | N34: Revenue | O34: Net Profit | P34: Margin | Q34: Decision | T34: Scenario · SCALE count (A) | U34: =IF($Q$5=TRUE(), IFERROR(_xlfn.SINGLE(_xlfn.FORMULATEXT(G51)), "=COUNTIF(Scenario_Analysis!I2:I402,""SCALE"")"), "— toggle Q5=TRUE to reveal —") -> — toggle Q5=TRUE to reveal —
B35: =RANK(G35,$G$35:$G$44) -> 2 | C35: Health Beauty | E35: =COUNTIF(Profitability_Model!B2:B402,"health_beauty") -> 55 | F35: =SUMIF(Profitability_Model!B2:B402,"health_beauty",Profitability_Model!C2:C402) -> 518756 | G35: =SUMIF(Profitability_Model!B2:B402,"health_beauty",Profitability_Model!H2:H402) -> 225056.18 | H35: =IFERROR(G35/F35,0) -> 0.43383822 | I35: =G35/SUM(Profitability_Model!H2:H402) -> 0.17420241 | J35: 1 | K35: =LEFT(INDEX(Profitability_Model!A2:A402,MATCH(LARGE(Profitability_Model!H2:H402,1),Profitability_Model!H2:H402,0)),16)&"..." -> bb50f2e236e5eea0... | M35: =INDEX(Profitability_Model!B2:B402,MATCH(LARGE(Profitability_Model!H2:H402,1),Profitability_Model!H2:H402,0)) -> health_beauty | N35: =INDEX(Profitability_Model!C2:C402,MATCH(LARGE(Profitability_Model!H2:H402,1),Profitability_Model!H2:H402,0)) -> 63885 | O35: =LARGE(Profitability_Model!H2:H402,1) -> 32319 | P35: =INDEX(Profitability_Model!J2:J402,MATCH(LARGE(Profitability_Model!H2:H402,1),Profitability_Model!H2:H402,0)) -> 0.5058934 | Q35: =INDEX(Profitability_Model!L2:L402,MATCH(LARGE(Profitability_Model!H2:H402,1),Profitability_Model!H2:H402,0)) -> SCALE | T35: Sensitivity · Cell K52 (best) | U35: =IF($Q$5=TRUE(), IFERROR(_xludf.formulatext(K52), "=Sensitivity_Analysis!C5"), "— toggle Q5=TRUE to reveal —") -> — toggle Q5=TRUE to reveal —
B36: =RANK(G36,$G$35:$G$44) -> 1 | C36: Watches Gifts | E36: =COUNTIF(Profitability_Model!B2:B402,"watches_gifts") -> 46 | F36: =SUMIF(Profitability_Model!B2:B402,"watches_gifts",Profitability_Model!C2:C402) -> 487795.98 | G36: =SUMIF(Profitability_Model!B2:B402,"watches_gifts",Profitability_Model!H2:H402) -> 232128.84 | H36: =IFERROR(G36/F36,0) -> 0.4758728 | I36: =G36/SUM(Profitability_Model!H2:H402) -> 0.17967693 | J36: 2 | K36: =LEFT(INDEX(Profitability_Model!A2:A402,MATCH(LARGE(Profitability_Model!H2:H402,2),Profitability_Model!H2:H402,0)),16)&"..." -> 6cdd53843498f928... | M36: =INDEX(Profitability_Model!B2:B402,MATCH(LARGE(Profitability_Model!H2:H402,2),Profitability_Model!H2:H402,0)) -> health_beauty | N36: =INDEX(Profitability_Model!C2:C402,MATCH(LARGE(Profitability_Model!H2:H402,2),Profitability_Model!H2:H402,0)) -> 54730.2 | O36: =LARGE(Profitability_Model!H2:H402,2) -> 26563.57 | P36: =INDEX(Profitability_Model!J2:J402,MATCH(LARGE(Profitability_Model!H2:H402,2),Profitability_Model!H2:H402,0)) -> 0.48535489 | Q36: =INDEX(Profitability_Model!L2:L402,MATCH(LARGE(Profitability_Model!H2:H402,2),Profitability_Model!H2:H402,0)) -> SCALE | T36: Sensitivity · Cell O56 (worst) | U36: =IF($Q$5=TRUE(), IFERROR(_xludf.formulatext(O56), "=Sensitivity_Analysis!G9"), "— toggle Q5=TRUE to reveal —") -> — toggle Q5=TRUE to reveal —
B37: =RANK(G37,$G$35:$G$44) -> 5 | C37: Computers Accessories | E37: =COUNTIF(Profitability_Model!B2:B402,"computers_accessories") -> 34 | F37: =SUMIF(Profitability_Model!B2:B402,"computers_accessories",Profitability_Model!C2:C402) -> 323521.97 | G37: =SUMIF(Profitability_Model!B2:B402,"computers_accessories",Profitability_Model!H2:H402) -> 64623.22 | H37: =IFERROR(G37/F37,0) -> 0.19974909 | I37: =G37/SUM(Profitability_Model!H2:H402) -> 0.050020937 | J37: 3 | K37: =LEFT(INDEX(Profitability_Model!A2:A402,MATCH(LARGE(Profitability_Model!H2:H402,3),Profitability_Model!H2:H402,0)),16)&"..." -> 25c38557cf793876... | M37: =INDEX(Profitability_Model!B2:B402,MATCH(LARGE(Profitability_Model!H2:H402,3),Profitability_Model!H2:H402,0)) -> baby | N37: =INDEX(Profitability_Model!C2:C402,MATCH(LARGE(Profitability_Model!H2:H402,3),Profitability_Model!H2:H402,0)) -> 38907.32 | O37: =LARGE(Profitability_Model!H2:H402,3) -> 20957.94 | P37: =INDEX(Profitability_Model!J2:J402,MATCH(LARGE(Profitability_Model!H2:H402,3),Profitability_Model!H2:H402,0)) -> 0.53866316 | Q37: =INDEX(Profitability_Model!L2:L402,MATCH(LARGE(Profitability_Model!H2:H402,3),Profitability_Model!H2:H402,0)) -> EXIT
B38: =RANK(G38,$G$35:$G$44) -> 3 | C38: Cool Stuff | E38: =COUNTIF(Profitability_Model!B2:B402,"cool_stuff") -> 24 | F38: =SUMIF(Profitability_Model!B2:B402,"cool_stuff",Profitability_Model!C2:C402) -> 232895.88 | G38: =SUMIF(Profitability_Model!B2:B402,"cool_stuff",Profitability_Model!H2:H402) -> 91635.19 | H38: =IFERROR(G38/F38,0) -> 0.3934599 | I38: =G38/SUM(Profitability_Model!H2:H402) -> 0.070929273 | J38: 4 | K38: =LEFT(INDEX(Profitability_Model!A2:A402,MATCH(LARGE(Profitability_Model!H2:H402,4),Profitability_Model!H2:H402,0)),16)&"..." -> d6160fb7873f1840... | M38: =INDEX(Profitability_Model!B2:B402,MATCH(LARGE(Profitability_Model!H2:H402,4),Profitability_Model!H2:H402,0)) -> computers | N38: =INDEX(Profitability_Model!C2:C402,MATCH(LARGE(Profitability_Model!H2:H402,4),Profitability_Model!H2:H402,0)) -> 48899.34 | O38: =LARGE(Profitability_Model!H2:H402,4) -> 19139.63 | P38: =INDEX(Profitability_Model!J2:J402,MATCH(LARGE(Profitability_Model!H2:H402,4),Profitability_Model!H2:H402,0)) -> 0.39140876 | Q38: =INDEX(Profitability_Model!L2:L402,MATCH(LARGE(Profitability_Model!H2:H402,4),Profitability_Model!H2:H402,0)) -> SCALE
B39: =RANK(G39,$G$35:$G$44) -> 6 | C39: Bed Bath Table | E39: =COUNTIF(Profitability_Model!B2:B402,"bed_bath_table") -> 21 | F39: =SUMIF(Profitability_Model!B2:B402,"bed_bath_table",Profitability_Model!C2:C402) -> 206262.36 | G39: =SUMIF(Profitability_Model!B2:B402,"bed_bath_table",Profitability_Model!H2:H402) -> 62380.51 | H39: =IFERROR(G39/F39,0) -> 0.30243283 | I39: =G39/SUM(Profitability_Model!H2:H402) -> 0.04828499 | J39: 5 | K39: =LEFT(INDEX(Profitability_Model!A2:A402,MATCH(LARGE(Profitability_Model!H2:H402,5),Profitability_Model!H2:H402,0)),16)&"..." -> 53b36df67ebb7c41... | M39: =INDEX(Profitability_Model!B2:B402,MATCH(LARGE(Profitability_Model!H2:H402,5),Profitability_Model!H2:H402,0)) -> watches_gifts | N39: =INDEX(Profitability_Model!C2:C402,MATCH(LARGE(Profitability_Model!H2:H402,5),Profitability_Model!H2:H402,0)) -> 37683.42 | O39: =LARGE(Profitability_Model!H2:H402,5) -> 17918.59 | P39: =INDEX(Profitability_Model!J2:J402,MATCH(LARGE(Profitability_Model!H2:H402,5),Profitability_Model!H2:H402,0)) -> 0.47550328 | Q39: =INDEX(Profitability_Model!L2:L402,MATCH(LARGE(Profitability_Model!H2:H402,5),Profitability_Model!H2:H402,0)) -> SCALE | T39: Toggle cell: Q5 (TRUE = show formulas, FALSE = hide)
B40: =RANK(G40,$G$35:$G$44) -> 10 | C40: Garden Tools | E40: =COUNTIF(Profitability_Model!B2:B402,"garden_tools") -> 17 | F40: =SUMIF(Profitability_Model!B2:B402,"garden_tools",Profitability_Model!C2:C402) -> 200454.76 | G40: =SUMIF(Profitability_Model!B2:B402,"garden_tools",Profitability_Model!H2:H402) -> 16743.79 | H40: =IFERROR(G40/F40,0) -> 0.083529022 | I40: =G40/SUM(Profitability_Model!H2:H402) -> 0.012960358 | J40: 6 | K40: =LEFT(INDEX(Profitability_Model!A2:A402,MATCH(LARGE(Profitability_Model!H2:H402,6),Profitability_Model!H2:H402,0)),16)&"..." -> 5f504b3a1c75b73d... | M40: =INDEX(Profitability_Model!B2:B402,MATCH(LARGE(Profitability_Model!H2:H402,6),Profitability_Model!H2:H402,0)) -> cool_stuff | N40: =INDEX(Profitability_Model!C2:C402,MATCH(LARGE(Profitability_Model!H2:H402,6),Profitability_Model!H2:H402,0)) -> 37733.9 | O40: =LARGE(Profitability_Model!H2:H402,6) -> 16424.05 | P40: =INDEX(Profitability_Model!J2:J402,MATCH(LARGE(Profitability_Model!H2:H402,6),Profitability_Model!H2:H402,0)) -> 0.43525981 | Q40: =INDEX(Profitability_Model!L2:L402,MATCH(LARGE(Profitability_Model!H2:H402,6),Profitability_Model!H2:H402,0)) -> SCALE
B41: =RANK(G41,$G$35:$G$44) -> 7 | C41: Sports Leisure | E41: =COUNTIF(Profitability_Model!B2:B402,"sports_leisure") -> 17 | F41: =SUMIF(Profitability_Model!B2:B402,"sports_leisure",Profitability_Model!C2:C402) -> 100674 | G41: =SUMIF(Profitability_Model!B2:B402,"sports_leisure",Profitability_Model!H2:H402) -> 42215.42 | H41: =IFERROR(G41/F41,0) -> 0.41932793 | I41: =G41/SUM(Profitability_Model!H2:H402) -> 0.03267641 | J41: 7 | K41: =LEFT(INDEX(Profitability_Model!A2:A402,MATCH(LARGE(Profitability_Model!H2:H402,7),Profitability_Model!H2:H402,0)),16)&"..." -> d285360f29ac7fd9... | M41: =INDEX(Profitability_Model!B2:B402,MATCH(LARGE(Profitability_Model!H2:H402,7),Profitability_Model!H2:H402,0)) -> watches_gifts | N41: =INDEX(Profitability_Model!C2:C402,MATCH(LARGE(Profitability_Model!H2:H402,7),Profitability_Model!H2:H402,0)) -> 31623.81 | O41: =LARGE(Profitability_Model!H2:H402,7) -> 15702.77 | P41: =INDEX(Profitability_Model!J2:J402,MATCH(LARGE(Profitability_Model!H2:H402,7),Profitability_Model!H2:H402,0)) -> 0.49654896 | Q41: =INDEX(Profitability_Model!L2:L402,MATCH(LARGE(Profitability_Model!H2:H402,7),Profitability_Model!H2:H402,0)) -> OPTIMIZE
B42: =RANK(G42,$G$35:$G$44) -> 4 | C42: Computers | E42: =COUNTIF(Profitability_Model!B2:B402,"computers") -> 15 | F42: =SUMIF(Profitability_Model!B2:B402,"computers",Profitability_Model!C2:C402) -> 195498.64 | G42: =SUMIF(Profitability_Model!B2:B402,"computers",Profitability_Model!H2:H402) -> 73778.76 | H42: =IFERROR(G42/F42,0) -> 0.37738759 | I42: =G42/SUM(Profitability_Model!H2:H402) -> 0.057107688 | J42: 8 | K42: =LEFT(INDEX(Profitability_Model!A2:A402,MATCH(LARGE(Profitability_Model!H2:H402,8),Profitability_Model!H2:H402,0)),16)&"..." -> f819f0c84a64f02d... | M42: =INDEX(Profitability_Model!B2:B402,MATCH(LARGE(Profitability_Model!H2:H402,8),Profitability_Model!H2:H402,0)) -> watches_gifts | N42: =INDEX(Profitability_Model!C2:C402,MATCH(LARGE(Profitability_Model!H2:H402,8),Profitability_Model!H2:H402,0)) -> 29024.48 | O42: =LARGE(Profitability_Model!H2:H402,8) -> 15167.79 | P42: =INDEX(Profitability_Model!J2:J402,MATCH(LARGE(Profitability_Model!H2:H402,8),Profitability_Model!H2:H402,0)) -> 0.52258611 | Q42: =INDEX(Profitability_Model!L2:L402,MATCH(LARGE(Profitability_Model!H2:H402,8),Profitability_Model!H2:H402,0)) -> SCALE
B43: =RANK(G43,$G$35:$G$44) -> 9 | C43: Perfumery | E43: =COUNTIF(Profitability_Model!B2:B402,"perfumery") -> 15 | F43: =SUMIF(Profitability_Model!B2:B402,"perfumery",Profitability_Model!C2:C402) -> 97369.35 | G43: =SUMIF(Profitability_Model!B2:B402,"perfumery",Profitability_Model!H2:H402) -> 38162.52 | H43: =IFERROR(G43/F43,0) -> 0.39193566 | I43: =G43/SUM(Profitability_Model!H2:H402) -> 0.029539305 | J43: 9 | K43: =LEFT(INDEX(Profitability_Model!A2:A402,MATCH(LARGE(Profitability_Model!H2:H402,9),Profitability_Model!H2:H402,0)),16)&"..." -> 7a10781637204d8d... | M43: =INDEX(Profitability_Model!B2:B402,MATCH(LARGE(Profitability_Model!H2:H402,9),Profitability_Model!H2:H402,0)) -> watches_gifts | N43: =INDEX(Profitability_Model!C2:C402,MATCH(LARGE(Profitability_Model!H2:H402,9),Profitability_Model!H2:H402,0)) -> 30467.5 | O43: =LARGE(Profitability_Model!H2:H402,9) -> 14585.43 | P43: =INDEX(Profitability_Model!J2:J402,MATCH(LARGE(Profitability_Model!H2:H402,9),Profitability_Model!H2:H402,0)) -> 0.47872093 | Q43: =INDEX(Profitability_Model!L2:L402,MATCH(LARGE(Profitability_Model!H2:H402,9),Profitability_Model!H2:H402,0)) -> SCALE
B44: =RANK(G44,$G$35:$G$44) -> 8 | C44: Housewares | E44: =COUNTIF(Profitability_Model!B2:B402,"housewares") -> 14 | F44: =SUMIF(Profitability_Model!B2:B402,"housewares",Profitability_Model!C2:C402) -> 111534.72 | G44: =SUMIF(Profitability_Model!B2:B402,"housewares",Profitability_Model!H2:H402) -> 38759.89 | H44: =IFERROR(G44/F44,0) -> 0.34751412 | I44: =G44/SUM(Profitability_Model!H2:H402) -> 0.030001693 | J44: 10 | K44: =LEFT(INDEX(Profitability_Model!A2:A402,MATCH(LARGE(Profitability_Model!H2:H402,10),Profitability_Model!H2:H402,0)),16)&"..." -> e0d64dcfaa3b6db5... | M44: =INDEX(Profitability_Model!B2:B402,MATCH(LARGE(Profitability_Model!H2:H402,10),Profitability_Model!H2:H402,0)) -> watches_gifts | N44: =INDEX(Profitability_Model!C2:C402,MATCH(LARGE(Profitability_Model!H2:H402,10),Profitability_Model!H2:H402,0)) -> 31786.82 | O44: =LARGE(Profitability_Model!H2:H402,10) -> 13839.25 | P44: =INDEX(Profitability_Model!J2:J402,MATCH(LARGE(Profitability_Model!H2:H402,10),Profitability_Model!H2:H402,0)) -> 0.43537699 | Q44: =INDEX(Profitability_Model!L2:L402,MATCH(LARGE(Profitability_Model!H2:H402,10),Profitability_Model!H2:H402,0)) -> OPTIMIZE
B45: TOP 10 SUBTOTAL | E45: =SUM(E35:E44) -> 258 | F45: =SUM(F35:F44) -> 2474763.7 | G45: =SUM(G35:G44) -> 885484.32 | H45: =IFERROR(G45/F45,0) -> 0.35780561 | I45: =G45/SUM(Profitability_Model!H2:H402) -> 0.6854
B47: SCENARIO STRESS TEST — Margin Resilience | J47: SENSITIVITY HEATMAP — Portfolio Avg Net Margin
B49: Scenario | C49: Description | E49: Avg Margin | F49: Δ vs Base | G49: SCALE | H49: OPTIMIZE | I49: EXIT | J49: Avg portfolio net margin under combined COGS uplift × Return-rate uplift
B50: Baseline | C50: Current state — actual data | E50: =AVERAGE(Scenario_Analysis!D2:D402) -> 0.36744704 | F50: — | G50: =COUNTIF(Scenario_Analysis!E2:E402,"SCALE") -> 216 | H50: =COUNTIF(Scenario_Analysis!E2:E402,"OPTIMIZE") -> 138 | I50: =COUNTIF(Scenario_Analysis!E2:E402,"EXIT") -> 46 | K50: COGS uplift →
B51: Scenario A | C51: COGS uplift +10% — supplier cost shock | E51: =AVERAGE(Scenario_Analysis!G2:G402) -> 0.32093453 | F51: =E51-$E$50 -> -0.046512504 | G51: =COUNTIF(Scenario_Analysis!I2:I402,"SCALE") -> 198 | H51: =COUNTIF(Scenario_Analysis!I2:I402,"OPTIMIZE") -> 146 | I51: =COUNTIF(Scenario_Analysis!I2:I402,"EXIT") -> 56 | J51: Return Δ ↓ | K51: 0 | L51: 0.05 | M51: 0.1 | N51: 0.15 | O51: 0.2
B52: Scenario B | C52: Return-rate uplift — quality / logistics | E52: =AVERAGE(Scenario_Analysis!K2:K402) -> 0.36516903 | F52: =E52-$E$50 -> -0.0022780085 | G52: =COUNTIF(Scenario_Analysis!M2:M402,"SCALE") -> 215 | H52: =COUNTIF(Scenario_Analysis!M2:M402,"OPTIMIZE") -> 136 | I52: =COUNTIF(Scenario_Analysis!M2:M402,"EXIT") -> 49 | J52: 0 | K52: =Sensitivity_Analysis!C5 -> 0.35980985 | L52: =Sensitivity_Analysis!D5 -> 0.33648742 | M52: =Sensitivity_Analysis!E5 -> 0.313165 | N52: =Sensitivity_Analysis!F5 -> 0.28984257 | O52: =Sensitivity_Analysis!G5 -> 0.26652015
B53: Scenario C | C53: Combined COGS + Returns stress | E53: =AVERAGE(Scenario_Analysis!O2:O402) -> 0.33415477 | F53: =E53-$E$50 -> -0.033292261 | G53: =COUNTIF(Scenario_Analysis!Q2:Q402,"SCALE") -> 204 | H53: =COUNTIF(Scenario_Analysis!Q2:Q402,"OPTIMIZE") -> 141 | I53: =COUNTIF(Scenario_Analysis!Q2:Q402,"EXIT") -> 55 | J53: 0.025 | K53: =Sensitivity_Analysis!C6 -> 0.35860992 | L53: =Sensitivity_Analysis!D6 -> 0.3352875 | M53: =Sensitivity_Analysis!E6 -> 0.31196507 | N53: =Sensitivity_Analysis!F6 -> 0.28864265 | O53: =Sensitivity_Analysis!G6 -> 0.26532022
J54: 0.05 | K54: =Sensitivity_Analysis!C7 -> 0.35741 | L54: =Sensitivity_Analysis!D7 -> 0.33408757 | M54: =Sensitivity_Analysis!E7 -> 0.31076515 | N54: =Sensitivity_Analysis!F7 -> 0.28744272 | O54: =Sensitivity_Analysis!G7 -> 0.2641203
J55: 0.075 | K55: =Sensitivity_Analysis!C8 -> 0.35621007 | L55: =Sensitivity_Analysis!D8 -> 0.33288765 | M55: =Sensitivity_Analysis!E8 -> 0.30956522 | N55: =Sensitivity_Analysis!F8 -> 0.2862428 | O55: =Sensitivity_Analysis!G8 -> 0.26292037
J56: 0.1 | K56: =Sensitivity_Analysis!C9 -> 0.35501015 | L56: =Sensitivity_Analysis!D9 -> 0.33168772 | M56: =Sensitivity_Analysis!E9 -> 0.3083653 | N56: =Sensitivity_Analysis!F9 -> 0.28504287 | O56: =Sensitivity_Analysis!G9 -> 0.26172045
J58: Best ● ████████████ ● Worst (cell color = relative margin health)
J59: ⚡ RISK SUMMARY
J60: ="• Best case (no stress): "&TEXT(K52,"0.0%")&" portfolio avg net margin" -> • Best case (no stress): 36.0% portfolio avg net margin
J61: ="• Worst case (COGS +20%, Returns +10%): "&TEXT(O56,"0.0%")&" margin" -> • Worst case (COGS +20%, Returns +10%): 26.2% margin
J62: ="• Margin compression range: "&TEXT(K52-O56,"0.0%")&" pp from best to worst case" -> • Margin compression range: 9.8% pp from best to worst case
J63: ="• COGS is the dominant risk: +20% COGS reduces margin by "&TEXT(K52-O52,"0.0%")&" pp" -> • COGS is the dominant risk: +20% COGS reduces margin by 9.3% pp
J64: ="• Returns sensitivity is mild: +10% returns reduces margin only "&TEXT(K52-K56,"0.0%")&" pp" -> • Returns sensitivity is mild: +10% returns reduces margin only 0.5% pp
J65: ="• Portfolio remains profitable in ALL "&COUNTIF(K52:O56,">0")&" of 25 stress combinations" -> • Portfolio remains profitable in ALL 25 of 25 stress combinations
B66: 💡 SCENARIO INSIGHTS | J66: 🎯 STRATEGIC RECOMMENDATION
B67: ="• Scenario A (COGS +10%) is the most damaging — margin drops by "&TEXT($E$50-$E$51,"0.0%")&" pp" -> • Scenario A (COGS +10%) is the most damaging — margin drops by 4.7% pp | J67: ="• Aggressively SCALE the "&COUNTIF(Profitability_Model!L2:L402,"SCALE")&" high-performing SKUs (54% of portfolio)" -> • Aggressively SCALE the 216 high-performing SKUs (54% of portfolio)
B68: ="• Scenario B (returns) has the smallest impact — "&TEXT($E$50-$E$52,"0.0%")&" pp margin drop" -> • Scenario B (returns) has the smallest impact — 0.2% pp margin drop | J68: ="• Initiate EXIT plans for "&COUNTIF(Profitability_Model!L2:L402,"EXIT")&" loss-makers — recover R$ "&TEXT(-SUMIFS(Profitability_Model!H2:H402,Profitability_Model!L2:L402,"EXIT",Profitability_Model!H2:H402,"<0"),"#,##0")&" in losses" -> • Initiate EXIT plans for 46 loss-makers — recover R$ 4,888 in losses
B69: ="• Under worst-case A, EXIT SKUs rise from "&$I$50&" to "&$I$51&" (+"&($I$51-$I$50)&")" -> • Under worst-case A, EXIT SKUs rise from 46 to 56 (+10) | J69: ="• Renegotiate supplier contracts — top risk factor is COGS volatility" -> • Renegotiate supplier contracts — top risk factor is COGS volatility
B70: ="• "&COUNTIF(Scenario_Analysis!R2:R402,"Stable")&" of 400 SKUs remain stable across all 3 scenarios ("&TEXT(COUNTIF(Scenario_Analysis!R2:R402,"Stable")/400,"0.0%")&")" -> • 372 of 400 SKUs remain stable across all 3 scenarios (93.0%) | J70: ="• Monitor "&COUNTIF(Scenario_Analysis!R2:R402,"Decision changes")&" sensitive SKUs that flip categories under stress" -> • Monitor 28 sensitive SKUs that flip categories under stress
B71: ="• Portfolio retains "&TEXT(MIN(E51:E53)/E50,"0.0%")&" of baseline margin in worst case — resilient model" -> • Portfolio retains 87.3% of baseline margin in worst case — resilient model | J71: ="• Focus optimization on top 10 categories — they drive "&TEXT($I$45,"0.0%")&" of total profit" -> • Focus optimization on top 10 categories — they drive 68.5% of total profit
B75: 🎛 INTERACTIVE FILTERS · Dashboard responds to your selections below
B76: CATEGORY | E76: DECISION | H76: SCENARIO
B77: All | E77: OPTIMIZE | H77: Scenario C — Combined
B79: 📊 LIVE FILTERED SNAPSHOT · recalculates from the slicers above
B80: FILTERED SKUs | E80: REVENUE | H80: NET PROFIT | K80: AVG NET MARGIN | N80: % OF PORTFOLIO | AA80: All | AB80: All | AC80: Baseline
B81: =COUNTIFS(Profitability_Model!$B$2:$B$402,IF(Dashboard!$B$77="All","*",Dashboard!$B$77),Profitability_Model!$L$2:$L$402,IF(Dashboard!$E$77="All","*",Dashboard!$E$77)) -> 138 | E81: =SUMIFS(Profitability_Model!$C$2:$C$402,Profitability_Model!$B$2:$B$402,IF(Dashboard!$B$77="All","*",Dashboard!$B$77),Profitability_Model!$L$2:$L$402,IF(Dashboard!$E$77="All","*",Dashboard!$E$77)) -> 1196906.3 | H81: =CHOOSE(MATCH(Dashboard!$H$77,{"Baseline","Scenario A — COGS +10%","Scenario B — Returns +pp","Scenario C — Combined"},0),SUMIFS(Profitability_Model!$H$2:$H$401,Profitability_Model!$B$2:$B$401,IF(Dashboard!$B$77="All","*",Dashboard!$B$77),Profitability_Model!$L$2:$L$401,IF(Dashboard!$E$77="All","*",Dashboard!$E$77)),SUMIFS(Scenario_Analysis!$F$3:$F$402,Scenario_Analysis!$B$3:$B$402,IF(Dashboard!$B$77="All","*",Dashboard!$B$77),Profitability_Model!$L$2:$L$401,IF(Dashboard!$E$77="All","*",Dashboard!$E$77)),SUMIFS(Scenario_Analysis!$J$3:$J$402,Scenario_Analysis!$B$3:$B$402,IF(Dashboard!$B$77="All","*",Dashboard!$B$77),Profitability_Model!$L$2:$L$401,IF(Dashboard!$E$77="All","*",Dashboard!$E$77)),SUMIFS(Scenario_Analysis!$N$3:$N$402,Scenario_Analysis!$B$3:$B$402,IF(Dashboard!$B$77="All","*",Dashboard!$B$77),Profitability_Model!$L$2:$L$401,IF(Dashboard!$E$77="All","*",Dashboard!$E$77))) -> 367477.32 | K81: =IFERROR(CHOOSE(MATCH(Dashboard!$H$77,{"Baseline","Scenario A — COGS +10%","Scenario B — Returns +pp","Scenario C — Combined"},0),AVERAGEIFS(Profitability_Model!$J$2:$J$401,Profitability_Model!$B$2:$B$401,IF(Dashboard!$B$77="All","*",Dashboard!$B$77),Profitability_Model!$L$2:$L$401,IF(Dashboard!$E$77="All","*",Dashboard!$E$77)),AVERAGEIFS(Scenario_Analysis!$G$3:$G$402,Scenario_Analysis!$B$3:$B$402,IF(Dashboard!$B$77="All","*",Dashboard!$B$77),Profitability_Model!$L$2:$L$401,IF(Dashboard!$E$77="All","*",Dashboard!$E$77)),AVERAGEIFS(Scenario_Analysis!$K$3:$K$402,Scenario_Analysis!$B$3:$B$402,IF(Dashboard!$B$77="All","*",Dashboard!$B$77),Profitability_Model!$L$2:$L$401,IF(Dashboard!$E$77="All","*",Dashboard!$E$77)),AVERAGEIFS(Scenario_Analysis!$O$3:$O$402,Scenario_Analysis!$B$3:$B$402,IF(Dashboard!$B$77="All","*",Dashboard!$B$77),Profitability_Model!$L$2:$L$401,IF(Dashboard!$E$77="All","*",Dashboard!$E$77))),0) -> 0.33101361 | N81: =IFERROR(SUMIFS(Profitability_Model!$C$2:$C$402,Profitability_Model!$B$2:$B$402,IF(Dashboard!$B$77="All","*",Dashboard!$B$77),Profitability_Model!$L$2:$L$402,IF(Dashboard!$E$77="All","*",Dashboard!$E$77))/SUM(Profitability_Model!$C$2:$C$402),0) -> 0.3333469 | AA81: agro_industry_and_commerce | AB81: SCALE | AC81: Scenario A — COGS +10%
B82: SKU Profitability Dashboard · All metrics calculated live via formulas from source tabs · Toggle Q5 = TRUE to view formulas in column S | AA82: art | AB82: OPTIMIZE | AC82: Scenario B — Returns +pp
B83: =" Generated "&TEXT(TODAY(),"mmmm d, yyyy")&" · Data source: Profitability_Model · Scenario_Analysis · Sensitivity_Analysis" -> Generated June 10, 2026 · Data source: Profitability_Model · Scenario_Analysis · Sensitivity_Analysis | AA83: audio | AB83: EXIT | AC83: Scenario C — Combined
AA84: auto
AA85: baby
AA86: bed_bath_table
AA87: books_general_interest
AA88: computers
AA89: computers_accessories
AA90: consoles_games
AA91: construction_tools_construction
AA92: construction_tools_lights

Sheet Decision_Logic
B2: SKU DECISION LOGIC | CLASSIFICATION FRAMEWORK
B3: How every SKU is classified into SCALE / OPTIMIZE / EXIT — thresholds, quality gate, decision order & stability rule
B5: 1 · CLASSIFICATION RULES
B6: Decision | C6: What it means | D6: Net margin condition | E6: Review score condition | F6: Strategic intent
B7: ● SCALE | C7: Strong, well-reviewed performers worth backing | D7: ≥ 25% | E7: ≥ 4.0 | F7: Invest & grow — protect supply, push volume
B8: ● OPTIMIZE | C8: Viable, but short of both SCALE gates — margin or quality to lift | D8: ≥ 10% | E8: ≥ 3.0 | F8: Fix & improve — cost, pricing or quality levers
B9: ● EXIT | C9: Unprofitable or poorly rated — value-destroying | D9: < 10% | E9: < 3.0 | F9: Discontinue / restructure — recover capital
B11: SCALE needs BOTH gates (margin ≥ 25% and review ≥ 4.0). Failing either one caps a SKU at OPTIMIZE; breaching either floor (margin < 10% or review < 3.0) forces EXIT.
B13: 2 · MARGIN THRESHOLDS
B14: Band | C14: Net margin range | D14: Health | E14: Maps to
B15: Healthy | C15: ≥ 25.0% | D15: Green | E15: SCALE
B16: Caution | C16: 10.0% – 24.9% | D16: Amber | E16: OPTIMIZE
B17: Critical | C17: < 10.0% | D17: Red | E17: EXIT
B19: Net margin = net profit ÷ gross revenue, after returns, COGS and all operating costs (storage, fulfilment, freight).
B21: 3 · QUALITY GATE · average review score
B22: Review score | C22: Effect on classification
B23: ≥ 4.0 | C23: Required for SCALE — signals durable customer satisfaction
B24: 3.0 – 3.9 | C24: Caps a SKU at OPTIMIZE even if margins are strong
B25: < 3.0 | C25: Forces EXIT regardless of margin — reputational / returns risk
B27: 4 · DECISION RULE · evaluation order
B28: Step 1 | C28: IF net margin < 10% OR review < 3.0 → EXIT
B29: Step 2 | C29: ELSE IF net margin ≥ 25% AND review ≥ 4.0 → SCALE
B30: Step 3 | C30: ELSE → OPTIMIZE
B31: Excel implementation (per SKU, applied in Scenario_Analysis cols I / M / Q and upstream in the SQL pipeline):
B32: =IF(OR(net_margin<0.1, review<3),"EXIT", IF(AND(net_margin>=0.25, review>=4),"SCALE","OPTIMIZE"))
B34: 5 · STABILITY RULE · resilience under stress
B35: Flag | C35: Definition | F35: Live count
B36: Stable | C36: Decision is identical across Baseline + Scenarios A, B and C | F36: =COUNTIF(Scenario_Analysis!R3:R402,"Stable") -> 372
B37: Decision changes | C37: At least one scenario flips the SKU into a different category → monitor | F37: =COUNTIF(Scenario_Analysis!R2:R402,"Decision changes") -> 28
B38: Stability rate | C38: Share of the 400-SKU portfolio whose decision never changes under stress | F38: =COUNTIF(Scenario_Analysis!R2:R402,"Stable")/400 -> 0.93
B41: Logic applied consistently across Profitability_Model, Scenario_Analysis and the Dashboard. · Thresholds are the single source of truth for all SCALE / OPTIMIZE / EXIT labels in this workbook.

Sheet Risk_Summary
B2: EXECUTIVE RISK SUMMARY | MARGIN STRESS & KEY DRIVERS
B3: Portfolio-average net margin under stress — best case, worst case, compression and the drivers behind it
B5: BEST-CASE MARGIN | E5: WORST-CASE MARGIN | H5: MARGIN COMPRESSION
B6: =MAX(Sensitivity_Analysis!C5:G9) -> 0.35980985 | E6: =MIN(Sensitivity_Analysis!C5:G9) -> 0.26172045 | H6: =Sensitivity_Analysis!C5-Sensitivity_Analysis!G9 -> 0.098089403
B7: No stress applied (current state) | E7: COGS +20% · Returns +10% | H7: Peak-to-trough, percentage points
B9: MARGIN UNDER STRESS
B10: Case | C10: Stress applied | F10: Avg net margin | H10: Δ vs best case
B11: Best case | C11: No stress — actual portfolio | F11: =Sensitivity_Analysis!C5 -> 0.35980985 | H11: —
B12: COGS shock | C12: Cost of goods +20% (returns held) | F12: =Sensitivity_Analysis!G5 -> 0.26652015 | H12: =Sensitivity_Analysis!G5-Sensitivity_Analysis!C5 -> -0.093289701
B13: Returns shock | C13: Return rate +10pp (COGS held) | F13: =Sensitivity_Analysis!C9 -> 0.35501015 | H13: =Sensitivity_Analysis!C9-Sensitivity_Analysis!C5 -> -0.0047997023
B14: Worst case | C14: COGS +20% & Returns +10pp combined | F14: =Sensitivity_Analysis!G9 -> 0.26172045 | H14: =Sensitivity_Analysis!G9-Sensitivity_Analysis!C5 -> -0.098089403
B17: KEY RISK DRIVERS
B18: COGS · primary driver | F18: RETURNS · secondary driver
B19: =Sensitivity_Analysis!C5-Sensitivity_Analysis!G5 -> 0.093289701 | D19: margin lost at COGS +20% | F19: =Sensitivity_Analysis!C5-Sensitivity_Analysis!C9 -> 0.0047997023 | H19: margin lost at Returns +10pp
B20: =" COGS sensitivity is "&TEXT(IFERROR((Sensitivity_Analysis!C5-Sensitivity_Analysis!G5)/(Sensitivity_Analysis!C5-Sensitivity_Analysis!C9),0),"0.0")&"× the returns impact — supplier-cost volatility is the single largest threat to portfolio margin." -> COGS sensitivity is 19.4× the returns impact — supplier-cost volatility is the single largest threat to portfolio margin.
B22: RESILIENCE & WATCH-LIST
B23: =" • Portfolio stays profitable in all "&COUNTIF(Sensitivity_Analysis!C5:G9,">0")&" of 25 stress combinations tested." -> • Portfolio stays profitable in all 25 of 25 stress combinations tested.
B24: =" • Worst case retains "&TEXT(Sensitivity_Analysis!G9/Sensitivity_Analysis!C5,"0.0%")&" of best-case margin — the book is resilient, not fragile." -> • Worst case retains 72.7% of best-case margin — the book is resilient, not fragile.
B25: =" • "&COUNTIF(Scenario_Analysis!R2:R402,"Stable")&" of 400 SKUs keep their decision under every scenario ("&TEXT(COUNTIF(Scenario_Analysis!R2:R402,"Stable")/400,"0.0%")&" stability)." -> • 372 of 400 SKUs keep their decision under every scenario (93.0% stability).
B26: =" • "&COUNTIF(Scenario_Analysis!R2:R402,"Decision changes")&" sensitive SKUs flip category under stress and need active monitoring." -> • 28 sensitive SKUs flip category under stress and need active monitoring.
B27: =" • Mitigation priority: lock supplier pricing on SCALE SKUs first — that is where COGS risk concentrates." -> • Mitigation priority: lock supplier pricing on SCALE SKUs first — that is where COGS risk concentrates.

Sheet Framework_Value
B2: FRAMEWORK VALUE | BEFORE vs AFTER
B3: What this decision-support model adds over a traditional SME spreadsheet review
B5: CAPABILITY COMPARISON
B6: Capability | C6: Traditional SME analysis (before) | D6: This framework (after) | E6: Value added
B7: SKU Visibility | C7: Revenue-only ranking; costs pooled, true per-SKU profit unknown | D7: Full per-SKU P&L across all 400 SKUs — COGS, storage, fulfilment, freight & returns isolated | E7: Every SKU sized on real net profit, not just sales
B8: Profitability Analysis | C8: Gross margin guesswork; loss-makers hidden inside category averages | D8: Net margin, gross margin & break-even price computed live per SKU | E8: Loss-makers surfaced individually and ranked
B9: Scenario Modeling | C9: None — single static view, no "what-if" capability | D9: 3 independent stress scenarios (COGS, returns, price) recomputed per SKU | E9: Forward-looking; impact quantified before it happens
B10: Risk Monitoring | C10: Reactive — problems noticed only after margin erodes | D10: 5×5 sensitivity grid + best/worst-case margin & driver attribution | E10: Risk quantified and ranked ahead of time
B11: Decision Support | C11: Subjective calls; inconsistent and hard to defend | D11: Rule-based SCALE / OPTIMIZE / EXIT labels with stability flags | E11: Consistent, auditable, board-ready decisions
B13: WHAT THE FRAMEWORK DELIVERS TODAY
B14: SKUs ANALYSED | C14: CLASSIFIED SCALE / OPT / EXIT | D14: STRESS COMBINATIONS TESTED | E14: DECISION STABILITY RATE
B15: =COUNTIF(Profitability_Model!L3:L402,"<>") -> 400 | C15: =COUNTIF(Profitability_Model!L3:L402,"SCALE")&" / "&COUNTIF(Profitability_Model!L3:L402,"OPTIMIZE")&" / "&COUNTIF(Profitability_Model!L3:L402,"EXIT") -> 216 / 138 / 46 | D15: =COUNT(Sensitivity_Analysis!C5:G9) -> 25 | E15: =COUNTIF(Scenario_Analysis!R3:R402,"Stable")/400 -> 0.93
B17: Before → after: from a revenue list with no risk lens, to a per-SKU, stress-tested, rule-based decision engine covering all 400 SKUs.
